Workbook

Sheet Sheet1
A1: company | B1: Наименование | C1: year | D1: Дивиденд | E1: industry | F1: sum | G1: peer_sum | H1: payout | I1: payout_ratio | J1: abs | K1: pabs | L1: inc | M1: inc_ratio | N1: dec | O1: dec_ratio | P1: Size | Q1: Tangibility | R1: Sales_growth | S1: REBE | T1: ROA | U1: Leverage | V1: Psize | W1: PTangibility | X1: PSales_growth | Y1: PREBE | Z1: PROA | AA1: PLeverage
A2: GAZP | B2: =A2&" "& "IV" &" кв. "&C2 -> GAZP IV кв. 2025 | C2: 2025 | D2: =SUMIFS(Дивиденды!$C:$C,Дивиденды!$A:$A,A2,Дивиденды!$I:$I,C2) -> 0 | E2: 1 | F2: =D2 -> 0 | G2: =AVERAGEIFS($D:$D,$E:$E,E2,$C:$C,C2,$A:$A,"<>"&A2) -> 77.756667 | H2: =IF(D2>0,1,0) -> 0 | I2: =IFERROR((COUNTIFS($E:$E,E2,$C:$C,C2,$H:$H,1)-H2)/(COUNTIFS($E:$E,E2,$C:$C,C2)-1),0) -> 0.66666667 | J2: =IF(A3<>A2,"",IF(D2=D3,0,IF(AND(D3=0,D2<>0), 1,(D2-D3)/D3))) -> 0 | K2: =IFERROR(AVERAGEIFS($J:$J,$E:$E,E2,$C:$C,C2,$A:$A,"<>"&A2),"") -> -0.62296625 | L2: =IF(J2<>"",IF(J2>0,1,0),"") -> 0 | M2: =IFERROR(AVERAGEIFS($L:$L,$E:$E,E2,$C:$C,C2,$A:$A,"<>"&A2),"") -> 0 | N2: =IF(J2<>"",IF(J2<0,1,0),"") -> 0 | O2: =IFERROR(AVERAGEIFS($N:$N,$E:$E,E2,$C:$C,C2,$A:$A,"<>"&A2),"") -> 0.83333333 | P2: =IFERROR(LN('Дивиденды по годам'!I2),"") | Q2: =IFERROR('Дивиденды по годам'!G2/'Дивиденды по годам'!I2, "") | R2: =IFERROR(IF(AND('Дивиденды по годам'!N2<>"",'Дивиденды по годам'!U2<>"",'Дивиденды по годам'!U2<>0),'Дивиденды по годам'!N2/'Дивиденды по годам'!U2-1,""),"") | S2: =IFERROR(IF(AND('Дивиденды по годам'!L2<>"",'Дивиденды по годам'!I2<>"",'Дивиденды по годам'!J2<>"",'Дивиденды по годам'!K2<>"",('Дивиденды по годам'!I2-'Дивиденды по годам'!J2-'Дивиденды по годам'!K2)<>0),'Дивиденды по годам'!L2/('Дивиденды по годам'!I2-'Дивиденды по годам'!J2-'Дивиденды по годам'!K2),""),"") | T2: =IFERROR(IF(AND('Дивиденды по годам'!Q2<>"",'Дивиденды по годам'!I2<>"",'Дивиденды по годам'!V2<>"",('Дивиденды по годам'!I2+'Дивиденды по годам'!V2)<>0),'Дивиденды по годам'!Q2/(('Дивиденды по годам'!I2+'Дивиденды по годам'!V2)/2),""),"") | U2: =IFERROR(IF(AND('Дивиденды по годам'!J2<>"",'Дивиденды по годам'!K2<>"",'Дивиденды по годам'!M2<>"",'Дивиденды по годам'!M2<>0),('Дивиденды по годам'!J2+'Дивиденды по годам'!K2)/'Дивиденды по годам'!M2,""),"") | V2: {=IFERROR(AVERAGE(_xlfn._xlws.FILTER(P$2:P$1073,($C$2:$C$1073=$C2)*($E$2:$E$1073=$E2)*(ROW(P$2:P$1073)<>ROW(P2))*(P$2:P$1073<>""))),"")} -> 28.307188 | W2: {=IFERROR(AVERAGE(_xlfn._xlws.FILTER(Q$2:Q$1073,($C$2:$C$1073=$C2)*($E$2:$E$1073=$E2)*(ROW(Q$2:Q$1073)<>ROW(Q2))*(Q$2:Q$1073<>""))),"")} -> 0.53419344 | X2: {=IFERROR(AVERAGE(_xlfn._xlws.FILTER(R$2:R$1073,($C$2:$C$1073=$C2)*($E$2:$E$1073=$E2)*(ROW(R$2:R$1073)<>ROW(R2))*(R$2:R$1073<>""))),"")} -> -0.25128972 | Y2: {=IFERROR(AVERAGE(_xlfn._xlws.FILTER(S$2:S$1073,($C$2:$C$1073=$C2)*($E$2:$E$1073=$E2)*(ROW(S$2:S$1073)<>ROW(S2))*(S$2:S$1073<>""))),"")} -> 0.71039154 | Z2: {=IFERROR(AVERAGE(_xlfn._xlws.FILTER(T$2:T$1073,($C$2:$C$1073=$C2)*($E$2:$E$1073=$E2)*(ROW(T$2:T$1073)<>ROW(T2))*(T$2:T$1073<>""))),"")} -> 0.011099136 | AA2: {=IFERROR(AVERAGE(_xlfn._xlws.FILTER(U$2:U$1073,($C$2:$C$1073=$C2)*($E$2:$E$1073=$E2)*(ROW(U$2:U$1073)<>ROW(U2))*(U$2:U$1073<>""))),"")} -> 0.71283761
A3: GAZP | B3: =A3&" "& "IV" &" кв. "&C3 -> GAZP IV кв. 2024 | C3: 2024 | D3: =SUMIFS(Дивиденды!$C:$C,Дивиденды!$A:$A,A3,Дивиденды!$I:$I,C3) -> 0 | E3: 1 | F3: =D3 -> 0 | G3: =AVERAGEIFS($D:$D,$E:$E,E3,$C:$C,C3,$A:$A,"<>"&A3) -> 214.65 | H3: =IF(D3>0,1,0) -> 0 | I3: =IFERROR((COUNTIFS($E:$E,E3,$C:$C,C3,$H:$H,1)-H3)/(COUNTIFS($E:$E,E3,$C:$C,C3)-1),0) -> 0.83333333 | J3: =IF(A4<>A3,"",IF(D3=D4,0,IF(AND(D4=0,D3<>0), 1,(D3-D4)/D4))) -> 0 | K3: =IFERROR(AVERAGEIFS($J:$J,$E:$E,E3,$C:$C,C3,$A:$A,"<>"&A3),"") -> 0.033213968 | L3: =IF(J3<>"",IF(J3>0,1,0),"") -> 0 | M3: =IFERROR(AVERAGEIFS($L:$L,$E:$E,E3,$C:$C,C3,$A:$A,"<>"&A3),"") -> 0.66666667 | N3: =IF(J3<>"",IF(J3<0,1,0),"") -> 0 | O3: =IFERROR(AVERAGEIFS($N:$N,$E:$E,E3,$C:$C,C3,$A:$A,"<>"&A3),"") -> 0.16666667 | P3: =IFERROR(LN('Дивиденды по годам'!I3),"") -> 31.055227 | Q3: =IFERROR('Дивиденды по годам'!G3/'Дивиденды по годам'!I3, "") -> 0.67690981 | R3: =IFERROR(IF(AND('Дивиденды по годам'!N3<>"",'Дивиденды по годам'!U3<>"",'Дивиденды по годам'!U3<>0),'Дивиденды по годам'!N3/'Дивиденды по годам'!U3-1,""),"") -> 0.25438004 | S3: =IFERROR(IF(AND('Дивиденды по годам'!L3<>"",'Дивиденды по годам'!I3<>"",'Дивиденды по годам'!J3<>"",'Дивиденды по годам'!K3<>"",('Дивиденды по годам'!I3-'Дивиденды по годам'!J3-'Дивиденды по годам'!K3)<>0),'Дивиденды по годам'!L3/('Дивиденды по годам'!I3-'Дивиденды по годам'!J3-'Дивиденды по годам'!K3),""),"") -> 0.88491057 | T3: =IFERROR(IF(AND('Дивиденды по годам'!Q3<>"",'Дивиденды по годам'!I3<>"",'Дивиденды по годам'!V3<>"",('Дивиденды по годам'!I3+'Дивиденды по годам'!V3)<>0),'Дивиденды по годам'!Q3/(('Дивиденды по годам'!I3+'Дивиденды по годам'!V3)/2),""),"") -> 0.04439204 | U3: =IFERROR(IF(AND('Дивиденды по годам'!J3<>"",'Дивиденды по годам'!K3<>"",'Дивиденды по годам'!M3<>"",'Дивиденды по годам'!M3<>0),('Дивиденды по годам'!J3+'Дивиденды по годам'!K3)/'Дивиденды по годам'!M3,""),"") -> 0.73819835 | V3: {=IFERROR(AVERAGE(_xlfn._xlws.FILTER(P$2:P$1073,($C$2:$C$1073=$C3)*($E$2:$E$1073=$E3)*(ROW(P$2:P$1073)<>ROW(P3))*(P$2:P$1073<>""))),"")} -> 28.89571 | W3: {=IFERROR(AVERAGE(_xlfn._xlws.FILTER(Q$2:Q$1073,($C$2:$C$1073=$C3)*($E$2:$E$1073=$E3)*(ROW(Q$2:Q$1073)<>ROW(Q3))*(Q$2:Q$1073<>""))),"")} -> 0.51199198 | X3: {=IFERROR(AVERAGE(_xlfn._xlws.FILTER(R$2:R$1073,($C$2:$C$1073=$C3)*($E$2:$E$1073=$E3)*(ROW(R$2:R$1073)<>ROW(R3))*(R$2:R$1073<>""))),"")} -> 0.17118061 | Y3: {=IFERROR(AVERAGE(_xlfn._xlws.FILTER(S$2:S$1073,($C$2:$C$1073=$C3)*($E$2:$E$1073=$E3)*(ROW(S$2:S$1073)<>ROW(S3))*(S$2:S$1073<>""))),"")} -> 0.79852548 | Z3: {=IFERROR(AVERAGE(_xlfn._xlws.FILTER(T$2:T$1073,($C$2:$C$1073=$C3)*($E$2:$E$1073=$E3)*(ROW(T$2:T$1073)<>ROW(T3))*(T$2:T$1073<>""))),"")} -> 0.12177692 | AA3: {=IFERROR(AVERAGE(_xlfn._xlws.FILTER(U$2:U$1073,($C$2:$C$1073=$C3)*($E$2:$E$1073=$E3)*(ROW(U$2:U$1073)<>ROW(U3))*(U$2:U$1073<>""))),"")} -> 0.85190113
A4: GAZP | B4: =A4&" "& "IV" &" кв. "&C4 -> GAZP IV кв. 2023 | C4: 2023 | D4: =SUMIFS(Дивиденды!$C:$C,Дивиденды!$A:$A,A4,Дивиденды!$I:$I,C4) -> 0 | E4: 1 | F4: =D4 -> 0 | G4: =AVERAGEIFS($D:$D,$E:$E,E4,$C:$C,C4,$A:$A,"<>"&A4) -> 195.35 | H4: =IF(D4>0,1,0) -> 0 | I4: =IFERROR((COUNTIFS($E:$E,E4,$C:$C,C4,$H:$H,1)-H4)/(COUNTIFS($E:$E,E4,$C:$C,C4)-1),0) -> 0.83333333 | J4: =IF(A5<>A4,"",IF(D4=D5,0,IF(AND(D5=0,D4<>0), 1,(D4-D5)/D5))) -> -1 | K4: =IFERROR(AVERAGEIFS($J:$J,$E:$E,E4,$C:$C,C4,$A:$A,"<>"&A4),"") -> 0.07318505 | L4: =IF(J4<>"",IF(J4>0,1,0),"") -> 0 | M4: =IFERROR(AVERAGEIFS($L:$L,$E:$E,E4,$C:$C,C4,$A:$A,"<>"&A4),"") -> 0.5 | N4: =IF(J4<>"",IF(J4<0,1,0),"") -> 1 | O4: =IFERROR(AVERAGEIFS($N:$N,$E:$E,E4,$C:$C,C4,$A:$A,"<>"&A4),"") -> 0.33333333 | P4: =IFERROR(LN('Дивиденды по годам'!I4),"") -> 30.988397 | Q4: =IFERROR('Дивиденды по годам'!G4/'Дивиденды по годам'!I4, "") -> 0.64206898 | R4: =IFERROR(IF(AND('Дивиденды по годам'!N4<>"",'Дивиденды по годам'!U4<>"",'Дивиденды по годам'!U4<>0),'Дивиденды по годам'!N4/'Дивиденды по годам'!U4-1,""),"") -> -0.26830096 | S4: =IFERROR(IF(AND('Дивиденды по годам'!L4<>"",'Дивиденды по годам'!I4<>"",'Дивиденды по годам'!J4<>"",'Дивиденды по годам'!K4<>"",('Дивиденды по годам'!I4-'Дивиденды по годам'!J4-'Дивиденды по годам'!K4)<>0),'Дивиденды по годам'!L4/('Дивиденды по годам'!I4-'Дивиденды по годам'!J4-'Дивиденды по годам'!K4),""),"") -> 0.88690206 | T4: =IFERROR(IF(AND('Дивиденды по годам'!Q4<>"",'Дивиденды по годам'!I4<>"",'Дивиденды по годам'!V4<>"",('Дивиденды по годам'!I4+'Дивиденды по годам'!V4)<>0),'Дивиденды по годам'!Q4/(('Дивиденды по годам'!I4+'Дивиденды по годам'!V4)/2),""),"") -> -0.021263586 | U4: =IFERROR(IF(AND('Дивиденды по годам'!J4<>"",'Дивиденды по годам'!K4<>"",'Дивиденды по годам'!M4<>"",'Дивиденды по годам'!M4<>0),('Дивиденды по годам'!J4+'Дивиденды по годам'!K4)/'Дивиденды по годам'!M4,""),"") -> 0.74522866 | V4: {=IFERROR(AVERAGE(_xlfn._xlws.FILTER(P$2:P$1073,($C$2:$C$1073=$C4)*($E$2:$E$1073=$E4)*(ROW(P$2:P$1073)<>ROW(P4))*(P$2:P$1073<>""))),"")} -> 28.950488 | W4: {=IFERROR(AVERAGE(_xlfn._xlws.FILTER(Q$2:Q$1073,($C$2:$C$1073=$C4)*($E$2:$E$1073=$E4)*(ROW(Q$2:Q$1073)<>ROW(Q4))*(Q$2:Q$1073<>""))),"")} -> 0.47348976 | X4: {=IFERROR(AVERAGE(_xlfn._xlws.FILTER(R$2:R$1073,($C$2:$C$1073=$C4)*($E$2:$E$1073=$E4)*(ROW(R$2:R$1073)<>ROW(R4))*(R$2:R$1073<>""))),"")} -> -0.037500665 | Y4: {=IFERROR(AVERAGE(_xlfn._xlws.FILTER(S$2:S$1073,($C$2:$C$1073=$C4)*($E$2:$E$1073=$E4)*(ROW(S$2:S$1073)<>ROW(S4))*(S$2:S$1073<>""))),"")} -> 0.80302193 | Z4: {=IFERROR(AVERAGE(_xlfn._xlws.FILTER(T$2:T$1073,($C$2:$C$1073=$C4)*($E$2:$E$1073=$E4)*(ROW(T$2:T$1073)<>ROW(T4))*(T$2:T$1073<>""))),"")} -> 0.11841775 | AA4: {=IFERROR(AVERAGE(_xlfn._xlws.FILTER(U$2:U$1073,($C$2:$C$1073=$C4)*($E$2:$E$1073=$E4)*(ROW(U$2:U$1073)<>ROW(U4))*(U$2:U$1073<>""))),"")} -> 0.83818778
A5: GAZP | B5: =A5&" "& "IV" &" кв. "&C5 -> GAZP IV кв. 2022 | C5: 2022 | D5: =SUMIFS(Дивиденды!$C:$C,Дивиденды!$A:$A,A5,Дивиденды!$I:$I,C5) -> 51.03 | E5: 1 | F5: =D5 -> 51.03 | G5: =AVERAGEIFS($D:$D,$E:$E,E5,$C:$C,C5,$A:$A,"<>"&A5) -> 240.50333 | H5: =IF(D5>0,1,0) -> 1 | I5: =IFERROR((COUNTIFS($E:$E,E5,$C:$C,C5,$H:$H,1)-H5)/(COUNTIFS($E:$E,E5,$C:$C,C5)-1),0) -> 0.83333333 | J5: =IF(A6<>A5,"",IF(D5=D6,0,IF(AND(D6=0,D5<>0), 1,(D5-D6)/D6))) -> 1 | K5: =IFERROR(AVERAGEIFS($J:$J,$E:$E,E5,$C:$C,C5,$A:$A,"<>"&A5),"") -> 0.59952004 | L5: =IF(J5<>"",IF(J5>0,1,0),"") -> 1 | M5: =IFERROR(AVERAGEIFS($L:$L,$E:$E,E5,$C:$C,C5,$A:$A,"<>"&A5),"") -> 0.5 | N5: =IF(J5<>"",IF(J5<0,1,0),"") -> 0 | O5: =IFERROR(AVERAGEIFS($N:$N,$E:$E,E5,$C:$C,C5,$A:$A,"<>"&A5),"") -> 0.16666667 | P5: =IFERROR(LN('Дивиденды по годам'!I5),"") -> 30.894064 | Q5: =IFERROR('Дивиденды по годам'!G5/'Дивиденды по годам'!I5, "") -> 0.66665802 | R5: =IFERROR(IF(AND('Дивиденды по годам'!N5<>"",'Дивиденды по годам'!U5<>"",'Дивиденды по годам'!U5<>0),'Дивиденды по годам'!N5/'Дивиденды по годам'!U5-1,""),"") -> 0.13988357 | S5: =IFERROR(IF(AND('Дивиденды по годам'!L5<>"",'Дивиденды по годам'!I5<>"",'Дивиденды по годам'!J5<>"",'Дивиденды по годам'!K5<>"",('Дивиденды по годам'!I5-'Дивиденды по годам'!J5-'Дивиденды по годам'!K5)<>0),'Дивиденды по годам'!L5/('Дивиденды по годам'!I5-'Дивиденды по годам'!J5-'Дивиденды по годам'!K5),""),"") -> 0.9197466 | T5: =IFERROR(IF(AND('Дивиденды по годам'!Q5<>"",'Дивиденды по годам'!I5<>"",'Дивиденды по годам'!V5<>"",('Дивиденды по годам'!I5+'Дивиденды по годам'!V5)<>0),'Дивиденды по годам'!Q5/(('Дивиденды по годам'!I5+'Дивиденды по годам'!V5)/2),""),"") -> 0.04933207 | U5: =IFERROR(IF(AND('Дивиденды по годам'!J5<>"",'Дивиденды по годам'!K5<>"",'Дивиденды по годам'!M5<>"",'Дивиденды по годам'!M5<>0),('Дивиденды по годам'!J5+'Дивиденды по годам'!K5)/'Дивиденды по годам'!M5,""),"") -> 0.58878604 | V5: {=IFERROR(AVERAGE(_xlfn._xlws.FILTER(P$2:P$1073,($C$2:$C$1073=$C5)*($E$2:$E$1073=$E5)*(ROW(P$2:P$1073)<>ROW(P5))*(P$2:P$1073<>""))),"")} -> 28.005023 | W5: {=IFERROR(AVERAGE(_xlfn._xlws.FILTER(Q$2:Q$1073,($C$2:$C$1073=$C5)*($E$2:$E$1073=$E5)*(ROW(Q$2:Q$1073)<>ROW(Q5))*(Q$2:Q$1073<>""))),"")} -> 0.45949876 | X5: {=IFERROR(AVERAGE(_xlfn._xlws.FILTER(R$2:R$1073,($C$2:$C$1073=$C5)*($E$2:$E$1073=$E5)*(ROW(R$2:R$1073)<>ROW(R5))*(R$2:R$1073<>""))),"")} -> 0.1038114 | Y5: {=IFERROR(AVERAGE(_xlfn._xlws.FILTER(S$2:S$1073,($C$2:$C$1073=$C5)*($E$2:$E$1073=$E5)*(ROW(S$2:S$1073)<>ROW(S5))*(S$2:S$1073<>""))),"")} -> 0.78172804 | Z5: {=IFERROR(AVERAGE(_xlfn._xlws.FILTER(T$2:T$1073,($C$2:$C$1073=$C5)*($E$2:$E$1073=$E5)*(ROW(T$2:T$1073)<>ROW(T5))*(T$2:T$1073<>""))),"")} -> 0.12952165 | AA5: {=IFERROR(AVERAGE(_xlfn._xlws.FILTER(U$2:U$1073,($C$2:$C$1073=$C5)*($E$2:$E$1073=$E5)*(ROW(U$2:U$1073)<>ROW(U5))*(U$2:U$1073<>""))),"")} -> 0.8837483
A6: GAZP | B6: =A6&" "& "IV" &" кв. "&C6 -> GAZP IV кв. 2021 | C6: 2021 | D6: =SUMIFS(Дивиденды!$C:$C,Дивиденды!$A:$A,A6,Дивиденды!$I:$I,C6) -> 0 | E6: 1 | F6: =D6 -> 0 | G6: =AVERAGEIFS($D:$D,$E:$E,E6,$C:$C,C6,$A:$A,"<>"&A6) -> 82.756667 | H6: =IF(D6>0,1,0) -> 0 | I6: =IFERROR((COUNTIFS($E:$E,E6,$C:$C,C6,$H:$H,1)-H6)/(COUNTIFS($E:$E,E6,$C:$C,C6)-1),0) -> 0.83333333 | J6: =IF(A7<>A6,"",IF(D6=D7,0,IF(AND(D7=0,D6<>0), 1,(D6-D7)/D7))) -> -1 | K6: =IFERROR(AVERAGEIFS($J:$J,$E:$E,E6,$C:$C,C6,$A:$A,"<>"&A6),"") -> 1.2307909 | L6: =IF(J6<>"",IF(J6>0,1,0),"") -> 0 | M6: =IFERROR(AVERAGEIFS($L:$L,$E:$E,E6,$C:$C,C6,$A:$A,"<>"&A6),"") -> 0.83333333 | N6: =IF(J6<>"",IF(J6<0,1,0),"") -> 1 | O6: =IFERROR(AVERAGEIFS($N:$N,$E:$E,E6,$C:$C,C6,$A:$A,"<>"&A6),"") -> 0 | P6: =IFERROR(LN('Дивиденды по годам'!I6),"") -> 30.928606 | Q6: =IFERROR('Дивиденды по годам'!G6/'Дивиденды по годам'!I6, "") -> 0.61646121 | R6: =IFERROR(IF(AND('Дивиденды по годам'!N6<>"",'Дивиденды по годам'!U6<>"",'Дивиденды по годам'!U6<>0),'Дивиденды по годам'!N6/'Дивиденды по годам'!U6-1,""),"") -> 0.62006761 | S6: =IFERROR(IF(AND('Дивиденды по годам'!L6<>"",'Дивиденды по годам'!I6<>"",'Дивиденды по годам'!J6<>"",'Дивиденды по годам'!K6<>"",('Дивиденды по годам'!I6-'Дивиденды по годам'!J6-'Дивиденды по годам'!K6)<>0),'Дивиденды по годам'!L6/('Дивиденды по годам'!I6-'Дивиденды по годам'!J6-'Дивиденды по годам'!K6),""),"") -> 0.92570438 | T6: =IFERROR(IF(AND('Дивиденды по годам'!Q6<>"",'Дивиденды по годам'!I6<>"",'Дивиденды по годам'!V6<>"",('Дивиденды по годам'!I6+'Дивиденды по годам'!V6)<>0),'Дивиденды по годам'!Q6/(('Дивиденды по годам'!I6+'Дивиденды по годам'!V6)/2),""),"") -> 0.08567901 | U6: =IFERROR(IF(AND('Дивиденды по годам'!J6<>"",'Дивиденды по годам'!K6<>"",'Дивиденды по годам'!M6<>"",'Дивиденды по годам'!M6<>0),('Дивиденды по годам'!J6+'Дивиденды по годам'!K6)/'Дивиденды по годам'!M6,""),"") -> 0.60359905 | V6: {=IFERROR(AVERAGE(_xlfn._xlws.FILTER(P$2:P$1073,($C$2:$C$1073=$C6)*($E$2:$E$1073=$E6)*(ROW(P$2:P$1073)<>ROW(P6))*(P$2:P$1073<>""))),"")} -> 28.588015 | W6: {=IFERROR(AVERAGE(_xlfn._xlws.FILTER(Q$2:Q$1073,($C$2:$C$1073=$C6)*($E$2:$E$1073=$E6)*(ROW(Q$2:Q$1073)<>ROW(Q6))*(Q$2:Q$1073<>""))),"")} -> 0.54592305 | X6: {=IFERROR(AVERAGE(_xlfn._xlws.FILTER(R$2:R$1073,($C$2:$C$1073=$C6)*($E$2:$E$1073=$E6)*(ROW(R$2:R$1073)<>ROW(R6))*(R$2:R$1073<>""))),"")} -> 0.71962064 | Y6: {=IFERROR(AVERAGE(_xlfn._xlws.FILTER(S$2:S$1073,($C$2:$C$1073=$C6)*($E$2:$E$1073=$E6)*(ROW(S$2:S$1073)<>ROW(S6))*(S$2:S$1073<>""))),"")} -> 0.78164523 | Z6: {=IFERROR(AVERAGE(_xlfn._xlws.FILTER(T$2:T$1073,($C$2:$C$1073=$C6)*($E$2:$E$1073=$E6)*(ROW(T$2:T$1073)<>ROW(T6))*(T$2:T$1073<>""))),"")} -> 0.12893486 | AA6: {=IFERROR(AVERAGE(_xlfn._xlws.FILTER(U$2:U$1073,($C$2:$C$1073=$C6)*($E$2:$E$1073=$E6)*(ROW(U$2:U$1073)<>ROW(U6))*(U$2:U$1073<>""))),"")} -> 1.1281548
A7: GAZP | B7: =A7&" "& "IV" &" кв. "&C7 -> GAZP IV кв. 2020 | C7: 2020 | D7: =SUMIFS(Дивиденды!$C:$C,Дивиденды!$A:$A,A7,Дивиденды!$I:$I,C7) -> 12.55 | E7: 1 | F7: =D7 -> 12.55 | G7: =AVERAGEIFS($D:$D,$E:$E,E7,$C:$C,C7,$A:$A,"<>"&A7) -> 54.073333 | H7: =IF(D7>0,1,0) -> 1 | I7: =IFERROR((COUNTIFS($E:$E,E7,$C:$C,C7,$H:$H,1)-H7)/(COUNTIFS($E:$E,E7,$C:$C,C7)-1),0) -> 0.83333333 | J7: =IF(A8<>A7,"",IF(D7=D8,0,IF(AND(D8=0,D7<>0), 1,(D7-D8)/D8))) -> -0.17650919 | K7: =IFERROR(AVERAGEIFS($J:$J,$E:$E,E7,$C:$C,C7,$A:$A,"<>"&A7),"") -> -0.29877017 | L7: =IF(J7<>"",IF(J7>0,1,0),"") -> 0 | M7: =IFERROR(AVERAGEIFS($L:$L,$E:$E,E7,$C:$C,C7,$A:$A,"<>"&A7),"") -> 0.33333333 | N7: =IF(J7<>"",IF(J7<0,1,0),"") -> 1 | O7: =IFERROR(AVERAGEIFS($N:$N,$E:$E,E7,$C:$C,C7,$A:$A,"<>"&A7),"") -> 0.5 | P7: =IFERROR(LN('Дивиденды по годам'!I7),"") -> 30.781712 | Q7: =IFERROR('Дивиденды по годам'!G7/'Дивиденды по годам'!I7, "") -> 0.68957552 | R7: =IFERROR(IF(AND('Дивиденды по годам'!N7<>"",'Дивиденды по годам'!U7<>"",'Дивиденды по годам'!U7<>0),'Дивиденды по годам'!N7/'Дивиденды по годам'!U7-1,""),"") -> -0.17469058 | S7: =IFERROR(IF(AND('Дивиденды по годам'!L7<>"",'Дивиденды по годам'!I7<>"",'Дивиденды по годам'!J7<>"",'Дивиденды по годам'!K7<>"",('Дивиденды по годам'!I7-'Дивиденды по годам'!J7-'Дивиденды по годам'!K7)<>0),'Дивиденды по годам'!L7/('Дивиденды по годам'!I7-'Дивиденды по годам'!J7-'Дивиденды по годам'!K7),""),"") -> 0.92655943 | T7: =IFERROR(IF(AND('Дивиденды по годам'!Q7<>"",'Дивиденды по годам'!I7<>"",'Дивиденды по годам'!V7<>"",('Дивиденды по годам'!I7+'Дивиденды по годам'!V7)<>0),'Дивиденды по годам'!Q7/(('Дивиденды по годам'!I7+'Дивиденды по годам'!V7)/2),""),"") -> 0.0071806644 | U7: =IFERROR(IF(AND('Дивиденды по годам'!J7<>"",'Дивиденды по годам'!K7<>"",'Дивиденды по годам'!M7<>"",'Дивиденды по годам'!M7<>0),('Дивиденды по годам'!J7+'Дивиденды по годам'!K7)/'Дивиденды по годам'!M7,""),"") -> 0.57734601 | V7: {=IFERROR(AVERAGE(_xlfn._xlws.FILTER(P$2:P$1073,($C$2:$C$1073=$C7)*($E$2:$E$1073=$E7)*(ROW(P$2:P$1073)<>ROW(P7))*(P$2:P$1073<>""))),"")} -> 28.624109 | W7: {=IFERROR(AVERAGE(_xlfn._xlws.FILTER(Q$2:Q$1073,($C$2:$C$1073=$C7)*($E$2:$E$1073=$E7)*(ROW(Q$2:Q$1073)<>ROW(Q7))*(Q$2:Q$1073<>""))),"")} -> 0.5371219 | X7: {=IFERROR(AVERAGE(_xlfn._xlws.FILTER(R$2:R$1073,($C$2:$C$1073=$C7)*($E$2:$E$1073=$E7)*(ROW(R$2:R$1073)<>ROW(R7))*(R$2:R$1073<>""))),"")} -> -0.27049471 | Y7: {=IFERROR(AVERAGE(_xlfn._xlws.FILTER(S$2:S$1073,($C$2:$C$1073=$C7)*($E$2:$E$1073=$E7)*(ROW(S$2:S$1073)<>ROW(S7))*(S$2:S$1073<>""))),"")} -> 0.74822584 | Z7: {=IFERROR(AVERAGE(_xlfn._xlws.FILTER(T$2:T$1073,($C$2:$C$1073=$C7)*($E$2:$E$1073=$E7)*(ROW(T$2:T$1073)<>ROW(T7))*(T$2:T$1073<>""))),"")} -> 0.032136749 | AA7: {=IFERROR(AVERAGE(_xlfn._xlws.FILTER(U$2:U$1073,($C$2:$C$1073=$C7)*($E$2:$E$1073=$E7)*(ROW(U$2:U$1073)<>ROW(U7))*(U$2:U$1073<>""))),"")} -> 1.2967729
A8: GAZP | B8: =A8&" "& "IV" &" кв. "&C8 -> GAZP IV кв. 2019 | C8: 2019 | D8: =SUMIFS(Дивиденды!$C:$C,Дивиденды!$A:$A,A8,Дивиденды!$I:$I,C8) -> 15.24 | E8: 1 | F8: =D8 -> 15.24 | G8: =AVERAGEIFS($D:$D,$E:$E,E8,$C:$C,C8,$A:$A,"<>"&A8) -> 112.14333 | H8: =IF(D8>0,1,0) -> 1 | I8: =IFERROR((COUNTIFS($E:$E,E8,$C:$C,C8,$H:$H,1)-H8)/(COUNTIFS($E:$E,E8,$C:$C,C8)-1),0) -> 0.83333333 | J8: =IF(A9<>A8,"",IF(D8=D9,0,IF(AND(D9=0,D8<>0), 1,(D8-D9)/D9))) -> -0.082480433 | K8: =IFERROR(AVERAGEIFS($J:$J,$E:$E,E8,$C:$C,C8,$A:$A,"<>"&A8),"") -> 0.24288945 | L8: =IF(J8<>"",IF(J8>0,1,0),"") -> 0 | M8: =IFERROR(AVERAGEIFS($L:$L,$E:$E,E8,$C:$C,C8,$A:$A,"<>"&A8),"") -> 0.5 | N8: =IF(J8<>"",IF(J8<0,1,0),"") -> 1 | O8: =IFERROR(AVERAGEIFS($N:$N,$E:$E,E8,$C:$C,C8,$A:$A,"<>"&A8),"") -> 0.16666667 | P8: =IFERROR(LN('Дивиденды по годам'!I8),"") -> 30.716701 | Q8: =IFERROR('Дивиденды по годам'!G8/'Дивиденды по годам'!I8, "") -> 0.67892385 | R8: =IFERROR(IF(AND('Дивиденды по годам'!N8<>"",'Дивиденды по годам'!U8<>"",'Дивиденды по годам'!U8<>0),'Дивиденды по годам'!N8/'Дивиденды по годам'!U8-1,""),"") -> -0.068645653 | S8: =IFERROR(IF(AND('Дивиденды по годам'!L8<>"",'Дивиденды по годам'!I8<>"",'Дивиденды по годам'!J8<>"",'Дивиденды по годам'!K8<>"",('Дивиденды по годам'!I8-'Дивиденды по годам'!J8-'Дивиденды по годам'!K8)<>0),'Дивиденды по годам'!L8/('Дивиденды по годам'!I8-'Дивиденды по годам'!J8-'Дивиденды по годам'!K8),""),"") -> 0.94282055 | T8: =IFERROR(IF(AND('Дивиденды по годам'!Q8<>"",'Дивиденды по годам'!I8<>"",'Дивиденды по годам'!V8<>"",('Дивиденды по годам'!I8+'Дивиденды по годам'!V8)<>0),'Дивиденды по годам'!Q8/(('Дивиденды по годам'!I8+'Дивиденды по годам'!V8)/2),""),"") -> 0.059472199 | U8: =IFERROR(IF(AND('Дивиденды по годам'!J8<>"",'Дивиденды по годам'!K8<>"",'Дивиденды по годам'!M8<>"",'Дивиденды по годам'!M8<>0),('Дивиденды по годам'!J8+'Дивиденды по годам'!K8)/'Дивиденды по годам'!M8,""),"") -> 0.49718231 | V8: {=IFERROR(AVERAGE(_xlfn._xlws.FILTER(P$2:P$1073,($C$2:$C$1073=$C8)*($E$2:$E$1073=$E8)*(ROW(P$2:P$1073)<>ROW(P8))*(P$2:P$1073<>""))),"")} -> 28.572217 | W8: {=IFERROR(AVERAGE(_xlfn._xlws.FILTER(Q$2:Q$1073,($C$2:$C$1073=$C8)*($E$2:$E$1073=$E8)*(ROW(Q$2:Q$1073)<>ROW(Q8))*(Q$2:Q$1073<>""))),"")} -> 0.51462951 | X8: {=IFERROR(AVERAGE(_xlfn._xlws.FILTER(R$2:R$1073,($C$2:$C$1073=$C8)*($E$2:$E$1073=$E8)*(ROW(R$2:R$1073)<>ROW(R8))*(R$2:R$1073<>""))),"")} -> 0.025367391 | Y8: {=IFERROR(AVERAGE(_xlfn._xlws.FILTER(S$2:S$1073,($C$2:$C$1073=$C8)*($E$2:$E$1073=$E8)*(ROW(S$2:S$1073)<>ROW(S8))*(S$2:S$1073<>""))),"")} -> 0.82043004 | Z8: {=IFERROR(AVERAGE(_xlfn._xlws.FILTER(T$2:T$1073,($C$2:$C$1073=$C8)*($E$2:$E$1073=$E8)*(ROW(T$2:T$1073)<>ROW(T8))*(T$2:T$1073<>""))),"")} -> 0.16320282 | AA8: {=IFERROR(AVERAGE(_xlfn._xlws.FILTER(U$2:U$1073,($C$2:$C$1073=$C8)*($E$2:$E$1073=$E8)*(ROW(U$2:U$1073)<>ROW(U8))*(U$2:U$1073<>""))),"")} -> 0.95146752
A9: GAZP | B9: =A9&" "& "IV" &" кв. "&C9 -> GAZP IV кв. 2018 | C9: 2018 | D9: =SUMIFS(Дивиденды!$C:$C,Дивиденды!$A:$A,A9,Дивиденды!$I:$I,C9) -> 16.61 | E9: 1 | F9: =D9 -> 16.61 | G9: =AVERAGEIFS($D:$D,$E:$E,E9,$C:$C,C9,$A:$A,"<>"&A9) -> 64.588333 | H9: =IF(D9>0,1,0) -> 1 | I9: =IFERROR((COUNTIFS($E:$E,E9,$C:$C,C9,$H:$H,1)-H9)/(COUNTIFS($E:$E,E9,$C:$C,C9)-1),0) -> 0.83333333 | J9: =IF(A10<>A9,"",IF(D9=D10,0,IF(AND(D10=0,D9<>0), 1,(D9-D10)/D10))) -> 1.0659204 | K9: =IFERROR(AVERAGEIFS($J:$J,$E:$E,E9,$C:$C,C9,$A:$A,"<>"&A9),"") -> 0.58403361 | L9: =IF(J9<>"",IF(J9>0,1,0),"") -> 1 | M9: =IFERROR(AVERAGEIFS($L:$L,$E:$E,E9,$C:$C,C9,$A:$A,"<>"&A9),"") -> 0.66666667 | N9: =IF(J9<>"",IF(J9<0,1,0),"") -> 0 | O9: =IFERROR(AVERAGEIFS($N:$N,$E:$E,E9,$C:$C,C9,$A:$A,"<>"&A9),"") -> 0 | P9: =IFERROR(LN('Дивиденды по годам'!I9),"") -> 30.666476 | Q9: =IFERROR('Дивиденды по годам'!G9/'Дивиденды по годам'!I9, "") -> 0.66358203 | R9: =IFERROR(IF(AND('Дивиденды по годам'!N9<>"",'Дивиденды по годам'!U9<>"",'Дивиденды по годам'!U9<>0),'Дивиденды по годам'!N9/'Дивиденды по годам'!U9-1,""),"") -> 0.25633934 | S9: =IFERROR(IF(AND('Дивиденды по годам'!L9<>"",'Дивиденды по годам'!I9<>"",'Дивиденды по годам'!J9<>"",'Дивиденды по годам'!K9<>"",('Дивиденды по годам'!I9-'Дивиденды по годам'!J9-'Дивиденды по годам'!K9)<>0),'Дивиденды по годам'!L9/('Дивиденды по годам'!I9-'Дивиденды по годам'!J9-'Дивиденды по годам'!K9),""),"") -> 0.95895668 | T9: =IFERROR(IF(AND('Дивиденды по годам'!Q9<>"",'Дивиденды по годам'!I9<>"",'Дивиденды по годам'!V9<>"",('Дивиденды по годам'!I9+'Дивиденды по годам'!V9)<>0),'Дивиденды по годам'!Q9/(('Дивиденды по годам'!I9+'Дивиденды по годам'!V9)/2),""),"") -> 0.078311239 | U9: =IFERROR(IF(AND('Дивиденды по годам'!J9<>"",'Дивиденды по годам'!K9<>"",'Дивиденды по годам'!M9<>"",'Дивиденды по годам'!M9<>0),('Дивиденды по годам'!J9+'Дивиденды по годам'!K9)/'Дивиденды по годам'!M9,""),"") -> 0.5106133 | V9: {=IFERROR(AVERAGE(_xlfn._xlws.FILTER(P$2:P$1073,($C$2:$C$1073=$C9)*($E$2:$E$1073=$E9)*(ROW(P$2:P$1073)<>ROW(P9))*(P$2:P$1073<>""))),"")} -> 28.458498 | W9: {=IFERROR(AVERAGE(_xlfn._xlws.FILTER(Q$2:Q$1073,($C$2:$C$1073=$C9)*($E$2:$E$1073=$E9)*(ROW(Q$2:Q$1073)<>ROW(Q9))*(Q$2:Q$1073<>""))),"")} -> 0.50857093 | X9: {=IFERROR(AVERAGE(_xlfn._xlws.FILTER(R$2:R$1073,($C$2:$C$1073=$C9)*($E$2:$E$1073=$E9)*(ROW(R$2:R$1073)<>ROW(R9))*(R$2:R$1073<>""))),"")} -> 0.36447021 | Y9: {=IFERROR(AVERAGE(_xlfn._xlws.FILTER(S$2:S$1073,($C$2:$C$1073=$C9)*($E$2:$E$1073=$E9)*(ROW(S$2:S$1073)<>ROW(S9))*(S$2:S$1073<>""))),"")} -> 0.75475667 | Z9: {=IFERROR(AVERAGE(_xlfn._xlws.FILTER(T$2:T$1073,($C$2:$C$1073=$C9)*($E$2:$E$1073=$E9)*(ROW(T$2:T$1073)<>ROW(T9))*(T$2:T$1073<>""))),"")} -> 0.12546632 | AA9: {=IFERROR(AVERAGE(_xlfn._xlws.FILTER(U$2:U$1073,($C$2:$C$1073=$C9)*($E$2:$E$1073=$E9)*(ROW(U$2:U$1073)<>ROW(U9))*(U$2:U$1073<>""))),"")} -> 0.92459536
A10: GAZP | B10: =A10&" "& "IV" &" кв. "&C10 -> GAZP IV кв. 2017 | C10: 2017 | D10: =SUMIFS(Дивиденды!$C:$C,Дивиденды!$A:$A,A10,Дивиденды!$I:$I,C10) -> 8.04 | E10: 1 | F10: =D10 -> 8.04 | G10: =AVERAGEIFS($D:$D,$E:$E,E10,$C:$C,C10,$A:$A,"<>"&A10) -> 46.836667 | H10: =IF(D10>0,1,0) -> 1 | I10: =IFERROR((COUNTIFS($E:$E,E10,$C:$C,C10,$H:$H,1)-H10)/(COUNTIFS($E:$E,E10,$C:$C,C10)-1),0) -> 0.83333333 | J10: =IF(A11<>A10,"",IF(D10=D11,0,IF(AND(D11=0,D10<>0), 1,(D10-D11)/D11))) -> 0 | K10: =IFERROR(AVERAGEIFS($J:$J,$E:$E,E10,$C:$C,C10,$A:$A,"<>"&A10),"") -> 0.2941553 | L10: =IF(J10<>"",IF(J10>0,1,0),"") -> 0 | M10: =IFERROR(AVERAGEIFS($L:$L,$E:$E,E10,$C:$C,C10,$A:$A,"<>"&A10),"") -> 0.83333333 | N10: =IF(J10<>"",IF(J10<0,1,0),"") -> 0 | O10: =IFERROR(AVERAGEIFS($N:$N,$E:$E,E10,$C:$C,C10,$A:$A,"<>"&A10),"") -> 0 | P10: =IFERROR(LN('Дивиденды по годам'!I10),"") -> 30.534571 | Q10: =IFERROR('Дивиденды по годам'!G10/'Дивиденды по годам'!I10, "") -> 0.68782484 | R10: =IFERROR(IF(AND('Дивиденды по годам'!N10<>"",'Дивиденды по годам'!U10<>"",'Дивиденды по годам'!U10<>0),'Дивиденды по годам'!N10/'Дивиденды по годам'!U10-1,""),"") -> 0.071197573 | S10: =IFERROR(IF(AND('Дивиденды по годам'!L10<>"",'Дивиденды по годам'!I10<>"",'Дивиденды по годам'!J10<>"",'Дивиденды по годам'!K10<>"",('Дивиденды по годам'!I10-'Дивиденды по годам'!J10-'Дивиденды по годам'!K10)<>0),'Дивиденды по годам'!L10/('Дивиденды по годам'!I10-'Дивиденды по годам'!J10-'Дивиденды по годам'!K10),""),"") -> 0.96041191 | T10: =IFERROR(IF(AND('Дивиденды по годам'!Q10<>"",'Дивиденды по годам'!I10<>"",'Дивиденды по годам'!V10<>"",('Дивиденды по годам'!I10+'Дивиденды по годам'!V10)<>0),'Дивиденды по годам'!Q10/(('Дивиденды по годам'!I10+'Дивиденды по годам'!V10)/2),""),"") -> 0.043625085 | U10: =IFERROR(IF(AND('Дивиденды по годам'!J10<>"",'Дивиденды по годам'!K10<>"",'Дивиденды по годам'!M10<>"",'Дивиденды по годам'!M10<>0),('Дивиденды по годам'!J10+'Дивиденды по годам'!K10)/'Дивиденды по годам'!M10,""),"") -> 0.51793923 | V10: {=IFERROR(AVERAGE(_xlfn._xlws.FILTER(P$2:P$1073,($C$2:$C$1073=$C10)*($E$2:$E$1073=$E10)*(ROW(P$2:P$1073)<>ROW(P10))*(P$2:P$1073<>""))),"")} -> 28.340294 | W10: {=IFERROR(AVERAGE(_xlfn._xlws.FILTER(Q$2:Q$1073,($C$2:$C$1073=$C10)*($E$2:$E$1073=$E10)*(ROW(Q$2:Q$1073)<>ROW(Q10))*(Q$2:Q$1073<>""))),"")} -> 0.5242558 | X10: {=IFERROR(AVERAGE(_xlfn._xlws.FILTER(R$2:R$1073,($C$2:$C$1073=$C10)*($E$2:$E$1073=$E10)*(ROW(R$2:R$1073)<>ROW(R10))*(R$2:R$1073<>""))),"")} -> 0.16368052 | Y10: {=IFERROR(AVERAGE(_xlfn._xlws.FILTER(S$2:S$1073,($C$2:$C$1073=$C10)*($E$2:$E$1073=$E10)*(ROW(S$2:S$1073)<>ROW(S10))*(S$2:S$1073<>""))),"")} -> 0.73280408 | Z10: {=IFERROR(AVERAGE(_xlfn._xlws.FILTER(T$2:T$1073,($C$2:$C$1073=$C10)*($E$2:$E$1073=$E10)*(ROW(T$2:T$1073)<>ROW(T10))*(T$2:T$1073<>""))),"")} -> 0.077823093 | AA10: {=IFERROR(AVERAGE(_xlfn._xlws.FILTER(U$2:U$1073,($C$2:$C$1073=$C10)*($E$2:$E$1073=$E10)*(ROW(U$2:U$1073)<>ROW(U10))*(U$2:U$1073<>""))),"")} -> 0.97472196
A11: GAZP | B11: =A11&" "& "IV" &" кв. "&C11 -> GAZP IV кв. 2016 | C11: 2016 | D11: =SUMIFS(Дивиденды!$C:$C,Дивиденды!$A:$A,A11,Дивиденды!$I:$I,C11) -> 8.04 | E11: 1 | F11: =D11 -> 8.04 | G11: =AVERAGEIFS($D:$D,$E:$E,E11,$C:$C,C11,$A:$A,"<>"&A11) -> 39.715 | H11: =IF(D11>0,1,0) -> 1 | I11: =IFERROR((COUNTIFS($E:$E,E11,$C:$C,C11,$H:$H,1)-H11)/(COUNTIFS($E:$E,E11,$C:$C,C11)-1),0) -> 0.83333333 | J11: =IF(A12<>A11,"",IF(D11=D12,0,IF(AND(D12=0,D11<>0), 1,(D11-D12)/D12))) -> 0.019011407 | K11: =IFERROR(AVERAGEIFS($J:$J,$E:$E,E11,$C:$C,C11,$A:$A,"<>"&A11),"") -> 0.12024418 | L11: =IF(J11<>"",IF(J11>0,1,0),"") -> 1 | M11: =IFERROR(AVERAGEIFS($L:$L,$E:$E,E11,$C:$C,C11,$A:$A,"<>"&A11),"") -> 0.5 | N11: =IF(J11<>"",IF(J11<0,1,0),"") -> 0 | O11: =IFERROR(AVERAGEIFS($N:$N,$E:$E,E11,$C:$C,C11,$A:$A,"<>"&A11),"") -> 0.16666667 | P11: =IFERROR(LN('Дивиденды по годам'!I11),"") -> 30.459455 | Q11: =IFERROR('Дивиденды по годам'!G11/'Дивиденды по годам'!I11, "") -> 0.67987406 | R11: =IFERROR(IF(AND('Дивиденды по годам'!N11<>"",'Дивиденды по годам'!U11<>"",'Дивиденды по годам'!U11<>0),'Дивиденды по годам'!N11/'Дивиденды по годам'!U11-1,""),"") -> 0.0062129136 | S11: =IFERROR(IF(AND('Дивиденды по годам'!L11<>"",'Дивиденды по годам'!I11<>"",'Дивиденды по годам'!J11<>"",'Дивиденды по годам'!K11<>"",('Дивиденды по годам'!I11-'Дивиденды по годам'!J11-'Дивиденды по годам'!K11)<>0),'Дивиденды по годам'!L11/('Дивиденды по годам'!I11-'Дивиденды по годам'!J11-'Дивиденды по годам'!K11),""),"") -> 0.96184328 | T11: =IFERROR(IF(AND('Дивиденды по годам'!Q11<>"",'Дивиденды по годам'!I11<>"",'Дивиденды по годам'!V11<>"",('Дивиденды по годам'!I11+'Дивиденды по годам'!V11)<>0),'Дивиденды по годам'!Q11/(('Дивиденды по годам'!I11+'Дивиденды по годам'!V11)/2),""),"") -> 0.058703285 | U11: =IFERROR(IF(AND('Дивиденды по годам'!J11<>"",'Дивиденды по годам'!K11<>"",'Дивиденды по годам'!M11<>"",'Дивиденды по годам'!M11<>0),('Дивиденды по годам'!J11+'Дивиденды по годам'!K11)/'Дивиденды по годам'!M11,""),"") -> 0.47869044 | V11: {=IFERROR(AVERAGE(_xlfn._xlws.FILTER(P$2:P$1073,($C$2:$C$1073=$C11)*($E$2:$E$1073=$E11)*(ROW(P$2:P$1073)<>ROW(P11))*(P$2:P$1073<>""))),"")} -> 28.279917 | W11: {=IFERROR(AVERAGE(_xlfn._xlws.FILTER(Q$2:Q$1073,($C$2:$C$1073=$C11)*($E$2:$E$1073=$E11)*(ROW(Q$2:Q$1073)<>ROW(Q11))*(Q$2:Q$1073<>""))),"")} -> 0.50976916 | X11: {=IFERROR(AVERAGE(_xlfn._xlws.FILTER(R$2:R$1073,($C$2:$C$1073=$C11)*($E$2:$E$1073=$E11)*(ROW(R$2:R$1073)<>ROW(R11))*(R$2:R$1073<>""))),"")} -> 0.012025011 | Y11: {=IFERROR(AVERAGE(_xlfn._xlws.FILTER(S$2:S$1073,($C$2:$C$1073=$C11)*($E$2:$E$1073=$E11)*(ROW(S$2:S$1073)<>ROW(S11))*(S$2:S$1073<>""))),"")} -> 0.68181067 | Z11: {=IFERROR(AVERAGE(_xlfn._xlws.FILTER(T$2:T$1073,($C$2:$C$1073=$C11)*($E$2:$E$1073=$E11)*(ROW(T$2:T$1073)<>ROW(T11))*(T$2:T$1073<>""))),"")} -> 0.10464156 | AA11: {=IFERROR(AVERAGE(_xlfn._xlws.FILTER(U$2:U$1073,($C$2:$C$1073=$C11)*($E$2:$E$1073=$E11)*(ROW(U$2:U$1073)<>ROW(U11))*(U$2:U$1073<>""))),"")} -> 1.0228333
A12: GAZP | B12: =A12&" "& "IV" &" кв. "&C12 -> GAZP IV кв. 2015 | C12: 2015 | D12: =SUMIFS(Дивиденды!$C:$C,Дивиденды!$A:$A,A12,Дивиденды!$I:$I,C12) -> 7.89 | E12: 1 | F12: =D12 -> 7.89 | G12: =AVERAGEIFS($D:$D,$E:$E,E12,$C:$C,C12,$A:$A,"<>"&A12) -> 35.635 | H12: =IF(D12>0,1,0) -> 1 | I12: =IFERROR((COUNTIFS($E:$E,E12,$C:$C,C12,$H:$H,1)-H12)/(COUNTIFS($E:$E,E12,$C:$C,C12)-1),0) -> 0.83333333 | J12: =IF(A13<>A12,"",IF(D12=D13,0,IF(AND(D13=0,D12<>0), 1,(D12-D13)/D13))) -> 0.095833333 | K12: =IFERROR(AVERAGEIFS($J:$J,$E:$E,E12,$C:$C,C12,$A:$A,"<>"&A12),"") -> 0.14170092 | L12: =IF(J12<>"",IF(J12>0,1,0),"") -> 1 | M12: =IFERROR(AVERAGEIFS($L:$L,$E:$E,E12,$C:$C,C12,$A:$A,"<>"&A12),"") -> 0.66666667 | N12: =IF(J12<>"",IF(J12<0,1,0),"") -> 0 | O12: =IFERROR(AVERAGEIFS($N:$N,$E:$E,E12,$C:$C,C12,$A:$A,"<>"&A12),"") -> 0.16666667 | P12: =IFERROR(LN('Дивиденды по годам'!I12),"") -> 30.467291 | Q12: =IFERROR('Дивиденды по годам'!G12/'Дивиденды по годам'!I12, "") -> 0.6453117 | R12: =IFERROR(IF(AND('Дивиденды по годам'!N12<>"",'Дивиденды по годам'!U12<>"",'Дивиденды по годам'!U12<>0),'Дивиденды по годам'!N12/'Дивиденды по годам'!U12-1,""),"") -> 0.086497916 | S12: =IFERROR(IF(AND('Дивиденды по годам'!L12<>"",'Дивиденды по годам'!I12<>"",'Дивиденды по годам'!J12<>"",'Дивиденды по годам'!K12<>"",('Дивиденды по годам'!I12-'Дивиденды по годам'!J12-'Дивиденды по годам'!K12)<>0),'Дивиденды по годам'!L12/('Дивиденды по годам'!I12-'Дивиденды по годам'!J12-'Дивиденды по годам'!K12),""),"") -> 0.94994687 | T12: =IFERROR(IF(AND('Дивиденды по годам'!Q12<>"",'Дивиденды по годам'!I12<>"",'Дивиденды по годам'!V12<>"",('Дивиденды по годам'!I12+'Дивиденды по годам'!V12)<>0),'Дивиденды по годам'!Q12/(('Дивиденды по годам'!I12+'Дивиденды по годам'!V12)/2),""),"") -> 0.049966568 | U12: =IFERROR(IF(AND('Дивиденды по годам'!J12<>"",'Дивиденды по годам'!K12<>"",'Дивиденды по годам'!M12<>"",'Дивиденды по годам'!M12<>0),('Дивиденды по годам'!J12+'Дивиденды по годам'!K12)/'Дивиденды по годам'!M12,""),"") -> 0.56231155 | V12: {=IFERROR(AVERAGE(_xlfn._xlws.FILTER(P$2:P$1073,($C$2:$C$1073=$C12)*($E$2:$E$1073=$E12)*(ROW(P$2:P$1073)<>ROW(P12))*(P$2:P$1073<>""))),"")} -> 28.027872 | W12: {=IFERROR(AVERAGE(_xlfn._xlws.FILTER(Q$2:Q$1073,($C$2:$C$1073=$C12)*($E$2:$E$1073=$E12)*(ROW(Q$2:Q$1073)<>ROW(Q12))*(Q$2:Q$1073<>""))),"")} -> 0.5715191 | X12: {=IFERROR(AVERAGE(_xlfn._xlws.FILTER(R$2:R$1073,($C$2:$C$1073=$C12)*($E$2:$E$1073=$E12)*(ROW(R$2:R$1073)<>ROW(R12))*(R$2:R$1073<>""))),"")} -> 0.11349517 | Y12: {=IFERROR(AVERAGE(_xlfn._xlws.FILTER(S$2:S$1073,($C$2:$C$1073=$C12)*($E$2:$E$1073=$E12)*(ROW(S$2:S$1073)<>ROW(S12))*(S$2:S$1073<>""))),"")} -> 0.93141876 | Z12: {=IFERROR(AVERAGE(_xlfn._xlws.FILTER(T$2:T$1073,($C$2:$C$1073=$C12)*($E$2:$E$1073=$E12)*(ROW(T$2:T$1073)<>ROW(T12))*(T$2:T$1073<>""))),"")} -> 0.083332631 | AA12: {=IFERROR(AVERAGE(_xlfn._xlws.FILTER(U$2:U$1073,($C$2:$C$1073=$C12)*($E$2:$E$1073=$E12)*(ROW(U$2:U$1073)<>ROW(U12))*(U$2:U$1073<>""))),"")} -> -1.2671068
A13: GAZP | B13: =A13&" "& "IV" &" кв. "&C13 -> GAZP IV кв. 2014 | C13: 2014 | D13: =SUMIFS(Дивиденды!$C:$C,Дивиденды!$A:$A,A13,Дивиденды!$I:$I,C13) -> 7.2 | E13: 1 | F13: =D13 -> 7.2 | G13: =AVERAGEIFS($D:$D,$E:$E,E13,$C:$C,C13,$A:$A,"<>"&A13) -> 30.623333 | H13: =IF(D13>0,1,0) -> 1 | I13: =IFERROR((COUNTIFS($E:$E,E13,$C:$C,C13,$H:$H,1)-H13)/(COUNTIFS($E:$E,E13,$C:$C,C13)-1),0) -> 0.83333333 | J13: =IF(A14<>A13,"",IF(D13=D14,0,IF(AND(D14=0,D13<>0), 1,(D13-D14)/D14))) -> 0 | K13: =IFERROR(AVERAGEIFS($J:$J,$E:$E,E13,$C:$C,C13,$A:$A,"<>"&A13),"") -> 0.11887241 | L13: =IF(J13<>"",IF(J13>0,1,0),"") -> 0 | M13: =IFERROR(AVERAGEIFS($L:$L,$E:$E,E13,$C:$C,C13,$A:$A,"<>"&A13),"") -> 0.66666667 | N13: =IF(J13<>"",IF(J13<0,1,0),"") -> 0 | O13: =IFERROR(AVERAGEIFS($N:$N,$E:$E,E13,$C:$C,C13,$A:$A,"<>"&A13),"") -> 0.16666667 | P13: =IFERROR(LN('Дивиденды по годам'!I13),"") -> 30.350833 | Q13: =IFERROR('Дивиденды по годам'!G13/'Дивиденды по годам'!I13, "") -> 0.65559075 | R13: =IFERROR(IF(AND('Дивиденды по годам'!N13<>"",'Дивиденды по годам'!U13<>"",'Дивиденды по годам'!U13<>0),'Дивиденды по годам'!N13/'Дивиденды по годам'!U13-1,""),"") -> 0.064733003 | S13: =IFERROR(IF(AND('Дивиденды по годам'!L13<>"",'Дивиденды по годам'!I13<>"",'Дивиденды по годам'!J13<>"",'Дивиденды по годам'!K13<>"",('Дивиденды по годам'!I13-'Дивиденды по годам'!J13-'Дивиденды по годам'!K13)<>0),'Дивиденды по годам'!L13/('Дивиденды по годам'!I13-'Дивиденды по годам'!J13-'Дивиденды по годам'!K13),""),"") -> 0.94814853 | T13: =IFERROR(IF(AND('Дивиденды по годам'!Q13<>"",'Дивиденды по годам'!I13<>"",'Дивиденды по годам'!V13<>"",('Дивиденды по годам'!I13+'Дивиденды по годам'!V13)<>0),'Дивиденды по годам'!Q13/(('Дивиденды по годам'!I13+'Дивиденды по годам'!V13)/2),""),"") -> 0.010987182 | U13: =IFERROR(IF(AND('Дивиденды по годам'!J13<>"",'Дивиденды по годам'!K13<>"",'Дивиденды по годам'!M13<>"",'Дивиденды по годам'!M13<>0),('Дивиденды по годам'!J13+'Дивиденды по годам'!K13)/'Дивиденды по годам'!M13,""),"") -> 0.49974689 | V13: {=IFERROR(AVERAGE(_xlfn._xlws.FILTER(P$2:P$1073,($C$2:$C$1073=$C13)*($E$2:$E$1073=$E13)*(ROW(P$2:P$1073)<>ROW(P13))*(P$2:P$1073<>""))),"")} -> 28.372329 | W13: {=IFERROR(AVERAGE(_xlfn._xlws.FILTER(Q$2:Q$1073,($C$2:$C$1073=$C13)*($E$2:$E$1073=$E13)*(ROW(Q$2:Q$1073)<>ROW(Q13))*(Q$2:Q$1073<>""))),"")} -> 0.62176756 | X13: {=IFERROR(AVERAGE(_xlfn._xlws.FILTER(R$2:R$1073,($C$2:$C$1073=$C13)*($E$2:$E$1073=$E13)*(ROW(R$2:R$1073)<>ROW(R13))*(R$2:R$1073<>""))),"")} -> 0.16466401 | Y13: {=IFERROR(AVERAGE(_xlfn._xlws.FILTER(S$2:S$1073,($C$2:$C$1073=$C13)*($E$2:$E$1073=$E13)*(ROW(S$2:S$1073)<>ROW(S13))*(S$2:S$1073<>""))),"")} -> 0.93308346 | Z13: {=IFERROR(AVERAGE(_xlfn._xlws.FILTER(T$2:T$1073,($C$2:$C$1073=$C13)*($E$2:$E$1073=$E13)*(ROW(T$2:T$1073)<>ROW(T13))*(T$2:T$1073<>""))),"")} -> 0.071375294 | AA13: {=IFERROR(AVERAGE(_xlfn._xlws.FILTER(U$2:U$1073,($C$2:$C$1073=$C13)*($E$2:$E$1073=$E13)*(ROW(U$2:U$1073)<>ROW(U13))*(U$2:U$1073<>""))),"")} -> 0.86783657
... A1073: SMLT | B1073: =A1073&" "& "IV" &" кв. "&C1073 -> SMLT IV кв. 2010 | C1073: 2010 | D1073: =SUMIFS(Дивиденды!$C:$C,Дивиденды!$A:$A,A1073,Дивиденды!$I:$I,C1073) -> 0 | E1073: 8 | F1073: =D1073 -> 0 | G1073: =AVERAGEIFS($D:$D,$E:$E,E1073,$C:$C,C1073,$A:$A,"<>"&A1073) -> 5 | H1073: =IF(D1073>0,1,0) -> 0 | I1073: =IFERROR((COUNTIFS($E:$E,E1073,$C:$C,C1073,$H:$H,1)-H1073)/(COUNTIFS($E:$E,E1073,$C:$C,C1073)-1),0) -> 0.33333333 | J1073: =IF(A1074<>A1073,"",IF(D1073=D1074,0,IF(AND(D1074=0,D1073<>0), 1,(D1073-D1074)/D1074))) | K1073: =IFERROR(AVERAGEIFS($J:$J,$E:$E,E1073,$C:$C,C1073,$A:$A,"<>"&A1073),"") | L1073: =IF(J1073<>"",IF(J1073>0,1,0),"") | M1073: =IFERROR(AVERAGEIFS($L:$L,$E:$E,E1073,$C:$C,C1073,$A:$A,"<>"&A1073),"") | N1073: =IF(J1073<>"",IF(J1073<0,1,0),"") | O1073: =IFERROR(AVERAGEIFS($N:$N,$E:$E,E1073,$C:$C,C1073,$A:$A,"<>"&A1073),"") | P1073: =IFERROR(LN('Дивиденды по годам'!I1073),"") | Q1073: =IFERROR('Дивиденды по годам'!G1073/'Дивиденды по годам'!I1073, "") | R1073: =IFERROR(IF(AND('Дивиденды по годам'!N1073<>"",'Дивиденды по годам'!U1073<>"",'Дивиденды по годам'!U1073<>0),'Дивиденды по годам'!N1073/'Дивиденды по годам'!U1073-1,""),"") | S1073: =IFERROR(IF(AND('Дивиденды по годам'!L1073<>"",'Дивиденды по годам'!I1073<>"",'Дивиденды по годам'!J1073<>"",'Дивиденды по годам'!K1073<>"",('Дивиденды по годам'!I1073-'Дивиденды по годам'!J1073-'Дивиденды по годам'!K1073)<>0),'Дивиденды по годам'!L1073/('Дивиденды по годам'!I1073-'Дивиденды по годам'!J1073-'Дивиденды по годам'!K1073),""),"") | T1073: =IFERROR(IF(AND('Дивиденды по годам'!Q1073<>"",'Дивиденды по годам'!I1073<>"",'Дивиденды по годам'!V1073<>"",('Дивиденды по годам'!I1073+'Дивиденды по годам'!V1073)<>0),'Дивиденды по годам'!Q1073/(('Дивиденды по годам'!I1073+'Дивиденды по годам'!V1073)/2),""),"") | U1073: =IFERROR(IF(AND('Дивиденды по годам'!J1073<>"",'Дивиденды по годам'!K1073<>"",'Дивиденды по годам'!M1073<>"",'Дивиденды по годам'!M1073<>0),('Дивиденды по годам'!J1073+'Дивиденды по годам'!K1073)/'Дивиденды по годам'!M1073,""),"") | V1073: {=IFERROR(AVERAGE(_xlfn._xlws.FILTER(P$2:P$1073,($C$2:$C$1073=$C1073)*($E$2:$E$1073=$E1073)*(ROW(P$2:P$1073)<>ROW(P1073))*(P$2:P$1073<>""))),"")} | W1073: {=IFERROR(AVERAGE(_xlfn._xlws.FILTER(Q$2:Q$1073,($C$2:$C$1073=$C1073)*($E$2:$E$1073=$E1073)*(ROW(Q$2:Q$1073)<>ROW(Q1073))*(Q$2:Q$1073<>""))),"")} | X1073: {=IFERROR(AVERAGE(_xlfn._xlws.FILTER(R$2:R$1073,($C$2:$C$1073=$C1073)*($E$2:$E$1073=$E1073)*(ROW(R$2:R$1073)<>ROW(R1073))*(R$2:R$1073<>""))),"")} | Y1073: {=IFERROR(AVERAGE(_xlfn._xlws.FILTER(S$2:S$1073,($C$2:$C$1073=$C1073)*($E$2:$E$1073=$E1073)*(ROW(S$2:S$1073)<>ROW(S1073))*(S$2:S$1073<>""))),"")} | Z1073: {=IFERROR(AVERAGE(_xlfn._xlws.FILTER(T$2:T$1073,($C$2:$C$1073=$C1073)*($E$2:$E$1073=$E1073)*(ROW(T$2:T$1073)<>ROW(T1073))*(T$2:T$1073<>""))),"")} | AA1073: {=IFERROR(AVERAGE(_xlfn._xlws.FILTER(U$2:U$1073,($C$2:$C$1073=$C1073)*($E$2:$E$1073=$E1073)*(ROW(U$2:U$1073)<>ROW(U1073))*(U$2:U$1073<>""))),"")}

Sheet Sheet2
A1: company | B1: Наименование | C1: year | D1: Дивиденд | E1: industry | F1: sum | G1: peer_sum | H1: payout | I1: payout_ratio | J1: abs | K1: pabs | L1: inc | M1: inc_ratio | N1: dec | O1: dec_ratio | P1: Size | Q1: Tangibility | R1: Sales_growth | S1: REBE | T1: ROA | U1: Leverage | V1: Psize | W1: PTangibility | X1: PSales_growth | Y1: PREBE | Z1: PROA | AA1: PLeverage
A2: GAZP | B2: GAZP IV кв. 2024 | C2: 2024 | D2: 0 | E2: 1 | F2: 0 | G2: 214.65 | H2: 0 | I2: 0.83333333 | J2: 0 | K2: 0.033213968 | L2: 0 | M2: 0.66666667 | N2: 0 | O2: 0.16666667 | P2: 31.055227 | Q2: 0.67690981 | R2: 0.25438004 | S2: 0.88491057 | T2: 0.04439204 | U2: 0.73819835 | V2: 28.89571 | W2: 0.51199198 | X2: 0.17118061 | Y2: 0.79852548 | Z2: 0.12177692 | AA2: 0.85190113
A3: GAZP | B3: GAZP IV кв. 2023 | C3: 2023 | D3: 0 | E3: 1 | F3: 0 | G3: 195.35 | H3: 0 | I3: 0.83333333 | J3: -1 | K3: 0.07318505 | L3: 0 | M3: 0.5 | N3: 1 | O3: 0.33333333 | P3: 30.988397 | Q3: 0.64206898 | R3: -0.26830096 | S3: 0.88690206 | T3: -0.021263586 | U3: 0.74522866 | V3: 28.950488 | W3: 0.47348976 | X3: -0.037500665 | Y3: 0.80302193 | Z3: 0.11841775 | AA3: 0.83818778
A4: GAZP | B4: GAZP IV кв. 2022 | C4: 2022 | D4: 51.03 | E4: 1 | F4: 51.03 | G4: 240.50333 | H4: 1 | I4: 0.83333333 | J4: 1 | K4: 0.59952004 | L4: 1 | M4: 0.5 | N4: 0 | O4: 0.16666667 | P4: 30.894064 | Q4: 0.66665802 | R4: 0.13988357 | S4: 0.9197466 | T4: 0.04933207 | U4: 0.58878604 | V4: 28.005023 | W4: 0.45949876 | X4: 0.1038114 | Y4: 0.78172804 | Z4: 0.12952165 | AA4: 0.8837483
A5: GAZP | B5: GAZP IV кв. 2021 | C5: 2021 | D5: 0 | E5: 1 | F5: 0 | G5: 82.756667 | H5: 0 | I5: 0.83333333 | J5: -1 | K5: 1.2307909 | L5: 0 | M5: 0.83333333 | N5: 1 | O5: 0 | P5: 30.928606 | Q5: 0.61646121 | R5: 0.62006761 | S5: 0.92570438 | T5: 0.08567901 | U5: 0.60359905 | V5: 28.588015 | W5: 0.54592305 | X5: 0.71962064 | Y5: 0.78164523 | Z5: 0.12893486 | AA5: 1.1281548
A6: GAZP | B6: GAZP IV кв. 2020 | C6: 2020 | D6: 12.55 | E6: 1 | F6: 12.55 | G6: 54.073333 | H6: 1 | I6: 0.83333333 | J6: -0.17650919 | K6: -0.29877017 | L6: 0 | M6: 0.33333333 | N6: 1 | O6: 0.5 | P6: 30.781712 | Q6: 0.68957552 | R6: -0.17469058 | S6: 0.92655943 | T6: 0.0071806644 | U6: 0.57734601 | V6: 28.624109 | W6: 0.5371219 | X6: -0.27049471 | Y6: 0.74822584 | Z6: 0.032136749 | AA6: 1.2967729
A7: GAZP | B7: GAZP IV кв. 2019 | C7: 2019 | D7: 15.24 | E7: 1 | F7: 15.24 | G7: 112.14333 | H7: 1 | I7: 0.83333333 | J7: -0.082480433 | K7: 0.24288945 | L7: 0 | M7: 0.5 | N7: 1 | O7: 0.16666667 | P7: 30.716701 | Q7: 0.67892385 | R7: -0.068645653 | S7: 0.94282055 | T7: 0.059472199 | U7: 0.49718231 | V7: 28.572217 | W7: 0.51462951 | X7: 0.025367391 | Y7: 0.82043004 | Z7: 0.16320282 | AA7: 0.95146752
A8: GAZP | B8: GAZP IV кв. 2018 | C8: 2018 | D8: 16.61 | E8: 1 | F8: 16.61 | G8: 64.588333 | H8: 1 | I8: 0.83333333 | J8: 1.0659204 | K8: 0.58403361 | L8: 1 | M8: 0.66666667 | N8: 0 | O8: 0 | P8: 30.666476 | Q8: 0.66358203 | R8: 0.25633934 | S8: 0.95895668 | T8: 0.078311239 | U8: 0.5106133 | V8: 28.458498 | W8: 0.50857093 | X8: 0.36447021 | Y8: 0.75475667 | Z8: 0.12546632 | AA8: 0.92459536
A9: GAZP | B9: GAZP IV кв. 2017 | C9: 2017 | D9: 8.04 | E9: 1 | F9: 8.04 | G9: 46.836667 | H9: 1 | I9: 0.83333333 | J9: 0 | K9: 0.2941553 | L9: 0 | M9: 0.83333333 | N9: 0 | O9: 0 | P9: 30.534571 | Q9: 0.68782484 | R9: 0.071197573 | S9: 0.96041191 | T9: 0.043625085 | U9: 0.51793923 | V9: 28.340294 | W9: 0.5242558 | X9: 0.16368052 | Y9: 0.73280408 | Z9: 0.077823093 | AA9: 0.97472196
A10: GAZP | B10: GAZP IV кв. 2016 | C10: 2016 | D10: 8.04 | E10: 1 | F10: 8.04 | G10: 39.715 | H10: 1 | I10: 0.83333333 | J10: 0.019011407 | K10: 0.12024418 | L10: 1 | M10: 0.5 | N10: 0 | O10: 0.16666667 | P10: 30.459455 | Q10: 0.67987406 | R10: 0.0062129136 | S10: 0.96184328 | T10: 0.058703285 | U10: 0.47869044 | V10: 28.279917 | W10: 0.50976916 | X10: 0.012025011 | Y10: 0.68181067 | Z10: 0.10464156 | AA10: 1.0228333
A11: GAZP | B11: GAZP IV кв. 2015 | C11: 2015 | D11: 7.89 | E11: 1 | F11: 7.89 | G11: 35.635 | H11: 1 | I11: 0.83333333 | J11: 0.095833333 | K11: 0.14170092 | L11: 1 | M11: 0.66666667 | N11: 0 | O11: 0.16666667 | P11: 30.467291 | Q11: 0.6453117 | R11: 0.086497916 | S11: 0.94994687 | T11: 0.049966568 | U11: 0.56231155 | V11: 28.027872 | W11: 0.5715191 | X11: 0.11349517 | Y11: 0.93141876 | Z11: 0.083332631 | AA11: -1.2671068
A12: GAZP | B12: GAZP IV кв. 2014 | C12: 2014 | D12: 7.2 | E12: 1 | F12: 7.2 | G12: 30.623333 | H12: 1 | I12: 0.83333333 | J12: 0 | K12: 0.11887241 | L12: 0 | M12: 0.66666667 | N12: 0 | O12: 0.16666667 | P12: 30.350833 | Q12: 0.65559075 | R12: 0.064733003 | S12: 0.94814853 | T12: 0.010987182 | U12: 0.49974689 | V12: 28.372329 | W12: 0.62176756 | X12: 0.16466401 | Y12: 0.98195602 | Z12: 0.071375294 | AA12: 0.86783657
A13: GAZP | B13: GAZP IV кв. 2012 | C13: 2012 | D13: 5.99 | E13: 1 | F13: 5.99 | G13: 19.001667 | H13: 1 | I13: 0.83333333 | J13: -0.33221851 | K13: 0.076735506 | L13: 0 | M13: 0.66666667 | N13: 1 | O13: 0.16666667 | P13: 30.12159 | Q13: 0.64785399 | R13: 0.027457091 | S13: 0.93903491 | T13: 0.10540944 | U13: 0.38696801 | V13: 27.941602 | W13: 0.6129454 | X13: 0.039420032 | Z13: 0.12618572 | AA13: 0.50988452
A14: LKOH | B14: LKOH IV кв. 2025 | C14: 2025 | D14: 397 | E14: 1 | F14: 397 | G14: 11.59 | H14: 1 | I14: 0.5 | J14: -0.62369668 | K14: -0.5190168 | L14: 0 | M14: 0 | N14: 1 | O14: 0.66666667 | P14: 29.331108 | Q14: 0.68588587 | R14: -0.56298308 | S14: 1.1230089 | T14: -0.14364114 | U14: 0.50958002 | V14: 28.648938 | W14: 0.47597261 | X14: -0.084693664 | Y14: 0.92840826 | Z14: 0.060424107 | AA14: 0.43679759
A15: LKOH | B15: LKOH IV кв. 2024 | C15: 2024 | D15: 1055 | E15: 1 | F15: 1055 | G15: 38.816667 | H15: 1 | I15: 0.66666667 | J15: 0.11640212 | K15: 0.013813615 | L15: 1 | M15: 0.5 | N15: 0 | O15: 0.16666667 | P15: 29.859165 | Q15: 0.54042765 | R15: 0.087440906 | S15: 0.82896494 | T15: 0.095236359 | U15: 0.34686712 | V15: 29.134922 | W15: 0.53928841 | X15: 0.20456844 | Y15: 0.81251189 | Z15: 0.11160806 | AA15: 0.93016738
A16: LKOH | B16: LKOH IV кв. 2021 | C16: 2021 | D16: 340 | E16: 1 | F16: 340 | G16: 26.09 | H16: 1 | I16: 0.66666667 | J16: 0.31274131 | K16: 1.0120007 | L16: 1 | M16: 0.66666667 | N16: 0 | O16: 0.16666667 | P16: 29.557421 | Q16: 0.62101761 | R16: 0.67307539 | S16: 0.94628607 | T16: 0.120643 | U16: 0.51768069 | V16: 28.862252 | W16: 0.54501177 | X16: 0.70901908 | Y16: 0.77752889 | Z16: 0.12194206 | AA16: 1.1453385
A17: LKOH | B17: LKOH IV кв. 2020 | C17: 2020 | D17: 259 | E17: 1 | F17: 259 | G17: 12.998333 | H17: 1 | I17: 0.83333333 | J17: -0.52214022 | K17: -0.241165 | L17: 0 | M17: 0.33333333 | N17: 1 | O17: 0.5 | P17: 29.421376 | Q17: 0.7117446 | R17: -0.28080295 | S17: 0.93398101 | T17: 0.0027864171 | U17: 0.4504765 | V17: 28.850832 | W17: 0.53342706 | X17: -0.25280932 | Y17: 0.74698891 | Z17: 0.032869124 | AA17: 1.3179179
A18: LKOH | B18: LKOH IV кв. 2019 | C18: 2019 | D18: 542 | E18: 1 | F18: 542 | G18: 24.35 | H18: 1 | I18: 0.83333333 | J18: 1.168 | K18: 0.03447604 | L18: 1 | M18: 0.33333333 | N18: 0 | O18: 0.33333333 | P18: 29.413916 | Q18: 0.67697548 | R18: -0.024221713 | S18: 1.057806 | T18: 0.1099747 | U18: 0.4966972 | V18: 28.789348 | W18: 0.51495424 | X18: 0.017963401 | Y18: 0.80126581 | Z18: 0.15478573 | AA18: 0.95154837
A19: LKOH | B19: LKOH IV кв. 2018 | C19: 2018 | D19: 250 | E19: 1 | F19: 250 | G19: 25.69 | H19: 1 | I19: 0.83333333 | J19: 0.1627907 | K19: 0.73455523 | L19: 1 | M19: 0.66666667 | N19: 0 | O19: 0 | P19: 29.377152 | Q19: 0.66798828 | R19: 0.35359412 | S19: 0.97302141 | T19: 0.11335429 | U19: 0.40722853 | V19: 28.673386 | W19: 0.50783656 | X19: 0.34826108 | Y19: 0.75241255 | Z19: 0.11962581 | AA19: 0.94182616
A20: LKOH | B20: LKOH IV кв. 2017 | C20: 2017 | D20: 215 | E20: 1 | F20: 215 | G20: 12.343333 | H20: 1 | I20: 0.83333333 | J20: 0.1025641 | K20: 0.27706128 | L20: 1 | M20: 0.66666667 | N20: 0 | O20: 0 | P20: 29.284708 | Q20: 0.68408303 | R20: 0.13576696 | S20: 1.02457 | T20: 0.082106552 | U20: 0.49731163 | V20: 28.548605 | W20: 0.52487944 | X20: 0.15291895 | Y20: 0.72211107 | Z20: 0.071409515 | AA20: 0.97815989
A21: LKOH | B21: LKOH IV кв. 2016 | C21: 2016 | D21: 195 | E21: 1 | F21: 195 | G21: 8.555 | H21: 1 | I21: 0.83333333 | J21: 0.10169492 | K21: 0.1064636 | L21: 1 | M21: 0.5 | N21: 0 | O21: 0.16666667 | P21: 29.243389 | Q21: 0.67628856 | R21: -0.09079848 | S21: 1.0232958 | T21: 0.041382403 | U21: 0.55365397 | V21: 28.482595 | W21: 0.51036674 | X21: 0.03142729 | Y21: 0.66952017 | Z21: 0.10810574 | AA21: 1.0103394
A22: LKOH | B22: LKOH IV кв. 2015 | C22: 2015 | D22: 177 | E22: 1 | F22: 177 | G22: 7.45 | H22: 1 | I22: 0.83333333 | J22: 0.14935065 | K22: 0.13278136 | L22: 1 | M22: 0.66666667 | N22: 0 | O22: 0.16666667 | P22: 29.244572 | Q22: 0.6794304 | R22: 0.028796563 | S22: 0.99938262 | T22: 0.062591509 | U22: 0.55370657 | V22: 28.272415 | W22: 0.56469536 | X22: 0.12792051 | Y22: 0.92153161 | Z22: 0.080176396 | AA22: -1.2653858
A23: LKOH | B23: LKOH IV кв. 2014 | C23: 2014 | D23: 154 | E23: 1 | F23: 154 | G23: 6.1566667 | H23: 1 | I23: 0.83333333 | J23: 0.4 | K23: 0.052205747 | L23: 1 | M23: 0.5 | N23: 0 | O23: 0.16666667 | P23: 29.097405 | Q23: 0.72868515 | R23: 0.23981588 | S23: 1.0364466 | T23: 0.04672791 | U23: 0.37427476 | V23: 28.685686 | W23: 0.60349396 | X23: 0.12089329 | Y23: 0.95252334 | Z23: 0.062440112 | AA23: 0.89920461
A24: NVTK | B24: NVTK IV кв. 2021 | C24: 2021 | D24: 71.44 | E24: 1 | F24: 71.44 | G24: 70.85 | H24: 1 | I24: 0.66666667 | J24: 1.0089989 | K24: 0.89595775 | L24: 1 | M24: 0.66666667 | N24: 0 | O24: 0.16666667 | P24: 28.530232 | Q24: 0.35421482 | R24: 0.62504144 | S24: 0.98415721 | T24: 0.19997202 | U24: 0.2857462 | V24: 29.067689 | W24: 0.59837233 | X24: 0.71862587 | Y24: 0.76995467 | Z24: 0.10607626 | AA24: 1.1917254
A25: NVTK | B25: NVTK IV кв. 2020 | C25: 2020 | D25: 35.56 | E25: 1 | F25: 35.56 | G25: 50.238333 | H25: 1 | I25: 0.83333333 | J25: 0.099907207 | K25: -0.34483957 | L25: 1 | M25: 0.16666667 | N25: 0 | O25: 0.66666667 | P25: 28.353328 | Q25: 0.35422241 | R25: -0.17500055 | S25: 0.97678505 | T25: 0.038597805 | U25: 0.2568018 | V25: 29.02884 | W25: 0.59301409 | X25: -0.27044305 | Y25: 0.7398549 | Z25: 0.026900559 | AA25: 1.350197
... A356: POSI | B356: POSI IV кв. 2021 | C356: 2021 | D356: 0 | E356: 5 | F356: 0 | G356: 0 | H356: 0 | I356: 0 | J356: 0 | K356: 0 | L356: 0 | M356: 0 | N356: 0 | O356: 0 | P356: 22.960963 | Q356: 0.059124874 | R356: 0.27950276 | S356: 0.99063987 | T356: 0.24063218 | U356: 1.6755493 | V356: 22.867511 | W356: 0.03011899 | X356: -0.040523781 | Y356: 0.43827851 | Z356: 0.029047209 | AA356: 17.210609
A357: POSI | B357: POSI IV кв. 2020 | C357: 2020 | D357: 0 | E357: 5 | F357: 0 | G357: 0 | H357: 0 | I357: 0 | J357: 0 | K357: 0 | L357: 0 | M357: 0 | N357: 0 | O357: 0 | P357: 22.60051 | Q357: 0.056237144 | R357: 0.60261811 | S357: 0.98625241 | T357: 0.26070423 | U357: 1.5905917 | V357: 24.198271 | W357: 0.011672549 | Y357: 0.7652293 | AA357: 6.3689254
A358: POSI | B358: POSI IV кв. 2019 | C358: 2019 | D358: 0 | E358: 5 | F358: 0 | G358: 0 | H358: 0 | I358: 0 | J358: 0 | K358: 0 | L358: 0 | M358: 0 | N358: 0 | O358: 0 | P358: 22.346826 | Q358: 0.075056137 | R358: 0.33893564 | S358: 0.96665544 | T358: 0.034488878 | U358: 4.0219461
A359: SOFL | B359: SOFL IV кв. 2024 | C359: 2024 | D359: 0 | E359: 5 | F359: 0 | G359: 120.67778 | H359: 0 | I359: 0.55555556 | J359: 0 | K359: 0.33674983 | L359: 0 | M359: 0.44444444 | N359: 0 | O359: 0.11111111 | P359: 25.317112 | Q359: 0.056273641 | R359: 0.10856643 | S359: 0.50325302 | T359: 0.030036161 | U359: 3.4363979 | V359: 24.578397 | W359: 0.07857655 | X359: 0.33435999 | Y359: 0.22556988 | Z359: 0.28396905 | AA359: 2.575913
A360: SOFL | B360: SOFL IV кв. 2023 | C360: 2023 | D360: 0 | E360: 5 | F360: 0 | G360: 16.477778 | H360: 0 | I360: 0.11111111 | J360: 0 | K360: 0.31688312 | L360: 0 | M360: 0.11111111 | N360: 0 | O360: 0 | P360: 25.034293 | Q360: 0.027510501 | R360: 0.30108808 | S360: 1.1490136 | T360: 0.051605332 | U360: 7.7502349 | V360: 23.889672 | W360: 0.044771405 | X360: 0.5796406 | Y360: 0.60461286 | Z360: 0.24226663 | AA360: 1.1370915
A361: SOFL | B361: SOFL IV кв. 2022 | C361: 2022 | D361: 0 | E361: 5 | F361: 0 | G361: 4.2777778 | H361: 0 | I361: 0.11111111 | J361: 0 | K361: 0.11111111 | L361: 0 | M361: 0.11111111 | N361: 0 | O361: 0 | P361: 24.524871 | Q361: 0.024992741 | R361: -0.1546023 | S361: 0.69300664 | T361: 0.16477792 | U361: 3.5710056 | V361: 24.243774 | W361: 0.067358083 | X361: 1.2227001 | Y361: 0.83534038 | Z361: 0.59897421 | AA361: 1.8103122
A362: SOFL | B362: SOFL IV кв. 2021 | C362: 2021 | D362: 0 | E362: 5 | F362: 0 | G362: 0 | H362: 0 | I362: 0 | J362: 0 | K362: 0 | L362: 0 | M362: 0 | N362: 0 | O362: 0 | P362: 24.247831 | Q362: 0.022393117 | R362: -0.040523781 | S362: 0.18243626 | T362: 0.029047209 | U362: 18.228895 | V362: 22.224077 | W362: 0.048484869 | X362: 0.27950276 | Y362: 0.84238031 | Z362: 0.24063218 | AA362: 8.933936
A363: YDEX | B363: YDEX IV кв. 2025 | C363: 2025 | D363: 80 | E363: 5 | F363: 80 | G363: 54.051111 | H363: 1 | I363: 0.55555556 | J363: -0.5 | K363: 0.24947366 | L363: 0 | M363: 0.44444444 | N363: 1 | O363: 0.33333333 | P363: 27.944621 | Q363: 0.24201917 | R363: 0.31660028 | S363: 0.73713612 | T363: 0.064514011 | U363: 2.8960127 | V363: 25.378142 | W363: 0.094722753 | X363: 0.061966379 | Y363: 0.6499985 | Z363: 0.26553844 | AA363: -1.7867758

Sheet Sheet4
A1: company | B1: Наименование | C1: year | D1: Дивиденд | E1: industry | F1: sum | G1: peer_sum | H1: payout | I1: payout_ratio | J1: abs | K1: pabs | L1: inc | M1: inc_ratio | N1: dec | O1: dec_ratio | P1: Size | Q1: Tangibility | R1: Sales_growth | S1: REBE | T1: ROA | U1: Leverage | V1: Psize | W1: PTangibility | X1: PSales_growth | Y1: PREBE | Z1: PROA | AA1: PLeverage
A2: GAZP | B2: GAZP IV кв. 2024 | C2: 2024 | D2: 0 | E2: 1 | F2: 0 | G2: 214.65 | H2: 0 | I2: 0.83333333 | J2: 0 | K2: 0.033213968 | L2: 0 | M2: 0.66666667 | N2: 0 | O2: 0.16666667 | P2: 31.055227 | Q2: 0.67690981 | R2: 0.25438004 | S2: 0.88491057 | T2: 0.04439204 | U2: 0.73819835 | V2: 28.89571 | W2: 0.51199198 | X2: 0.17118061 | Y2: 0.79852548 | Z2: 0.12177692 | AA2: 0.85190113
A3: GAZP | B3: GAZP IV кв. 2023 | C3: 2023 | D3: 0 | E3: 1 | F3: 0 | G3: 195.35 | H3: 0 | I3: 0.83333333 | J3: -1 | K3: 0.07318505 | L3: 0 | M3: 0.5 | N3: 1 | O3: 0.33333333 | P3: 30.988397 | Q3: 0.64206898 | R3: -0.26830096 | S3: 0.88690206 | T3: -0.021263586 | U3: 0.74522866 | V3: 28.950488 | W3: 0.47348976 | X3: -0.037500665 | Y3: 0.80302193 | Z3: 0.11841775 | AA3: 0.83818778
A4: GAZP | B4: GAZP IV кв. 2022 | C4: 2022 | D4: 51.03 | E4: 1 | F4: 51.03 | G4: 240.50333 | H4: 1 | I4: 0.83333333 | J4: 1 | K4: 0.59952004 | L4: 1 | M4: 0.5 | N4: 0 | O4: 0.16666667 | P4: 30.894064 | Q4: 0.66665802 | R4: 0.13988357 | S4: 0.9197466 | T4: 0.04933207 | U4: 0.58878604 | V4: 28.005023 | W4: 0.45949876 | X4: 0.1038114 | Y4: 0.78172804 | Z4: 0.12952165 | AA4: 0.8837483
A5: GAZP | B5: GAZP IV кв. 2021 | C5: 2021 | D5: 0 | E5: 1 | F5: 0 | G5: 82.756667 | H5: 0 | I5: 0.83333333 | J5: -1 | K5: 1.2307909 | L5: 0 | M5: 0.83333333 | N5: 1 | O5: 0 | P5: 30.928606 | Q5: 0.61646121 | R5: 0.62006761 | S5: 0.92570438 | T5: 0.08567901 | U5: 0.60359905 | V5: 28.588015 | W5: 0.54592305 | X5: 0.71962064 | Y5: 0.78164523 | Z5: 0.12893486 | AA5: 1.1281548
A6: GAZP | B6: GAZP IV кв. 2020 | C6: 2020 | D6: 12.55 | E6: 1 | F6: 12.55 | G6: 54.073333 | H6: 1 | I6: 0.83333333 | J6: -0.17650919 | K6: -0.29877017 | L6: 0 | M6: 0.33333333 | N6: 1 | O6: 0.5 | P6: 30.781712 | Q6: 0.68957552 | R6: -0.17469058 | S6: 0.92655943 | T6: 0.0071806644 | U6: 0.57734601 | V6: 28.624109 | W6: 0.5371219 | X6: -0.27049471 | Y6: 0.74822584 | Z6: 0.032136749 | AA6: 1.2967729
A7: GAZP | B7: GAZP IV кв. 2019 | C7: 2019 | D7: 15.24 | E7: 1 | F7: 15.24 | G7: 112.14333 | H7: 1 | I7: 0.83333333 | J7: -0.082480433 | K7: 0.24288945 | L7: 0 | M7: 0.5 | N7: 1 | O7: 0.16666667 | P7: 30.716701 | Q7: 0.67892385 | R7: -0.068645653 | S7: 0.94282055 | T7: 0.059472199 | U7: 0.49718231 | V7: 28.572217 | W7: 0.51462951 | X7: 0.025367391 | Y7: 0.82043004 | Z7: 0.16320282 | AA7: 0.95146752
A8: GAZP | B8: GAZP IV кв. 2018 | C8: 2018 | D8: 16.61 | E8: 1 | F8: 16.61 | G8: 64.588333 | H8: 1 | I8: 0.83333333 | J8: 1.0659204 | K8: 0.58403361 | L8: 1 | M8: 0.66666667 | N8: 0 | O8: 0 | P8: 30.666476 | Q8: 0.66358203 | R8: 0.25633934 | S8: 0.95895668 | T8: 0.078311239 | U8: 0.5106133 | V8: 28.458498 | W8: 0.50857093 | X8: 0.36447021 | Y8: 0.75475667 | Z8: 0.12546632 | AA8: 0.92459536
A9: GAZP | B9: GAZP IV кв. 2017 | C9: 2017 | D9: 8.04 | E9: 1 | F9: 8.04 | G9: 46.836667 | H9: 1 | I9: 0.83333333 | J9: 0 | K9: 0.2941553 | L9: 0 | M9: 0.83333333 | N9: 0 | O9: 0 | P9: 30.534571 | Q9: 0.68782484 | R9: 0.071197573 | S9: 0.96041191 | T9: 0.043625085 | U9: 0.51793923 | V9: 28.340294 | W9: 0.5242558 | X9: 0.16368052 | Y9: 0.73280408 | Z9: 0.077823093 | AA9: 0.97472196
A10: GAZP | B10: GAZP IV кв. 2016 | C10: 2016 | D10: 8.04 | E10: 1 | F10: 8.04 | G10: 39.715 | H10: 1 | I10: 0.83333333 | J10: 0.019011407 | K10: 0.12024418 | L10: 1 | M10: 0.5 | N10: 0 | O10: 0.16666667 | P10: 30.459455 | Q10: 0.67987406 | R10: 0.0062129136 | S10: 0.96184328 | T10: 0.058703285 | U10: 0.47869044 | V10: 28.279917 | W10: 0.50976916 | X10: 0.012025011 | Y10: 0.68181067 | Z10: 0.10464156 | AA10: 1.0228333
A11: GAZP | B11: GAZP IV кв. 2015 | C11: 2015 | D11: 7.89 | E11: 1 | F11: 7.89 | G11: 35.635 | H11: 1 | I11: 0.83333333 | J11: 0.095833333 | K11: 0.14170092 | L11: 1 | M11: 0.66666667 | N11: 0 | O11: 0.16666667 | P11: 30.467291 | Q11: 0.6453117 | R11: 0.086497916 | S11: 0.94994687 | T11: 0.049966568 | U11: 0.56231155 | V11: 28.027872 | W11: 0.5715191 | X11: 0.11349517 | Y11: 0.93141876 | Z11: 0.083332631 | AA11: -1.2671068
A12: GAZP | B12: GAZP IV кв. 2014 | C12: 2014 | D12: 7.2 | E12: 1 | F12: 7.2 | G12: 30.623333 | H12: 1 | I12: 0.83333333 | J12: 0 | K12: 0.11887241 | L12: 0 | M12: 0.66666667 | N12: 0 | O12: 0.16666667 | P12: 30.350833 | Q12: 0.65559075 | R12: 0.064733003 | S12: 0.94814853 | T12: 0.010987182 | U12: 0.49974689 | V12: 28.372329 | W12: 0.62176756 | X12: 0.16466401 | Y12: 0.98195602 | Z12: 0.071375294 | AA12: 0.86783657
A13: GAZP | B13: GAZP IV кв. 2012 | C13: 2012 | D13: 5.99 | E13: 1 | F13: 5.99 | G13: 19.001667 | H13: 1 | I13: 0.83333333 | J13: -0.33221851 | K13: 0.076735506 | L13: 0 | M13: 0.66666667 | N13: 1 | O13: 0.16666667 | P13: 30.12159 | Q13: 0.64785399 | R13: 0.027457091 | S13: 0.93903491 | T13: 0.10540944 | U13: 0.38696801 | V13: 27.941602 | W13: 0.6129454 | X13: 0.039420032 | Z13: 0.12618572 | AA13: 0.50988452
A14: LKOH | B14: LKOH IV кв. 2025 | C14: 2025 | D14: 397 | E14: 1 | F14: 397 | G14: 11.59 | H14: 1 | I14: 0.5 | J14: -0.62369668 | K14: -0.5190168 | L14: 0 | M14: 0 | N14: 1 | O14: 0.66666667 | P14: 29.331108 | Q14: 0.68588587 | R14: -0.56298308 | S14: 1.1230089 | T14: -0.14364114 | U14: 0.50958002 | V14: 28.648938 | W14: 0.47597261 | X14: -0.084693664 | Y14: 0.92840826 | Z14: 0.060424107 | AA14: 0.43679759
A15: LKOH | B15: LKOH IV кв. 2024 | C15: 2024 | D15: 1055 | E15: 1 | F15: 1055 | G15: 38.816667 | H15: 1 | I15: 0.66666667 | J15: 0.11640212 | K15: 0.013813615 | L15: 1 | M15: 0.5 | N15: 0 | O15: 0.16666667 | P15: 29.859165 | Q15: 0.54042765 | R15: 0.087440906 | S15: 0.82896494 | T15: 0.095236359 | U15: 0.34686712 | V15: 29.134922 | W15: 0.53928841 | X15: 0.20456844 | Y15: 0.81251189 | Z15: 0.11160806 | AA15: 0.93016738
A16: LKOH | B16: LKOH IV кв. 2021 | C16: 2021 | D16: 340 | E16: 1 | F16: 340 | G16: 26.09 | H16: 1 | I16: 0.66666667 | J16: 0.31274131 | K16: 1.0120007 | L16: 1 | M16: 0.66666667 | N16: 0 | O16: 0.16666667 | P16: 29.557421 | Q16: 0.62101761 | R16: 0.67307539 | S16: 0.94628607 | T16: 0.120643 | U16: 0.51768069 | V16: 28.862252 | W16: 0.54501177 | X16: 0.70901908 | Y16: 0.77752889 | Z16: 0.12194206 | AA16: 1.1453385
A17: LKOH | B17: LKOH IV кв. 2020 | C17: 2020 | D17: 259 | E17: 1 | F17: 259 | G17: 12.998333 | H17: 1 | I17: 0.83333333 | J17: -0.52214022 | K17: -0.241165 | L17: 0 | M17: 0.33333333 | N17: 1 | O17: 0.5 | P17: 29.421376 | Q17: 0.7117446 | R17: -0.28080295 | S17: 0.93398101 | T17: 0.0027864171 | U17: 0.4504765 | V17: 28.850832 | W17: 0.53342706 | X17: -0.25280932 | Y17: 0.74698891 | Z17: 0.032869124 | AA17: 1.3179179
A18: LKOH | B18: LKOH IV кв. 2019 | C18: 2019 | D18: 542 | E18: 1 | F18: 542 | G18: 24.35 | H18: 1 | I18: 0.83333333 | J18: 1.168 | K18: 0.03447604 | L18: 1 | M18: 0.33333333 | N18: 0 | O18: 0.33333333 | P18: 29.413916 | Q18: 0.67697548 | R18: -0.024221713 | S18: 1.057806 | T18: 0.1099747 | U18: 0.4966972 | V18: 28.789348 | W18: 0.51495424 | X18: 0.017963401 | Y18: 0.80126581 | Z18: 0.15478573 | AA18: 0.95154837
A19: LKOH | B19: LKOH IV кв. 2018 | C19: 2018 | D19: 250 | E19: 1 | F19: 250 | G19: 25.69 | H19: 1 | I19: 0.83333333 | J19: 0.1627907 | K19: 0.73455523 | L19: 1 | M19: 0.66666667 | N19: 0 | O19: 0 | P19: 29.377152 | Q19: 0.66798828 | R19: 0.35359412 | S19: 0.97302141 | T19: 0.11335429 | U19: 0.40722853 | V19: 28.673386 | W19: 0.50783656 | X19: 0.34826108 | Y19: 0.75241255 | Z19: 0.11962581 | AA19: 0.94182616
A20: LKOH | B20: LKOH IV кв. 2017 | C20: 2017 | D20: 215 | E20: 1 | F20: 215 | G20: 12.343333 | H20: 1 | I20: 0.83333333 | J20: 0.1025641 | K20: 0.27706128 | L20: 1 | M20: 0.66666667 | N20: 0 | O20: 0 | P20: 29.284708 | Q20: 0.68408303 | R20: 0.13576696 | S20: 1.02457 | T20: 0.082106552 | U20: 0.49731163 | V20: 28.548605 | W20: 0.52487944 | X20: 0.15291895 | Y20: 0.72211107 | Z20: 0.071409515 | AA20: 0.97815989
A21: LKOH | B21: LKOH IV кв. 2016 | C21: 2016 | D21: 195 | E21: 1 | F21: 195 | G21: 8.555 | H21: 1 | I21: 0.83333333 | J21: 0.10169492 | K21: 0.1064636 | L21: 1 | M21: 0.5 | N21: 0 | O21: 0.16666667 | P21: 29.243389 | Q21: 0.67628856 | R21: -0.09079848 | S21: 1.0232958 | T21: 0.041382403 | U21: 0.55365397 | V21: 28.482595 | W21: 0.51036674 | X21: 0.03142729 | Y21: 0.66952017 | Z21: 0.10810574 | AA21: 1.0103394
A22: LKOH | B22: LKOH IV кв. 2015 | C22: 2015 | D22: 177 | E22: 1 | F22: 177 | G22: 7.45 | H22: 1 | I22: 0.83333333 | J22: 0.14935065 | K22: 0.13278136 | L22: 1 | M22: 0.66666667 | N22: 0 | O22: 0.16666667 | P22: 29.244572 | Q22: 0.6794304 | R22: 0.028796563 | S22: 0.99938262 | T22: 0.062591509 | U22: 0.55370657 | V22: 28.272415 | W22: 0.56469536 | X22: 0.12792051 | Y22: 0.92153161 | Z22: 0.080176396 | AA22: -1.2653858
A23: LKOH | B23: LKOH IV кв. 2014 | C23: 2014 | D23: 154 | E23: 1 | F23: 154 | G23: 6.1566667 | H23: 1 | I23: 0.83333333 | J23: 0.4 | K23: 0.052205747 | L23: 1 | M23: 0.5 | N23: 0 | O23: 0.16666667 | P23: 29.097405 | Q23: 0.72868515 | R23: 0.23981588 | S23: 1.0364466 | T23: 0.04672791 | U23: 0.37427476 | V23: 28.685686 | W23: 0.60349396 | X23: 0.12089329 | Y23: 0.95252334 | Z23: 0.062440112 | AA23: 0.89920461
A24: NVTK | B24: NVTK IV кв. 2021 | C24: 2021 | D24: 71.44 | E24: 1 | F24: 71.44 | G24: 70.85 | H24: 1 | I24: 0.66666667 | J24: 1.0089989 | K24: 0.89595775 | L24: 1 | M24: 0.66666667 | N24: 0 | O24: 0.16666667 | P24: 28.530232 | Q24: 0.35421482 | R24: 0.62504144 | S24: 0.98415721 | T24: 0.19997202 | U24: 0.2857462 | V24: 29.067689 | W24: 0.59837233 | X24: 0.71862587 | Y24: 0.76995467 | Z24: 0.10607626 | AA24: 1.1917254
A25: NVTK | B25: NVTK IV кв. 2020 | C25: 2020 | D25: 35.56 | E25: 1 | F25: 35.56 | G25: 50.238333 | H25: 1 | I25: 0.83333333 | J25: 0.099907207 | K25: -0.34483957 | L25: 1 | M25: 0.16666667 | N25: 0 | O25: 0.66666667 | P25: 28.353328 | Q25: 0.35422241 | R25: -0.17500055 | S25: 0.97678505 | T25: 0.038597805 | U25: 0.2568018 | V25: 29.02884 | W25: 0.59301409 | X25: -0.27044305 | Y25: 0.7398549 | Z25: 0.026900559 | AA25: 1.350197
... A243: NLMK | B243: NLMK IV кв. 2014 | C243: 2014 | D243: 2.44 | E243: 3 | F243: 2.44 | G243: 7.612 | H243: 1 | I243: 0.4 | J243: 2.641791 | K243: 0.80913941 | L243: 1 | M243: 0.2 | N243: 0 | O243: 0.1 | P243: 26.723053 | Q243: 0.5637907 | R243: 0.15918712 | S243: 1.937615 | T243: 0.11467508 | U243: 0.64572226 | V243: 26.251014 | W243: 0.51066037 | X243: 0.06728246 | Y243: 0.65216551 | Z243: -0.10156849 | AA243: 1.7357874
A244: NLMK | B244: NLMK IV кв. 2013 | C244: 2013 | D244: 0.67 | E244: 3 | F244: 0.67 | G244: 1.159 | H244: 1 | I244: 0.3 | J244: 0.080645161 | K244: -0.21192863 | L244: 1 | M244: 0.1 | N244: 0 | O244: 0.4 | P244: 26.974931 | Q244: 0.61428066 | R244: -0.079448258 | S244: 1.1343753 | T244: 0.014343134 | U244: 0.58485486 | V244: 26.371645 | W244: 0.57261072 | X244: -0.041361278 | Z244: -0.036794693 | AA244: 3.428944
A245: PLZL | B245: PLZL IV кв. 2025 | C245: 2025 | D245: 106.85 | E245: 3 | F245: 106.85 | G245: 0 | H245: 1 | I245: 0 | J245: -0.47411163 | K245: -0.4 | L245: 0 | M245: 0 | N245: 1 | O245: 0.4 | P245: 27.854492 | Q245: 0.55182744 | R245: 0.025915126 | S245: 2.7813687 | T245: 0.26153393 | U245: 3.5984613 | V245: 27.479092 | W245: 0.52588909 | X245: -0.11078415 | Y245: 0.7305745 | Z245: -0.020145148 | AA245: 3.1280858
A246: PLZL | B246: PLZL IV кв. 2024 | C246: 2024 | D246: 203.18 | E246: 3 | F246: 203.18 | G246: 12.74 | H246: 1 | I246: 0.4 | J246: 1 | K246: -0.30461447 | L246: 1 | M246: 0 | N246: 0 | O246: 0.5 | P246: 27.77243 | Q246: 0.45106802 | R246: 0.47946687 | S246: 4.8244774 | T246: 0.30789416 | U246: 8.0689682 | V246: 27.233916 | W246: 0.48304608 | X246: -0.020135577 | Y246: 0.80743902 | Z246: 0.019286335 | AA246: 2.0143228
A247: PLZL | B247: PLZL IV кв. 2023 | C247: 2023 | D247: 0 | E247: 3 | F247: 0 | G247: 25.244 | H247: 0 | I247: 0.6 | J247: 0 | K247: 0.43287037 | L247: 0 | M247: 0.6 | N247: 0 | O247: 0.1 | P247: 27.448059 | Q247: 0.52760086 | R247: 0.59693879 | S247: -7.7096303 | T247: 0.19763591 | U247: -15.830116 | V247: 27.18713 | W247: 0.44859403 | X247: 0.084229115 | Y247: 0.91939673 | Z247: 0.11047473 | AA247: 0.96980158
A248: PLZL | B248: PLZL IV кв. 2022 | C248: 2022 | D248: 0 | E248: 3 | F248: 0 | G248: 1.73 | H248: 0 | I248: 0.2 | J248: -1 | K248: -0.50242801 | L248: 0 | M248: 0.1 | N248: 1 | O248: 0.7 | P248: 27.273216 | Q248: 0.58055746 | R248: -0.19472969 | S248: 0.75523139 | T248: 0.17282705 | U248: 0.87461024 | V248: 27.063795 | W248: 0.46090922 | X248: -0.0043881041 | Y248: 0.8614753 | Z248: 0.15725398 | AA248: 1.1812319
A249: PLZL | B249: PLZL IV кв. 2021 | C249: 2021 | D249: 26.75 | E249: 3 | F249: 26.75 | G249: 34.18 | H249: 1 | I249: 0.7 | J249: -0.57363723 | K249: 0.78806005 | L249: 0 | M249: 0.5 | N249: 1 | O249: 0.1 | P249: 27.112057 | Q249: 0.59786906 | R249: 0.0026412898 | S249: 0.66471778 | T249: 0.29527149 | U249: 1.2891822 | V249: 26.97209 | W249: 0.47668443 | X249: 0.75116719 | Y249: 1.0724755 | Z249: 0.28656614 | AA249: 2.124058
A250: PLZL | B250: PLZL IV кв. 2020 | C250: 2020 | D250: 62.74 | E250: 3 | F250: 62.74 | G250: 17.71 | H250: 1 | I250: 0.7 | J250: 0.53849926 | K250: 0.60552962 | L250: 1 | M250: 0.6 | N250: 0 | O250: 0.1 | P250: 27.012753 | Q250: 0.56492855 | R250: 0.41300435 | S250: 0.51693789 | T250: 0.23261191 | U250: 1.9828241 | V250: 26.799266 | W250: 0.50023473 | X250: -0.011348966 | Y250: 1.0934065 | Z250: 0.0804675 | AA250: 1.626539
A251: PLZL | B251: PLZL IV кв. 2019 | C251: 2019 | D251: 40.78 | E251: 3 | F251: 40.78 | G251: 15.513 | H251: 1 | I251: 0.7 | J251: 0.48452858 | K251: 0.20315374 | L251: 1 | M251: 0.3 | N251: 0 | O251: 0.4 | P251: 26.968364 | Q251: 0.56203732 | R251: 0.39562082 | S251: 0.36934001 | T251: 0.26766892 | U251: 3.3522091 | V251: 26.688793 | W251: 0.4945854 | X251: 0.0031964825 | Y251: 0.96206482 | Z251: 0.12503483 | AA251: 1.3796844
A252: PLZL | B252: PLZL IV кв. 2018 | C252: 2018 | D252: 27.47 | E252: 3 | F252: 27.47 | G252: 19.948 | H252: 1 | I252: 0.4 | J252: 0.092680986 | K252: 0.11158877 | L252: 1 | M252: 0.4 | N252: 0 | O252: 0.2 | P252: 26.759412 | Q252: 0.61790484 | R252: 0.16400615 | S252: -1.2428048 | T252: 0.073697376 | U252: 12.435629 | V252: 26.551658 | W252: 0.50818084 | X252: 0.22289535 | Y252: 1.1400875 | Z252: 0.1633931 | AA252: 1.3285126
A253: PLZL | B253: PLZL IV кв. 2017 | C253: 2017 | D253: 25.14 | E253: 3 | F253: 25.14 | G253: 13.44197 | H253: 1 | I253: 0.6 | J253: 0.6496063 | K253: 0.067697147 | L253: 1 | M253: 0.4 | N253: 0 | O253: 0.2 | P253: 26.652703 | Q253: 0.62121917 | R253: -0.037315815 | S253: 2.1722561 | T253: 0.19147726 | U253: 8.8277439 | V253: 26.533074 | W253: 0.52735508 | X253: 0.11309034 | Y253: 0.946399 | Z253: 0.11361086 | AA253: 1.2932857
A254: PLZL | B254: PLZL IV кв. 2016 | C254: 2016 | D254: 15.24 | E254: 3 | F254: 15.24 | G254: 10.46265 | H254: 1 | I254: 0.6 | J254: 1 | K254: 0.57820493 | L254: 1 | M254: 0.5 | N254: 0 | O254: 0 | P254: 26.663253 | Q254: 0.51853159 | R254: 0.2292945 | S254: -8.736715 | T254: 0.2840367 | U254: -14.68599 | V254: 26.542737 | W254: 0.50874654 | X254: 0.1263939 | Y254: 0.98456124 | Z254: 0.14856735 | AA254: 1.6400236
A255: PLZL | B255: PLZL IV кв. 2015 | C255: 2015 | D255: 0 | E255: 3 | F255: 0 | G255: 7.12465 | H255: 0 | I255: 0.6 | J255: 0 | K255: 0.88088717 | L255: 0 | M255: 0.5 | N255: 0 | O255: 0.1 | P255: 26.434788 | Q255: 0.40984603 | R255: 0.54489234 | S255: 1.122536 | T255: 0.2803637 | U255: 1.6297283 | V255: 26.350284 | W255: 0.50748324 | X255: 0.22069285 | Y255: 0.94997838 | Z255: -0.005296625 | AA255: 3.133086
A256: PLZL | B256: PLZL IV кв. 2014 | C256: 2014 | D256: 0 | E256: 3 | F256: 0 | G256: 7.856 | H256: 0 | I256: 0.5 | J256: 0 | K256: 1.0733185 | L256: 0 | M256: 0.3 | N256: 0 | O256: 0.1 | P256: 25.952222 | Q256: 0.19734109 | R256: 0.17080414 | S256: 0.77654321 | T256: -0.037425612 | U256: 1.9716049 | V256: 26.336662 | W256: 0.55137699 | X256: 0.065830334 | Y256: 0.79729948 | Z256: -0.082555907 | AA256: 1.5884671
... A391: RTKM | B391: RTKM IV кв. 2016 | C391: 2016 | D391: 5.39 | E391: 5 | F391: 5.39 | G391: 2.5081818 | H391: 1 | I391: 0.090909091 | J391: -0.089527027 | K391: 0.036928922 | L391: 0 | M391: 0.090909091 | N391: 1 | O391: 0 | P391: 27.043462 | Q391: 0.61845984 | R391: 0.00030603151 | S391: 1.2515113 | T391: 0.022130041 | U391: 1.2349487 | V391: 27.023079 | W391: 0.50111301 | X391: 0.010342461 | Y391: 1.0116292 | Z391: 0.087608778 | AA391: 2.7824075
A392: RTKM | B392: RTKM IV кв. 2015 | C392: 2015 | D392: 5.92 | E392: 5 | F392: 5.92 | G392: 1.7836364 | H392: 1 | I392: 0.090909091 | J392: 0.77245509 | K392: -0.021668549 | L392: 1 | M392: 0 | N392: 0 | O392: 0.090909091 | P392: 27.035581 | Q392: 0.61434194 | R392: -0.005292085 | S392: 1.2586396 | T392: 0.026166549 | U392: 1.2082479 | V392: 27.205422 | W392: 0.46322649 | X392: 0.049844434 | Z392: 0.075107046 | AA392: 2.8805851
A393: RTKM | B393: RTKM IV кв. 2014 | C393: 2014 | D393: 3.34 | E393: 5 | F393: 3.34 | G393: 2.3418182 | H393: 1 | I393: 0.090909091 | J393: 0.070512821 | K393: 0.007404015 | L393: 1 | M393: 0.090909091 | N393: 0 | O393: 0 | P393: 27.030697 | Q393: 0.59833332 | R393: 0.028207721 | S393: 1.3141212 | T393: 0.023759785 | U393: 1.2372496 | V393: 27.134964 | W393: 0.49181429 | X393: 0.030907809 | Y393: 0.9745362 | Z393: 0.09574298 | AA393: 2.3996047
A394: AFLT | B394: AFLT IV кв. 2025 | C394: 2025 | D394: 0 | E394: 7 | F394: 0 | G394: 3.885 | H394: 0 | I394: 0.25 | J394: -1 | K394: -0.43027638 | L394: 0 | M394: 0 | N394: 1 | O394: 0.5 | P394: 27.750136 | Q394: 0.20332375 | R394: 0.053077493 | S394: -1.8248334 | T394: 0.092410643 | U394: 21.216286 | V394: 27.082018 | X394: -0.37000559 | Z394: -0.090250579 | AA394: 0.48847456
A395: AFLT | B395: AFLT IV кв. 2024 | C395: 2024 | D395: 5.27 | E395: 7 | F395: 5.27 | G395: 14.17 | H395: 1 | I395: 0.5 | J395: 1 | K395: -0.058540696 | L395: 1 | M395: 0.5 | N395: 0 | O395: 0.25 | P395: 27.776762 | Q395: 0.13816108 | R395: 0.39953185 | S395: 2.4344732 | T395: 0.048456346 | U395: -16.957847 | V395: 25.813752 | W395: 0.57972858 | X395: 0.053049539 | Y395: 0.96431525 | Z395: 0.17878716 | AA395: 0.35604449
A396: AFLT | B396: AFLT IV кв. 2023 | C396: 2023 | D396: 0 | E396: 7 | F396: 0 | G396: 13.76 | H396: 0 | I396: 0.75 | J396: 0 | K396: 1.1429063 | L396: 0 | M396: 0.5 | N396: 0 | O396: 0.25 | P396: 27.738991 | Q396: 0.094183736 | R396: 0.48117663 | S396: 2.3795796 | T396: -0.01353941 | U396: -12.280697 | V396: 25.681333 | W396: 0.61605557 | X396: 0.3820057 | Y396: 0.95923622 | Z396: 0.23176754 | AA396: 0.38321192
A397: AFLT | B397: AFLT IV кв. 2022 | C397: 2022 | D397: 0 | E397: 7 | F397: 0 | G397: 4.9275 | H397: 0 | I397: 0.75 | J397: 0 | K397: 0.50510721 | L397: 0 | M397: 0.75 | N397: 0 | O397: 0 | P397: 27.5872 | Q397: 0.051264986 | R397: -0.15947069 | S397: 2.2763567 | T397: -0.048748291 | U397: -10.634937 | V397: 25.000884 | W397: 0.58868761 | X397: 0.10434991 | Y397: 0.98454231 | Z397: 0.21973922 | AA397: 0.44474173
A398: AFLT | B398: AFLT IV кв. 2021 | C398: 2021 | D398: 0 | E398: 7 | F398: 0 | G398: 2.51 | H398: 0 | I398: 0.5 | J398: 0 | K398: 1.6381617 | L398: 0 | M398: 0.25 | N398: 0 | O398: 0.5 | P398: 27.734886 | Q398: 0.017930506 | R398: 0.62727429 | S398: 1.2003032 | T398: -0.032422963 | U398: -8.5762439 | V398: 25.225056 | W398: 0.73565058 | X398: 0.20451264 | Y398: 0.90769575 | Z398: 0.21242607 | AA398: 0.76122645
A399: AFLT | B399: AFLT IV кв. 2020 | C399: 2020 | D399: 0 | E399: 7 | F399: 0 | G399: 5.98 | H399: 0 | I399: 0.75 | J399: 0 | K399: 0.34820128 | L399: 0 | M399: 0.5 | N399: 0 | O399: 0.25 | P399: 27.647095 | Q399: 0.019508878 | R399: -0.55422559 | S399: 1.2281657 | T399: -0.12639816 | U399: -9.8100498 | V399: 25.206343 | W399: 0.64526632 | X399: -0.1414357 | Y399: 1.371214 | Z399: 0.09457332 | AA399: 3.1778964
A400: AFLT | B400: AFLT IV кв. 2019 | C400: 2019 | D400: 0 | E400: 7 | F400: 0 | G400: 2.1675 | H400: 0 | I400: 0.5 | J400: -1 | K400: -0.16226904 | L400: 0 | M400: 0.25 | N400: 1 | O400: 0.25 | P400: 27.562012 | Q400: 0.028653685 | R400: 0.10842749 | S400: -12.333846 | T400: 0.021620169 | U400: 477.62462 | V400: 25.280184 | W400: 0.57867734 | X400: 0.10567902 | Y400: 0.69735536 | Z400: 0.1140502 | AA400: 3.2827195
A401: AFLT | B401: AFLT IV кв. 2018 | C401: 2018 | D401: 2.69 | E401: 7 | F401: 2.69 | G401: 6.4975 | H401: 1 | I401: 0.5 | J401: -0.79000781 | K401: 0.31089582 | L401: 0 | M401: 0.5 | N401: 1 | O401: 0 | P401: 26.480987 | Q401: 0.28729163 | R401: 0.14755298 | S401: 1.6534245 | T401: 0.017854352 | U401: 5.9841403 | V401: 25.109305 | W401: 0.65255935 | X401: 0.4315659 | Y401: 1.0566343 | Z401: 0.14082304 | AA401: 5.4840806
A402: AFLT | B402: AFLT IV кв. 2017 | C402: 2017 | D402: 12.81 | E402: 7 | F402: 12.81 | G402: 4.9675 | H402: 1 | I402: 0.25 | J402: -0.26716247 | K402: -0.079737733 | L402: 0 | M402: 0.25 | N402: 1 | O402: 0.25 | P402: 26.501939 | Q402: 0.3028856 | R402: 0.074723723 | S402: 1.2106569 | T402: 0.074072052 | U402: 3.8043805 | V402: 25.031809 | W402: 0.57372214 | X402: 0.082180777 | Y402: 0.24925231 | Z402: 0.18816039 | AA402: 5.6713513
A403: AFLT | B403: AFLT IV кв. 2016 | C403: 2016 | D403: 17.48 | E403: 7 | F403: 17.48 | G403: 3.280475 | H403: 1 | I403: 0.5 | J403: 1 | K403: 0.16982759 | L403: 1 | M403: 0.25 | N403: 0 | O403: 0.25 | P403: 26.424736 | Q403: 0.35046624 | R403: 0.19439366 | S403: 1.8935466 | T403: 0.12636595 | U403: 6.341534 | V403: 24.894869 | W403: 0.612634 | X403: 0.051988083 | Y403: 1.1589953 | Z403: 0.026029278 | AA403: -0.29108212
A404: NKHP | B404: NKHP IV кв. 2024 | C404: 2024 | D404: 55.72 | E404: 7 | F404: 55.72 | G404: 1.5575 | H404: 1 | I404: 0.5 | J404: 0.51908397 | K404: 0.061688312 | L404: 1 | M404: 0.5 | N404: 0 | O404: 0.25 | P404: 23.634426 | Q404: 0.60637055 | R404: 0.207329 | S404: 0.995743 | T404: 0.36334365 | U404: 0.15758863 | V404: 26.849336 | W404: 0.46267621 | X404: 0.10110025 | Y404: 1.443892 | Z404: 0.10006534 | AA404: -3.9228143
A405: NKHP | B405: NKHP IV кв. 2023 | C405: 2023 | D405: 36.68 | E405: 7 | F405: 36.68 | G405: 4.59 | H405: 1 | I405: 0.5 | J405: 1.5088919 | K405: 0.76568328 | L405: 1 | M405: 0.25 | N405: 0 | O405: 0.25 | P405: 23.550438 | Q405: 0.67520162 | R405: 0.86249318 | S405: 0.99483371 | T405: 0.33210353 | U405: 0.29144576 | V405: 26.728472 | W405: 0.4708011 | X405: 0.25490019 | Y405: 1.6516091 | Z405: 0.11655323 | AA405: -2.7598239
A406: NKHP | B406: NKHP IV кв. 2022 | C406: 2022 | D406: 14.62 | E406: 7 | F406: 14.62 | G406: 1.2725 | H406: 1 | I406: 0.5 | J406: 0.53894737 | K406: 0.37037037 | L406: 1 | M406: 0.5 | N406: 0 | O406: 0 | P406: 23.251806 | Q406: 0.83648439 | R406: -0.22160913 | S406: 0.99395382 | T406: 0.16398491 | U406: 0.12120337 | V406: 26.446015 | W406: 0.32694781 | X406: 0.13541913 | Y406: 1.6257438 | Z406: 0.11337262 | AA406: -3.1406384
... A440: SMLT | B440: SMLT IV кв. 2017 | C440: 2017 | D440: 0 | E440: 8 | F440: 0 | G440: 26 | H440: 0 | I440: 0.33333333 | J440: 0 | K440: 0 | L440: 0 | M440: 0 | N440: 0 | O440: 0 | P440: 24.61208 | Q440: 0.0055559621 | R440: 0.68857683 | S440: 0.60998433 | T440: 0.081462871 | U440: 11.702186 | V440: 26.178909 | W440: 0.065835834 | X440: 1.1633474 | Y440: 0.54206004 | Z440: 0.035432781 | AA440: 3.0400083

Sheet Sheet3
A1: company | B1: Наименование | C1: year | D1: Дивиденд | E1: industry | F1: sum | G1: peer_sum | H1: payout | I1: payout_ratio | J1: abs | K1: pabs | L1: inc | M1: inc_ratio | N1: dec | O1: dec_ratio | P1: Size | Q1: Tangibility | R1: Sales_growth | S1: REBE | T1: ROA | U1: Leverage | V1: Leverage1 | W1: Assets | X1: Psize | Y1: PTangibility | Z1: PSales_growth | AA1: PREBE | AB1: PROA | AC1: PLeverage | AD1: PLeverage1 | AE1: ПРОВЕРКА REBE
A2: GAZP | B2: =A2&" "& "IV" &" кв. "&C2 -> GAZP IV кв. 2025 | C2: 2025 | D2: =SUMIFS(Дивиденды!$C:$C,Дивиденды!$A:$A,A2,Дивиденды!$I:$I,C2) -> 0 | E2: 1 | F2: =D2 -> 0 | G2: =AVERAGEIFS($D:$D,$E:$E,E2,$C:$C,C2,$A:$A,"<>"&A2) -> 77.756667 | H2: =IF(D2>0,1,0) -> 0 | I2: =IFERROR((COUNTIFS($E:$E,E2,$C:$C,C2,$H:$H,1)-H2)/(COUNTIFS($E:$E,E2,$C:$C,C2)-1),0) -> 0.66666667 | J2: =IF(A3<>A2,"",IF(D2=D3,0,IF(AND(D3=0,D2<>0), 1,(D2-D3)/D3))) -> 0 | K2: =IFERROR(AVERAGEIFS($J:$J,$E:$E,E2,$C:$C,C2,$A:$A,"<>"&A2),"") -> -0.62296625 | L2: =IF(J2<>"",IF(J2>0,1,0),"") -> 0 | M2: =IFERROR(AVERAGEIFS($L:$L,$E:$E,E2,$C:$C,C2,$A:$A,"<>"&A2),"") -> 0 | N2: =IF(J2<>"",IF(J2<0,1,0),"") -> 0 | O2: =IFERROR(AVERAGEIFS($N:$N,$E:$E,E2,$C:$C,C2,$A:$A,"<>"&A2),"") -> 0.83333333 | P2: =IFERROR(LN('Дивиденды по годам'!I2),"") | Q2: =IFERROR('Дивиденды по годам'!G2/'Дивиденды по годам'!I2, "") | R2: =IFERROR(IF(AND('Дивиденды по годам'!N2<>"",'Дивиденды по годам'!U2<>"",'Дивиденды по годам'!U2<>0),'Дивиденды по годам'!N2/'Дивиденды по годам'!U2-1,""),"") | S2: =IFERROR(IF(AND('Дивиденды по годам'!L2<>"",'Дивиденды по годам'!I2<>"",'Дивиденды по годам'!J2<>"",'Дивиденды по годам'!K2<>"",('Дивиденды по годам'!I2-'Дивиденды по годам'!J2-'Дивиденды по годам'!K2)<>0),'Дивиденды по годам'!L2/('Дивиденды по годам'!I2-'Дивиденды по годам'!J2-'Дивиденды по годам'!K2),""),"") | T2: =IFERROR(IF(AND('Дивиденды по годам'!Q2<>"",'Дивиденды по годам'!I2<>"",'Дивиденды по годам'!V2<>"",('Дивиденды по годам'!I2+'Дивиденды по годам'!V2)<>0),'Дивиденды по годам'!Q2/(('Дивиденды по годам'!I2+'Дивиденды по годам'!V2)/2),""),"") | U2: =IFERROR(IF(AND('Дивиденды по годам'!J2<>"",'Дивиденды по годам'!K2<>"",'Дивиденды по годам'!M2<>"",'Дивиденды по годам'!M2<>0),('Дивиденды по годам'!J2+'Дивиденды по годам'!K2)/'Дивиденды по годам'!M2,""),"") | V2: =IFERROR(IF(AND('Дивиденды по годам'!J2<>"",'Дивиденды по годам'!K2<>"",'Дивиденды по годам'!M2<>"",'Дивиденды по годам'!I2<>0),('Дивиденды по годам'!J2+'Дивиденды по годам'!K2)/'Дивиденды по годам'!I2,""),"") | W2: =IFERROR('Дивиденды по годам'!I2,"") | X2: {=IFERROR(AVERAGE(_xlfn._xlws.FILTER(P$2:P$1073,($C$2:$C$1073=$C2)*($E$2:$E$1073=$E2)*(ROW(P$2:P$1073)<>ROW(P2))*(P$2:P$1073<>""))),"")} -> 28.307188 | Y2: {=IFERROR(AVERAGE(_xlfn._xlws.FILTER(Q$2:Q$1073,($C$2:$C$1073=$C2)*($E$2:$E$1073=$E2)*(ROW(Q$2:Q$1073)<>ROW(Q2))*(Q$2:Q$1073<>""))),"")} -> 0.53419344 | Z2: {=IFERROR(AVERAGE(_xlfn._xlws.FILTER(R$2:R$1073,($C$2:$C$1073=$C2)*($E$2:$E$1073=$E2)*(ROW(R$2:R$1073)<>ROW(R2))*(R$2:R$1073<>""))),"")} -> -0.25128972 | AA2: {=IFERROR(AVERAGE(_xlfn._xlws.FILTER(S$2:S$1073,($C$2:$C$1073=$C2)*($E$2:$E$1073=$E2)*(ROW(S$2:S$1073)<>ROW(S2))*(S$2:S$1073<>""))),"")} -> 0.71039154 | AB2: {=IFERROR(AVERAGE(_xlfn._xlws.FILTER(T$2:T$1073,($C$2:$C$1073=$C2)*($E$2:$E$1073=$E2)*(ROW(T$2:T$1073)<>ROW(T2))*(T$2:T$1073<>""))),"")} -> 0.011099136 | AC2: {=IFERROR(AVERAGE(_xlfn._xlws.FILTER(U$2:U$1073,($C$2:$C$1073=$C2)*($E$2:$E$1073=$E2)*(ROW(U$2:U$1073)<>ROW(U2))*(U$2:U$1073<>""))),"")} -> 0.71283761 | AD2: {=IFERROR(AVERAGE(_xlfn._xlws.FILTER(V$2:V$1073,($C$2:$C$1073=$C2)*($E$2:$E$1073=$E2)*(ROW(V$2:V$1073)<>ROW(V2))*(V$2:V$1073<>""))),"")} -> 0.37992268 | AE2: =IF('Дивиденды по годам'!M2<0,1,0) -> 0
A3: GAZP | B3: =A3&" "& "IV" &" кв. "&C3 -> GAZP IV кв. 2024 | C3: 2024 | D3: =SUMIFS(Дивиденды!$C:$C,Дивиденды!$A:$A,A3,Дивиденды!$I:$I,C3) -> 0 | E3: 1 | F3: =D3 -> 0 | G3: =AVERAGEIFS($D:$D,$E:$E,E3,$C:$C,C3,$A:$A,"<>"&A3) -> 214.65 | H3: =IF(D3>0,1,0) -> 0 | I3: =IFERROR((COUNTIFS($E:$E,E3,$C:$C,C3,$H:$H,1)-H3)/(COUNTIFS($E:$E,E3,$C:$C,C3)-1),0) -> 0.83333333 | J3: =IF(A4<>A3,"",IF(D3=D4,0,IF(AND(D4=0,D3<>0), 1,(D3-D4)/D4))) -> 0 | K3: =IFERROR(AVERAGEIFS($J:$J,$E:$E,E3,$C:$C,C3,$A:$A,"<>"&A3),"") -> 0.033213968 | L3: =IF(J3<>"",IF(J3>0,1,0),"") -> 0 | M3: =IFERROR(AVERAGEIFS($L:$L,$E:$E,E3,$C:$C,C3,$A:$A,"<>"&A3),"") -> 0.66666667 | N3: =IF(J3<>"",IF(J3<0,1,0),"") -> 0 | O3: =IFERROR(AVERAGEIFS($N:$N,$E:$E,E3,$C:$C,C3,$A:$A,"<>"&A3),"") -> 0.16666667 | P3: =IFERROR(LN('Дивиденды по годам'!I3),"") -> 31.055227 | Q3: =IFERROR('Дивиденды по годам'!G3/'Дивиденды по годам'!I3, "") -> 0.67690981 | R3: =IFERROR(IF(AND('Дивиденды по годам'!N3<>"",'Дивиденды по годам'!U3<>"",'Дивиденды по годам'!U3<>0),'Дивиденды по годам'!N3/'Дивиденды по годам'!U3-1,""),"") -> 0.25438004 | S3: =IFERROR(IF(AND('Дивиденды по годам'!L3<>"",'Дивиденды по годам'!I3<>"",'Дивиденды по годам'!J3<>"",'Дивиденды по годам'!K3<>"",('Дивиденды по годам'!I3-'Дивиденды по годам'!J3-'Дивиденды по годам'!K3)<>0),'Дивиденды по годам'!L3/('Дивиденды по годам'!I3-'Дивиденды по годам'!J3-'Дивиденды по годам'!K3),""),"") -> 0.88491057 | T3: =IFERROR(IF(AND('Дивиденды по годам'!Q3<>"",'Дивиденды по годам'!I3<>"",'Дивиденды по годам'!V3<>"",('Дивиденды по годам'!I3+'Дивиденды по годам'!V3)<>0),'Дивиденды по годам'!Q3/(('Дивиденды по годам'!I3+'Дивиденды по годам'!V3)/2),""),"") -> 0.04439204 | U3: =IFERROR(IF(AND('Дивиденды по годам'!J3<>"",'Дивиденды по годам'!K3<>"",'Дивиденды по годам'!M3<>"",'Дивиденды по годам'!M3<>0),('Дивиденды по годам'!J3+'Дивиденды по годам'!K3)/'Дивиденды по годам'!M3,""),"") -> 0.73819835 | V3: =IFERROR(IF(AND('Дивиденды по годам'!J3<>"",'Дивиденды по годам'!K3<>"",'Дивиденды по годам'!M3<>"",'Дивиденды по годам'!I3<>0),('Дивиденды по годам'!J3+'Дивиденды по годам'!K3)/'Дивиденды по годам'!I3,""),"") -> 0.42469166 | W3: =IFERROR('Дивиденды по годам'!I3,"") -> 30698255000000 | X3: {=IFERROR(AVERAGE(_xlfn._xlws.FILTER(P$2:P$1073,($C$2:$C$1073=$C3)*($E$2:$E$1073=$E3)*(ROW(P$2:P$1073)<>ROW(P3))*(P$2:P$1073<>""))),"")} -> 28.89571 | Y3: {=IFERROR(AVERAGE(_xlfn._xlws.FILTER(Q$2:Q$1073,($C$2:$C$1073=$C3)*($E$2:$E$1073=$E3)*(ROW(Q$2:Q$1073)<>ROW(Q3))*(Q$2:Q$1073<>""))),"")} -> 0.51199198 | Z3: {=IFERROR(AVERAGE(_xlfn._xlws.FILTER(R$2:R$1073,($C$2:$C$1073=$C3)*($E$2:$E$1073=$E3)*(ROW(R$2:R$1073)<>ROW(R3))*(R$2:R$1073<>""))),"")} -> 0.17118061 | AA3: {=IFERROR(AVERAGE(_xlfn._xlws.FILTER(S$2:S$1073,($C$2:$C$1073=$C3)*($E$2:$E$1073=$E3)*(ROW(S$2:S$1073)<>ROW(S3))*(S$2:S$1073<>""))),"")} -> 0.79852548 | AB3: {=IFERROR(AVERAGE(_xlfn._xlws.FILTER(T$2:T$1073,($C$2:$C$1073=$C3)*($E$2:$E$1073=$E3)*(ROW(T$2:T$1073)<>ROW(T3))*(T$2:T$1073<>""))),"")} -> 0.12177692 | AC3: {=IFERROR(AVERAGE(_xlfn._xlws.FILTER(U$2:U$1073,($C$2:$C$1073=$C3)*($E$2:$E$1073=$E3)*(ROW(U$2:U$1073)<>ROW(U3))*(U$2:U$1073<>""))),"")} -> 0.85190113 | AD3: {=IFERROR(AVERAGE(_xlfn._xlws.FILTER(V$2:V$1073,($C$2:$C$1073=$C3)*($E$2:$E$1073=$E3)*(ROW(V$2:V$1073)<>ROW(V3))*(V$2:V$1073<>""))),"")} -> 0.41548489 | AE3: =IF('Дивиденды по годам'!M3<0,1,0) -> 0
A4: GAZP | B4: =A4&" "& "IV" &" кв. "&C4 -> GAZP IV кв. 2023 | C4: 2023 | D4: =SUMIFS(Дивиденды!$C:$C,Дивиденды!$A:$A,A4,Дивиденды!$I:$I,C4) -> 0 | E4: 1 | F4: =D4 -> 0 | G4: =AVERAGEIFS($D:$D,$E:$E,E4,$C:$C,C4,$A:$A,"<>"&A4) -> 195.35 | H4: =IF(D4>0,1,0) -> 0 | I4: =IFERROR((COUNTIFS($E:$E,E4,$C:$C,C4,$H:$H,1)-H4)/(COUNTIFS($E:$E,E4,$C:$C,C4)-1),0) -> 0.83333333 | J4: =IF(A5<>A4,"",IF(D4=D5,0,IF(AND(D5=0,D4<>0), 1,(D4-D5)/D5))) -> -1 | K4: =IFERROR(AVERAGEIFS($J:$J,$E:$E,E4,$C:$C,C4,$A:$A,"<>"&A4),"") -> 0.07318505 | L4: =IF(J4<>"",IF(J4>0,1,0),"") -> 0 | M4: =IFERROR(AVERAGEIFS($L:$L,$E:$E,E4,$C:$C,C4,$A:$A,"<>"&A4),"") -> 0.5 | N4: =IF(J4<>"",IF(J4<0,1,0),"") -> 1 | O4: =IFERROR(AVERAGEIFS($N:$N,$E:$E,E4,$C:$C,C4,$A:$A,"<>"&A4),"") -> 0.33333333 | P4: =IFERROR(LN('Дивиденды по годам'!I4),"") -> 30.988397 | Q4: =IFERROR('Дивиденды по годам'!G4/'Дивиденды по годам'!I4, "") -> 0.64206898 | R4: =IFERROR(IF(AND('Дивиденды по годам'!N4<>"",'Дивиденды по годам'!U4<>"",'Дивиденды по годам'!U4<>0),'Дивиденды по годам'!N4/'Дивиденды по годам'!U4-1,""),"") -> -0.26830096 | S4: =IFERROR(IF(AND('Дивиденды по годам'!L4<>"",'Дивиденды по годам'!I4<>"",'Дивиденды по годам'!J4<>"",'Дивиденды по годам'!K4<>"",('Дивиденды по годам'!I4-'Дивиденды по годам'!J4-'Дивиденды по годам'!K4)<>0),'Дивиденды по годам'!L4/('Дивиденды по годам'!I4-'Дивиденды по годам'!J4-'Дивиденды по годам'!K4),""),"") -> 0.88690206 | T4: =IFERROR(IF(AND('Дивиденды по годам'!Q4<>"",'Дивиденды по годам'!I4<>"",'Дивиденды по годам'!V4<>"",('Дивиденды по годам'!I4+'Дивиденды по годам'!V4)<>0),'Дивиденды по годам'!Q4/(('Дивиденды по годам'!I4+'Дивиденды по годам'!V4)/2),""),"") -> -0.021263586 | U4: =IFERROR(IF(AND('Дивиденды по годам'!J4<>"",'Дивиденды по годам'!K4<>"",'Дивиденды по годам'!M4<>"",'Дивиденды по годам'!M4<>0),('Дивиденды по годам'!J4+'Дивиденды по годам'!K4)/'Дивиденды по годам'!M4,""),"") -> 0.74522866 | V4: =IFERROR(IF(AND('Дивиденды по годам'!J4<>"",'Дивиденды по годам'!K4<>"",'Дивиденды по годам'!M4<>"",'Дивиденды по годам'!I4<>0),('Дивиденды по годам'!J4+'Дивиденды по годам'!K4)/'Дивиденды по годам'!I4,""),"") -> 0.42700918 | W4: =IFERROR('Дивиденды по годам'!I4,"") -> 28713748000000 | X4: {=IFERROR(AVERAGE(_xlfn._xlws.FILTER(P$2:P$1073,($C$2:$C$1073=$C4)*($E$2:$E$1073=$E4)*(ROW(P$2:P$1073)<>ROW(P4))*(P$2:P$1073<>""))),"")} -> 28.950488 | Y4: {=IFERROR(AVERAGE(_xlfn._xlws.FILTER(Q$2:Q$1073,($C$2:$C$1073=$C4)*($E$2:$E$1073=$E4)*(ROW(Q$2:Q$1073)<>ROW(Q4))*(Q$2:Q$1073<>""))),"")} -> 0.47348976 | Z4: {=IFERROR(AVERAGE(_xlfn._xlws.FILTER(R$2:R$1073,($C$2:$C$1073=$C4)*($E$2:$E$1073=$E4)*(ROW(R$2:R$1073)<>ROW(R4))*(R$2:R$1073<>""))),"")} -> -0.037500665 | AA4: {=IFERROR(AVERAGE(_xlfn._xlws.FILTER(S$2:S$1073,($C$2:$C$1073=$C4)*($E$2:$E$1073=$E4)*(ROW(S$2:S$1073)<>ROW(S4))*(S$2:S$1073<>""))),"")} -> 0.80302193 | AB4: {=IFERROR(AVERAGE(_xlfn._xlws.FILTER(T$2:T$1073,($C$2:$C$1073=$C4)*($E$2:$E$1073=$E4)*(ROW(T$2:T$1073)<>ROW(T4))*(T$2:T$1073<>""))),"")} -> 0.11841775 | AC4: {=IFERROR(AVERAGE(_xlfn._xlws.FILTER(U$2:U$1073,($C$2:$C$1073=$C4)*($E$2:$E$1073=$E4)*(ROW(U$2:U$1073)<>ROW(U4))*(U$2:U$1073<>""))),"")} -> 0.83818778 | AD4: {=IFERROR(AVERAGE(_xlfn._xlws.FILTER(V$2:V$1073,($C$2:$C$1073=$C4)*($E$2:$E$1073=$E4)*(ROW(V$2:V$1073)<>ROW(V4))*(V$2:V$1073<>""))),"")} -> 0.3725424 | AE4: =IF('Дивиденды по годам'!M4<0,1,0) -> 0
A5: GAZP | B5: =A5&" "& "IV" &" кв. "&C5 -> GAZP IV кв. 2022 | C5: 2022 | D5: =SUMIFS(Дивиденды!$C:$C,Дивиденды!$A:$A,A5,Дивиденды!$I:$I,C5) -> 51.03 | E5: 1 | F5: =D5 -> 51.03 | G5: =AVERAGEIFS($D:$D,$E:$E,E5,$C:$C,C5,$A:$A,"<>"&A5) -> 240.50333 | H5: =IF(D5>0,1,0) -> 1 | I5: =IFERROR((COUNTIFS($E:$E,E5,$C:$C,C5,$H:$H,1)-H5)/(COUNTIFS($E:$E,E5,$C:$C,C5)-1),0) -> 0.83333333 | J5: =IF(A6<>A5,"",IF(D5=D6,0,IF(AND(D6=0,D5<>0), 1,(D5-D6)/D6))) -> 1 | K5: =IFERROR(AVERAGEIFS($J:$J,$E:$E,E5,$C:$C,C5,$A:$A,"<>"&A5),"") -> 0.59952004 | L5: =IF(J5<>"",IF(J5>0,1,0),"") -> 1 | M5: =IFERROR(AVERAGEIFS($L:$L,$E:$E,E5,$C:$C,C5,$A:$A,"<>"&A5),"") -> 0.5 | N5: =IF(J5<>"",IF(J5<0,1,0),"") -> 0 | O5: =IFERROR(AVERAGEIFS($N:$N,$E:$E,E5,$C:$C,C5,$A:$A,"<>"&A5),"") -> 0.16666667 | P5: =IFERROR(LN('Дивиденды по годам'!I5),"") -> 30.894064 | Q5: =IFERROR('Дивиденды по годам'!G5/'Дивиденды по годам'!I5, "") -> 0.66665802 | R5: =IFERROR(IF(AND('Дивиденды по годам'!N5<>"",'Дивиденды по годам'!U5<>"",'Дивиденды по годам'!U5<>0),'Дивиденды по годам'!N5/'Дивиденды по годам'!U5-1,""),"") -> 0.13988357 | S5: =IFERROR(IF(AND('Дивиденды по годам'!L5<>"",'Дивиденды по годам'!I5<>"",'Дивиденды по годам'!J5<>"",'Дивиденды по годам'!K5<>"",('Дивиденды по годам'!I5-'Дивиденды по годам'!J5-'Дивиденды по годам'!K5)<>0),'Дивиденды по годам'!L5/('Дивиденды по годам'!I5-'Дивиденды по годам'!J5-'Дивиденды по годам'!K5),""),"") -> 0.9197466 | T5: =IFERROR(IF(AND('Дивиденды по годам'!Q5<>"",'Дивиденды по годам'!I5<>"",'Дивиденды по годам'!V5<>"",('Дивиденды по годам'!I5+'Дивиденды по годам'!V5)<>0),'Дивиденды по годам'!Q5/(('Дивиденды по годам'!I5+'Дивиденды по годам'!V5)/2),""),"") -> 0.04933207 | U5: =IFERROR(IF(AND('Дивиденды по годам'!J5<>"",'Дивиденды по годам'!K5<>"",'Дивиденды по годам'!M5<>"",'Дивиденды по годам'!M5<>0),('Дивиденды по годам'!J5+'Дивиденды по годам'!K5)/'Дивиденды по годам'!M5,""),"") -> 0.58878604 | V5: =IFERROR(IF(AND('Дивиденды по годам'!J5<>"",'Дивиденды по годам'!K5<>"",'Дивиденды по годам'!M5<>"",'Дивиденды по годам'!I5<>0),('Дивиденды по годам'!J5+'Дивиденды по годам'!K5)/'Дивиденды по годам'!I5,""),"") -> 0.37058863 | W5: =IFERROR('Дивиденды по годам'!I5,"") -> 26128929000000 | X5: {=IFERROR(AVERAGE(_xlfn._xlws.FILTER(P$2:P$1073,($C$2:$C$1073=$C5)*($E$2:$E$1073=$E5)*(ROW(P$2:P$1073)<>ROW(P5))*(P$2:P$1073<>""))),"")} -> 28.005023 | Y5: {=IFERROR(AVERAGE(_xlfn._xlws.FILTER(Q$2:Q$1073,($C$2:$C$1073=$C5)*($E$2:$E$1073=$E5)*(ROW(Q$2:Q$1073)<>ROW(Q5))*(Q$2:Q$1073<>""))),"")} -> 0.45949876 | Z5: {=IFERROR(AVERAGE(_xlfn._xlws.FILTER(R$2:R$1073,($C$2:$C$1073=$C5)*($E$2:$E$1073=$E5)*(ROW(R$2:R$1073)<>ROW(R5))*(R$2:R$1073<>""))),"")} -> 0.1038114 | AA5: {=IFERROR(AVERAGE(_xlfn._xlws.FILTER(S$2:S$1073,($C$2:$C$1073=$C5)*($E$2:$E$1073=$E5)*(ROW(S$2:S$1073)<>ROW(S5))*(S$2:S$1073<>""))),"")} -> 0.78172804 | AB5: {=IFERROR(AVERAGE(_xlfn._xlws.FILTER(T$2:T$1073,($C$2:$C$1073=$C5)*($E$2:$E$1073=$E5)*(ROW(T$2:T$1073)<>ROW(T5))*(T$2:T$1073<>""))),"")} -> 0.12952165 | AC5: {=IFERROR(AVERAGE(_xlfn._xlws.FILTER(U$2:U$1073,($C$2:$C$1073=$C5)*($E$2:$E$1073=$E5)*(ROW(U$2:U$1073)<>ROW(U5))*(U$2:U$1073<>""))),"")} -> 0.8837483 | AD5: {=IFERROR(AVERAGE(_xlfn._xlws.FILTER(V$2:V$1073,($C$2:$C$1073=$C5)*($E$2:$E$1073=$E5)*(ROW(V$2:V$1073)<>ROW(V5))*(V$2:V$1073<>""))),"")} -> 0.37181706 | AE5: =IF('Дивиденды по годам'!M5<0,1,0) -> 0
A6: GAZP | B6: =A6&" "& "IV" &" кв. "&C6 -> GAZP IV кв. 2021 | C6: 2021 | D6: =SUMIFS(Дивиденды!$C:$C,Дивиденды!$A:$A,A6,Дивиденды!$I:$I,C6) -> 0 | E6: 1 | F6: =D6 -> 0 | G6: =AVERAGEIFS($D:$D,$E:$E,E6,$C:$C,C6,$A:$A,"<>"&A6) -> 82.756667 | H6: =IF(D6>0,1,0) -> 0 | I6: =IFERROR((COUNTIFS($E:$E,E6,$C:$C,C6,$H:$H,1)-H6)/(COUNTIFS($E:$E,E6,$C:$C,C6)-1),0) -> 0.83333333 | J6: =IF(A7<>A6,"",IF(D6=D7,0,IF(AND(D7=0,D6<>0), 1,(D6-D7)/D7))) -> -1 | K6: =IFERROR(AVERAGEIFS($J:$J,$E:$E,E6,$C:$C,C6,$A:$A,"<>"&A6),"") -> 1.2307909 | L6: =IF(J6<>"",IF(J6>0,1,0),"") -> 0 | M6: =IFERROR(AVERAGEIFS($L:$L,$E:$E,E6,$C:$C,C6,$A:$A,"<>"&A6),"") -> 0.83333333 | N6: =IF(J6<>"",IF(J6<0,1,0),"") -> 1 | O6: =IFERROR(AVERAGEIFS($N:$N,$E:$E,E6,$C:$C,C6,$A:$A,"<>"&A6),"") -> 0 | P6: =IFERROR(LN('Дивиденды по годам'!I6),"") -> 30.928606 | Q6: =IFERROR('Дивиденды по годам'!G6/'Дивиденды по годам'!I6, "") -> 0.61646121 | R6: =IFERROR(IF(AND('Дивиденды по годам'!N6<>"",'Дивиденды по годам'!U6<>"",'Дивиденды по годам'!U6<>0),'Дивиденды по годам'!N6/'Дивиденды по годам'!U6-1,""),"") -> 0.62006761 | S6: =IFERROR(IF(AND('Дивиденды по годам'!L6<>"",'Дивиденды по годам'!I6<>"",'Дивиденды по годам'!J6<>"",'Дивиденды по годам'!K6<>"",('Дивиденды по годам'!I6-'Дивиденды по годам'!J6-'Дивиденды по годам'!K6)<>0),'Дивиденды по годам'!L6/('Дивиденды по годам'!I6-'Дивиденды по годам'!J6-'Дивиденды по годам'!K6),""),"") -> 0.92570438 | T6: =IFERROR(IF(AND('Дивиденды по годам'!Q6<>"",'Дивиденды по годам'!I6<>"",'Дивиденды по годам'!V6<>"",('Дивиденды по годам'!I6+'Дивиденды по годам'!V6)<>0),'Дивиденды по годам'!Q6/(('Дивиденды по годам'!I6+'Дивиденды по годам'!V6)/2),""),"") -> 0.08567901 | U6: =IFERROR(IF(AND('Дивиденды по годам'!J6<>"",'Дивиденды по годам'!K6<>"",'Дивиденды по годам'!M6<>"",'Дивиденды по годам'!M6<>0),('Дивиденды по годам'!J6+'Дивиденды по годам'!K6)/'Дивиденды по годам'!M6,""),"") -> 0.60359905 | V6: =IFERROR(IF(AND('Дивиденды по годам'!J6<>"",'Дивиденды по годам'!K6<>"",'Дивиденды по годам'!M6<>"",'Дивиденды по годам'!I6<>0),('Дивиденды по годам'!J6+'Дивиденды по годам'!K6)/'Дивиденды по годам'!I6,""),"") -> 0.37640272 | W6: =IFERROR('Дивиденды по годам'!I6,"") -> 27047230000000 | X6: {=IFERROR(AVERAGE(_xlfn._xlws.FILTER(P$2:P$1073,($C$2:$C$1073=$C6)*($E$2:$E$1073=$E6)*(ROW(P$2:P$1073)<>ROW(P6))*(P$2:P$1073<>""))),"")} -> 28.588015 | Y6: {=IFERROR(AVERAGE(_xlfn._xlws.FILTER(Q$2:Q$1073,($C$2:$C$1073=$C6)*($E$2:$E$1073=$E6)*(ROW(Q$2:Q$1073)<>ROW(Q6))*(Q$2:Q$1073<>""))),"")} -> 0.54592305 | Z6: {=IFERROR(AVERAGE(_xlfn._xlws.FILTER(R$2:R$1073,($C$2:$C$1073=$C6)*($E$2:$E$1073=$E6)*(ROW(R$2:R$1073)<>ROW(R6))*(R$2:R$1073<>""))),"")} -> 0.71962064 | AA6: {=IFERROR(AVERAGE(_xlfn._xlws.FILTER(S$2:S$1073,($C$2:$C$1073=$C6)*($E$2:$E$1073=$E6)*(ROW(S$2:S$1073)<>ROW(S6))*(S$2:S$1073<>""))),"")} -> 0.78164523 | AB6: {=IFERROR(AVERAGE(_xlfn._xlws.FILTER(T$2:T$1073,($C$2:$C$1073=$C6)*($E$2:$E$1073=$E6)*(ROW(T$2:T$1073)<>ROW(T6))*(T$2:T$1073<>""))),"")} -> 0.12893486 | AC6: {=IFERROR(AVERAGE(_xlfn._xlws.FILTER(U$2:U$1073,($C$2:$C$1073=$C6)*($E$2:$E$1073=$E6)*(ROW(U$2:U$1073)<>ROW(U6))*(U$2:U$1073<>""))),"")} -> 1.1281548 | AD6: {=IFERROR(AVERAGE(_xlfn._xlws.FILTER(V$2:V$1073,($C$2:$C$1073=$C6)*($E$2:$E$1073=$E6)*(ROW(V$2:V$1073)<>ROW(V6))*(V$2:V$1073<>""))),"")} -> 0.45428997 | AE6: =IF('Дивиденды по годам'!M6<0,1,0) -> 0
A7: GAZP | B7: =A7&" "& "IV" &" кв. "&C7 -> GAZP IV кв. 2020 | C7: 2020 | D7: =SUMIFS(Дивиденды!$C:$C,Дивиденды!$A:$A,A7,Дивиденды!$I:$I,C7) -> 12.55 | E7: 1 | F7: =D7 -> 12.55 | G7: =AVERAGEIFS($D:$D,$E:$E,E7,$C:$C,C7,$A:$A,"<>"&A7) -> 54.073333 | H7: =IF(D7>0,1,0) -> 1 | I7: =IFERROR((COUNTIFS($E:$E,E7,$C:$C,C7,$H:$H,1)-H7)/(COUNTIFS($E:$E,E7,$C:$C,C7)-1),0) -> 0.83333333 | J7: =IF(A8<>A7,"",IF(D7=D8,0,IF(AND(D8=0,D7<>0), 1,(D7-D8)/D8))) -> -0.17650919 | K7: =IFERROR(AVERAGEIFS($J:$J,$E:$E,E7,$C:$C,C7,$A:$A,"<>"&A7),"") -> -0.29877017 | L7: =IF(J7<>"",IF(J7>0,1,0),"") -> 0 | M7: =IFERROR(AVERAGEIFS($L:$L,$E:$E,E7,$C:$C,C7,$A:$A,"<>"&A7),"") -> 0.33333333 | N7: =IF(J7<>"",IF(J7<0,1,0),"") -> 1 | O7: =IFERROR(AVERAGEIFS($N:$N,$E:$E,E7,$C:$C,C7,$A:$A,"<>"&A7),"") -> 0.5 | P7: =IFERROR(LN('Дивиденды по годам'!I7),"") -> 30.781712 | Q7: =IFERROR('Дивиденды по годам'!G7/'Дивиденды по годам'!I7, "") -> 0.68957552 | R7: =IFERROR(IF(AND('Дивиденды по годам'!N7<>"",'Дивиденды по годам'!U7<>"",'Дивиденды по годам'!U7<>0),'Дивиденды по годам'!N7/'Дивиденды по годам'!U7-1,""),"") -> -0.17469058 | S7: =IFERROR(IF(AND('Дивиденды по годам'!L7<>"",'Дивиденды по годам'!I7<>"",'Дивиденды по годам'!J7<>"",'Дивиденды по годам'!K7<>"",('Дивиденды по годам'!I7-'Дивиденды по годам'!J7-'Дивиденды по годам'!K7)<>0),'Дивиденды по годам'!L7/('Дивиденды по годам'!I7-'Дивиденды по годам'!J7-'Дивиденды по годам'!K7),""),"") -> 0.92655943 | T7: =IFERROR(IF(AND('Дивиденды по годам'!Q7<>"",'Дивиденды по годам'!I7<>"",'Дивиденды по годам'!V7<>"",('Дивиденды по годам'!I7+'Дивиденды по годам'!V7)<>0),'Дивиденды по годам'!Q7/(('Дивиденды по годам'!I7+'Дивиденды по годам'!V7)/2),""),"") -> 0.0071806644 | U7: =IFERROR(IF(AND('Дивиденды по годам'!J7<>"",'Дивиденды по годам'!K7<>"",'Дивиденды по годам'!M7<>"",'Дивиденды по годам'!M7<>0),('Дивиденды по годам'!J7+'Дивиденды по годам'!K7)/'Дивиденды по годам'!M7,""),"") -> 0.57734601 | V7: =IFERROR(IF(AND('Дивиденды по годам'!J7<>"",'Дивиденды по годам'!K7<>"",'Дивиденды по годам'!M7<>"",'Дивиденды по годам'!I7<>0),('Дивиденды по годам'!J7+'Дивиденды по годам'!K7)/'Дивиденды по годам'!I7,""),"") -> 0.36602369 | W7: =IFERROR('Дивиденды по годам'!I7,"") -> 23352185000000 | X7: {=IFERROR(AVERAGE(_xlfn._xlws.FILTER(P$2:P$1073,($C$2:$C$1073=$C7)*($E$2:$E$1073=$E7)*(ROW(P$2:P$1073)<>ROW(P7))*(P$2:P$1073<>""))),"")} -> 28.624109 | Y7: {=IFERROR(AVERAGE(_xlfn._xlws.FILTER(Q$2:Q$1073,($C$2:$C$1073=$C7)*($E$2:$E$1073=$E7)*(ROW(Q$2:Q$1073)<>ROW(Q7))*(Q$2:Q$1073<>""))),"")} -> 0.5371219 | Z7: {=IFERROR(AVERAGE(_xlfn._xlws.FILTER(R$2:R$1073,($C$2:$C$1073=$C7)*($E$2:$E$1073=$E7)*(ROW(R$2:R$1073)<>ROW(R7))*(R$2:R$1073<>""))),"")} -> -0.27049471 | AA7: {=IFERROR(AVERAGE(_xlfn._xlws.FILTER(S$2:S$1073,($C$2:$C$1073=$C7)*($E$2:$E$1073=$E7)*(ROW(S$2:S$1073)<>ROW(S7))*(S$2:S$1073<>""))),"")} -> 0.74822584 | AB7: {=IFERROR(AVERAGE(_xlfn._xlws.FILTER(T$2:T$1073,($C$2:$C$1073=$C7)*($E$2:$E$1073=$E7)*(ROW(T$2:T$1073)<>ROW(T7))*(T$2:T$1073<>""))),"")} -> 0.032136749 | AC7: {=IFERROR(AVERAGE(_xlfn._xlws.FILTER(U$2:U$1073,($C$2:$C$1073=$C7)*($E$2:$E$1073=$E7)*(ROW(U$2:U$1073)<>ROW(U7))*(U$2:U$1073<>""))),"")} -> 1.2967729 | AD7: {=IFERROR(AVERAGE(_xlfn._xlws.FILTER(V$2:V$1073,($C$2:$C$1073=$C7)*($E$2:$E$1073=$E7)*(ROW(V$2:V$1073)<>ROW(V7))*(V$2:V$1073<>""))),"")} -> 0.40716346 | AE7: =IF('Дивиденды по годам'!M7<0,1,0) -> 0
A8: GAZP | B8: =A8&" "& "IV" &" кв. "&C8 -> GAZP IV кв. 2019 | C8: 2019 | D8: =SUMIFS(Дивиденды!$C:$C,Дивиденды!$A:$A,A8,Дивиденды!$I:$I,C8) -> 15.24 | E8: 1 | F8: =D8 -> 15.24 | G8: =AVERAGEIFS($D:$D,$E:$E,E8,$C:$C,C8,$A:$A,"<>"&A8) -> 112.14333 | H8: =IF(D8>0,1,0) -> 1 | I8: =IFERROR((COUNTIFS($E:$E,E8,$C:$C,C8,$H:$H,1)-H8)/(COUNTIFS($E:$E,E8,$C:$C,C8)-1),0) -> 0.83333333 | J8: =IF(A9<>A8,"",IF(D8=D9,0,IF(AND(D9=0,D8<>0), 1,(D8-D9)/D9))) -> -0.082480433 | K8: =IFERROR(AVERAGEIFS($J:$J,$E:$E,E8,$C:$C,C8,$A:$A,"<>"&A8),"") -> 0.24288945 | L8: =IF(J8<>"",IF(J8>0,1,0),"") -> 0 | M8: =IFERROR(AVERAGEIFS($L:$L,$E:$E,E8,$C:$C,C8,$A:$A,"<>"&A8),"") -> 0.5 | N8: =IF(J8<>"",IF(J8<0,1,0),"") -> 1 | O8: =IFERROR(AVERAGEIFS($N:$N,$E:$E,E8,$C:$C,C8,$A:$A,"<>"&A8),"") -> 0.16666667 | P8: =IFERROR(LN('Дивиденды по годам'!I8),"") -> 30.716701 | Q8: =IFERROR('Дивиденды по годам'!G8/'Дивиденды по годам'!I8, "") -> 0.67892385 | R8: =IFERROR(IF(AND('Дивиденды по годам'!N8<>"",'Дивиденды по годам'!U8<>"",'Дивиденды по годам'!U8<>0),'Дивиденды по годам'!N8/'Дивиденды по годам'!U8-1,""),"") -> -0.068645653 | S8: =IFERROR(IF(AND('Дивиденды по годам'!L8<>"",'Дивиденды по годам'!I8<>"",'Дивиденды по годам'!J8<>"",'Дивиденды по годам'!K8<>"",('Дивиденды по годам'!I8-'Дивиденды по годам'!J8-'Дивиденды по годам'!K8)<>0),'Дивиденды по годам'!L8/('Дивиденды по годам'!I8-'Дивиденды по годам'!J8-'Дивиденды по годам'!K8),""),"") -> 0.94282055 | T8: =IFERROR(IF(AND('Дивиденды по годам'!Q8<>"",'Дивиденды по годам'!I8<>"",'Дивиденды по годам'!V8<>"",('Дивиденды по годам'!I8+'Дивиденды по годам'!V8)<>0),'Дивиденды по годам'!Q8/(('Дивиденды по годам'!I8+'Дивиденды по годам'!V8)/2),""),"") -> 0.059472199 | U8: =IFERROR(IF(AND('Дивиденды по годам'!J8<>"",'Дивиденды по годам'!K8<>"",'Дивиденды по годам'!M8<>"",'Дивиденды по годам'!M8<>0),('Дивиденды по годам'!J8+'Дивиденды по годам'!K8)/'Дивиденды по годам'!M8,""),"") -> 0.49718231 | V8: =IFERROR(IF(AND('Дивиденды по годам'!J8<>"",'Дивиденды по годам'!K8<>"",'Дивиденды по годам'!M8<>"",'Дивиденды по годам'!I8<>0),('Дивиденды по годам'!J8+'Дивиденды по годам'!K8)/'Дивиденды по годам'!I8,""),"") -> 0.33207867 | W8: =IFERROR('Дивиденды по годам'!I8,"") -> 21882348000000 | X8: {=IFERROR(AVERAGE(_xlfn._xlws.FILTER(P$2:P$1073,($C$2:$C$1073=$C8)*($E$2:$E$1073=$E8)*(ROW(P$2:P$1073)<>ROW(P8))*(P$2:P$1073<>""))),"")} -> 28.572217 | Y8: {=IFERROR(AVERAGE(_xlfn._xlws.FILTER(Q$2:Q$1073,($C$2:$C$1073=$C8)*($E$2:$E$1073=$E8)*(ROW(Q$2:Q$1073)<>ROW(Q8))*(Q$2:Q$1073<>""))),"")} -> 0.51462951 | Z8: {=IFERROR(AVERAGE(_xlfn._xlws.FILTER(R$2:R$1073,($C$2:$C$1073=$C8)*($E$2:$E$1073=$E8)*(ROW(R$2:R$1073)<>ROW(R8))*(R$2:R$1073<>""))),"")} -> 0.025367391 | AA8: {=IFERROR(AVERAGE(_xlfn._xlws.FILTER(S$2:S$1073,($C$2:$C$1073=$C8)*($E$2:$E$1073=$E8)*(ROW(S$2:S$1073)<>ROW(S8))*(S$2:S$1073<>""))),"")} -> 0.82043004 | AB8: {=IFERROR(AVERAGE(_xlfn._xlws.FILTER(T$2:T$1073,($C$2:$C$1073=$C8)*($E$2:$E$1073=$E8)*(ROW(T$2:T$1073)<>ROW(T8))*(T$2:T$1073<>""))),"")} -> 0.16320282 | AC8: {=IFERROR(AVERAGE(_xlfn._xlws.FILTER(U$2:U$1073,($C$2:$C$1073=$C8)*($E$2:$E$1073=$E8)*(ROW(U$2:U$1073)<>ROW(U8))*(U$2:U$1073<>""))),"")} -> 0.95146752 | AD8: {=IFERROR(AVERAGE(_xlfn._xlws.FILTER(V$2:V$1073,($C$2:$C$1073=$C8)*($E$2:$E$1073=$E8)*(ROW(V$2:V$1073)<>ROW(V8))*(V$2:V$1073<>""))),"")} -> 0.39679468 | AE8: =IF('Дивиденды по годам'!M8<0,1,0) -> 0
A9: GAZP | B9: =A9&" "& "IV" &" кв. "&C9 -> GAZP IV кв. 2018 | C9: 2018 | D9: =SUMIFS(Дивиденды!$C:$C,Дивиденды!$A:$A,A9,Дивиденды!$I:$I,C9) -> 16.61 | E9: 1 | F9: =D9 -> 16.61 | G9: =AVERAGEIFS($D:$D,$E:$E,E9,$C:$C,C9,$A:$A,"<>"&A9) -> 64.588333 | H9: =IF(D9>0,1,0) -> 1 | I9: =IFERROR((COUNTIFS($E:$E,E9,$C:$C,C9,$H:$H,1)-H9)/(COUNTIFS($E:$E,E9,$C:$C,C9)-1),0) -> 0.83333333 | J9: =IF(A10<>A9,"",IF(D9=D10,0,IF(AND(D10=0,D9<>0), 1,(D9-D10)/D10))) -> 1.0659204 | K9: =IFERROR(AVERAGEIFS($J:$J,$E:$E,E9,$C:$C,C9,$A:$A,"<>"&A9),"") -> 0.58403361 | L9: =IF(J9<>"",IF(J9>0,1,0),"") -> 1 | M9: =IFERROR(AVERAGEIFS($L:$L,$E:$E,E9,$C:$C,C9,$A:$A,"<>"&A9),"") -> 0.66666667 | N9: =IF(J9<>"",IF(J9<0,1,0),"") -> 0 | O9: =IFERROR(AVERAGEIFS($N:$N,$E:$E,E9,$C:$C,C9,$A:$A,"<>"&A9),"") -> 0 | P9: =IFERROR(LN('Дивиденды по годам'!I9),"") -> 30.666476 | Q9: =IFERROR('Дивиденды по годам'!G9/'Дивиденды по годам'!I9, "") -> 0.66358203 | R9: =IFERROR(IF(AND('Дивиденды по годам'!N9<>"",'Дивиденды по годам'!U9<>"",'Дивиденды по годам'!U9<>0),'Дивиденды по годам'!N9/'Дивиденды по годам'!U9-1,""),"") -> 0.25633934 | S9: =IFERROR(IF(AND('Дивиденды по годам'!L9<>"",'Дивиденды по годам'!I9<>"",'Дивиденды по годам'!J9<>"",'Дивиденды по годам'!K9<>"",('Дивиденды по годам'!I9-'Дивиденды по годам'!J9-'Дивиденды по годам'!K9)<>0),'Дивиденды по годам'!L9/('Дивиденды по годам'!I9-'Дивиденды по годам'!J9-'Дивиденды по годам'!K9),""),"") -> 0.95895668 | T9: =IFERROR(IF(AND('Дивиденды по годам'!Q9<>"",'Дивиденды по годам'!I9<>"",'Дивиденды по годам'!V9<>"",('Дивиденды по годам'!I9+'Дивиденды по годам'!V9)<>0),'Дивиденды по годам'!Q9/(('Дивиденды по годам'!I9+'Дивиденды по годам'!V9)/2),""),"") -> 0.078311239 | U9: =IFERROR(IF(AND('Дивиденды по годам'!J9<>"",'Дивиденды по годам'!K9<>"",'Дивиденды по годам'!M9<>"",'Дивиденды по годам'!M9<>0),('Дивиденды по годам'!J9+'Дивиденды по годам'!K9)/'Дивиденды по годам'!M9,""),"") -> 0.5106133 | V9: =IFERROR(IF(AND('Дивиденды по годам'!J9<>"",'Дивиденды по годам'!K9<>"",'Дивиденды по годам'!M9<>"",'Дивиденды по годам'!I9<>0),('Дивиденды по годам'!J9+'Дивиденды по годам'!K9)/'Дивиденды по годам'!I9,""),"") -> 0.33801722 | W9: =IFERROR('Дивиденды по годам'!I9,"") -> 20810440000000 | X9: {=IFERROR(AVERAGE(_xlfn._xlws.FILTER(P$2:P$1073,($C$2:$C$1073=$C9)*($E$2:$E$1073=$E9)*(ROW(P$2:P$1073)<>ROW(P9))*(P$2:P$1073<>""))),"")} -> 28.458498 | Y9: {=IFERROR(AVERAGE(_xlfn._xlws.FILTER(Q$2:Q$1073,($C$2:$C$1073=$C9)*($E$2:$E$1073=$E9)*(ROW(Q$2:Q$1073)<>ROW(Q9))*(Q$2:Q$1073<>""))),"")} -> 0.50857093 | Z9: {=IFERROR(AVERAGE(_xlfn._xlws.FILTER(R$2:R$1073,($C$2:$C$1073=$C9)*($E$2:$E$1073=$E9)*(ROW(R$2:R$1073)<>ROW(R9))*(R$2:R$1073<>""))),"")} -> 0.36447021 | AA9: {=IFERROR(AVERAGE(_xlfn._xlws.FILTER(S$2:S$1073,($C$2:$C$1073=$C9)*($E$2:$E$1073=$E9)*(ROW(S$2:S$1073)<>ROW(S9))*(S$2:S$1073<>""))),"")} -> 0.75475667 | AB9: {=IFERROR(AVERAGE(_xlfn._xlws.FILTER(T$2:T$1073,($C$2:$C$1073=$C9)*($E$2:$E$1073=$E9)*(ROW(T$2:T$1073)<>ROW(T9))*(T$2:T$1073<>""))),"")} -> 0.12546632 | AC9: {=IFERROR(AVERAGE(_xlfn._xlws.FILTER(U$2:U$1073,($C$2:$C$1073=$C9)*($E$2:$E$1073=$E9)*(ROW(U$2:U$1073)<>ROW(U9))*(U$2:U$1073<>""))),"")} -> 0.92459536 | AD9: {=IFERROR(AVERAGE(_xlfn._xlws.FILTER(V$2:V$1073,($C$2:$C$1073=$C9)*($E$2:$E$1073=$E9)*(ROW(V$2:V$1073)<>ROW(V9))*(V$2:V$1073<>""))),"")} -> 0.39812338 | AE9: =IF('Дивиденды по годам'!M9<0,1,0) -> 0
A10: GAZP | B10: =A10&" "& "IV" &" кв. "&C10 -> GAZP IV кв. 2017 | C10: 2017 | D10: =SUMIFS(Дивиденды!$C:$C,Дивиденды!$A:$A,A10,Дивиденды!$I:$I,C10) -> 8.04 | E10: 1 | F10: =D10 -> 8.04 | G10: =AVERAGEIFS($D:$D,$E:$E,E10,$C:$C,C10,$A:$A,"<>"&A10) -> 46.836667 | H10: =IF(D10>0,1,0) -> 1 | I10: =IFERROR((COUNTIFS($E:$E,E10,$C:$C,C10,$H:$H,1)-H10)/(COUNTIFS($E:$E,E10,$C:$C,C10)-1),0) -> 0.83333333 | J10: =IF(A11<>A10,"",IF(D10=D11,0,IF(AND(D11=0,D10<>0), 1,(D10-D11)/D11))) -> 0 | K10: =IFERROR(AVERAGEIFS($J:$J,$E:$E,E10,$C:$C,C10,$A:$A,"<>"&A10),"") -> 0.2941553 | L10: =IF(J10<>"",IF(J10>0,1,0),"") -> 0 | M10: =IFERROR(AVERAGEIFS($L:$L,$E:$E,E10,$C:$C,C10,$A:$A,"<>"&A10),"") -> 0.83333333 | N10: =IF(J10<>"",IF(J10<0,1,0),"") -> 0 | O10: =IFERROR(AVERAGEIFS($N:$N,$E:$E,E10,$C:$C,C10,$A:$A,"<>"&A10),"") -> 0 | P10: =IFERROR(LN('Дивиденды по годам'!I10),"") -> 30.534571 | Q10: =IFERROR('Дивиденды по годам'!G10/'Дивиденды по годам'!I10, "") -> 0.68782484 | R10: =IFERROR(IF(AND('Дивиденды по годам'!N10<>"",'Дивиденды по годам'!U10<>"",'Дивиденды по годам'!U10<>0),'Дивиденды по годам'!N10/'Дивиденды по годам'!U10-1,""),"") -> 0.071197573 | S10: =IFERROR(IF(AND('Дивиденды по годам'!L10<>"",'Дивиденды по годам'!I10<>"",'Дивиденды по годам'!J10<>"",'Дивиденды по годам'!K10<>"",('Дивиденды по годам'!I10-'Дивиденды по годам'!J10-'Дивиденды по годам'!K10)<>0),'Дивиденды по годам'!L10/('Дивиденды по годам'!I10-'Дивиденды по годам'!J10-'Дивиденды по годам'!K10),""),"") -> 0.96041191 | T10: =IFERROR(IF(AND('Дивиденды по годам'!Q10<>"",'Дивиденды по годам'!I10<>"",'Дивиденды по годам'!V10<>"",('Дивиденды по годам'!I10+'Дивиденды по годам'!V10)<>0),'Дивиденды по годам'!Q10/(('Дивиденды по годам'!I10+'Дивиденды по годам'!V10)/2),""),"") -> 0.043625085 | U10: =IFERROR(IF(AND('Дивиденды по годам'!J10<>"",'Дивиденды по годам'!K10<>"",'Дивиденды по годам'!M10<>"",'Дивиденды по годам'!M10<>0),('Дивиденды по годам'!J10+'Дивиденды по годам'!K10)/'Дивиденды по годам'!M10,""),"") -> 0.51793923 | V10: =IFERROR(IF(AND('Дивиденды по годам'!J10<>"",'Дивиденды по годам'!K10<>"",'Дивиденды по годам'!M10<>"",'Дивиденды по годам'!I10<>0),('Дивиденды по годам'!J10+'Дивиденды по годам'!K10)/'Дивиденды по годам'!I10,""),"") -> 0.3412121 | W10: =IFERROR('Дивиденды по годам'!I10,"") -> 18238770000000 | X10: {=IFERROR(AVERAGE(_xlfn._xlws.FILTER(P$2:P$1073,($C$2:$C$1073=$C10)*($E$2:$E$1073=$E10)*(ROW(P$2:P$1073)<>ROW(P10))*(P$2:P$1073<>""))),"")} -> 28.340294 | Y10: {=IFERROR(AVERAGE(_xlfn._xlws.FILTER(Q$2:Q$1073,($C$2:$C$1073=$C10)*($E$2:$E$1073=$E10)*(ROW(Q$2:Q$1073)<>ROW(Q10))*(Q$2:Q$1073<>""))),"")} -> 0.5242558 | Z10: {=IFERROR(AVERAGE(_xlfn._xlws.FILTER(R$2:R$1073,($C$2:$C$1073=$C10)*($E$2:$E$1073=$E10)*(ROW(R$2:R$1073)<>ROW(R10))*(R$2:R$1073<>""))),"")} -> 0.16368052 | AA10: {=IFERROR(AVERAGE(_xlfn._xlws.FILTER(S$2:S$1073,($C$2:$C$1073=$C10)*($E$2:$E$1073=$E10)*(ROW(S$2:S$1073)<>ROW(S10))*(S$2:S$1073<>""))),"")} -> 0.73280408 | AB10: {=IFERROR(AVERAGE(_xlfn._xlws.FILTER(T$2:T$1073,($C$2:$C$1073=$C10)*($E$2:$E$1073=$E10)*(ROW(T$2:T$1073)<>ROW(T10))*(T$2:T$1073<>""))),"")} -> 0.077823093 | AC10: {=IFERROR(AVERAGE(_xlfn._xlws.FILTER(U$2:U$1073,($C$2:$C$1073=$C10)*($E$2:$E$1073=$E10)*(ROW(U$2:U$1073)<>ROW(U10))*(U$2:U$1073<>""))),"")} -> 0.97472196 | AD10: {=IFERROR(AVERAGE(_xlfn._xlws.FILTER(V$2:V$1073,($C$2:$C$1073=$C10)*($E$2:$E$1073=$E10)*(ROW(V$2:V$1073)<>ROW(V10))*(V$2:V$1073<>""))),"")} -> 0.4081667 | AE10: =IF('Дивиденды по годам'!M10<0,1,0) -> 0
A11: GAZP | B11: =A11&" "& "IV" &" кв. "&C11 -> GAZP IV кв. 2016 | C11: 2016 | D11: =SUMIFS(Дивиденды!$C:$C,Дивиденды!$A:$A,A11,Дивиденды!$I:$I,C11) -> 8.04 | E11: 1 | F11: =D11 -> 8.04 | G11: =AVERAGEIFS($D:$D,$E:$E,E11,$C:$C,C11,$A:$A,"<>"&A11) -> 39.715 | H11: =IF(D11>0,1,0) -> 1 | I11: =IFERROR((COUNTIFS($E:$E,E11,$C:$C,C11,$H:$H,1)-H11)/(COUNTIFS($E:$E,E11,$C:$C,C11)-1),0) -> 0.83333333 | J11: =IF(A12<>A11,"",IF(D11=D12,0,IF(AND(D12=0,D11<>0), 1,(D11-D12)/D12))) -> 0.019011407 | K11: =IFERROR(AVERAGEIFS($J:$J,$E:$E,E11,$C:$C,C11,$A:$A,"<>"&A11),"") -> 0.12024418 | L11: =IF(J11<>"",IF(J11>0,1,0),"") -> 1 | M11: =IFERROR(AVERAGEIFS($L:$L,$E:$E,E11,$C:$C,C11,$A:$A,"<>"&A11),"") -> 0.5 | N11: =IF(J11<>"",IF(J11<0,1,0),"") -> 0 | O11: =IFERROR(AVERAGEIFS($N:$N,$E:$E,E11,$C:$C,C11,$A:$A,"<>"&A11),"") -> 0.16666667 | P11: =IFERROR(LN('Дивиденды по годам'!I11),"") -> 30.459455 | Q11: =IFERROR('Дивиденды по годам'!G11/'Дивиденды по годам'!I11, "") -> 0.67987406 | R11: =IFERROR(IF(AND('Дивиденды по годам'!N11<>"",'Дивиденды по годам'!U11<>"",'Дивиденды по годам'!U11<>0),'Дивиденды по годам'!N11/'Дивиденды по годам'!U11-1,""),"") -> 0.0062129136 | S11: =IFERROR(IF(AND('Дивиденды по годам'!L11<>"",'Дивиденды по годам'!I11<>"",'Дивиденды по годам'!J11<>"",'Дивиденды по годам'!K11<>"",('Дивиденды по годам'!I11-'Дивиденды по годам'!J11-'Дивиденды по годам'!K11)<>0),'Дивиденды по годам'!L11/('Дивиденды по годам'!I11-'Дивиденды по годам'!J11-'Дивиденды по годам'!K11),""),"") -> 0.96184328 | T11: =IFERROR(IF(AND('Дивиденды по годам'!Q11<>"",'Дивиденды по годам'!I11<>"",'Дивиденды по годам'!V11<>"",('Дивиденды по годам'!I11+'Дивиденды по годам'!V11)<>0),'Дивиденды по годам'!Q11/(('Дивиденды по годам'!I11+'Дивиденды по годам'!V11)/2),""),"") -> 0.058703285 | U11: =IFERROR(IF(AND('Дивиденды по годам'!J11<>"",'Дивиденды по годам'!K11<>"",'Дивиденды по годам'!M11<>"",'Дивиденды по годам'!M11<>0),('Дивиденды по годам'!J11+'Дивиденды по годам'!K11)/'Дивиденды по годам'!M11,""),"") -> 0.47869044 | V11: =IFERROR(IF(AND('Дивиденды по годам'!J11<>"",'Дивиденды по годам'!K11<>"",'Дивиденды по годам'!M11<>"",'Дивиденды по годам'!I11<>0),('Дивиденды по годам'!J11+'Дивиденды по годам'!K11)/'Дивиденды по годам'!I11,""),"") -> 0.32372593 | W11: =IFERROR('Дивиденды по годам'!I11,"") -> 16918938000000 | X11: {=IFERROR(AVERAGE(_xlfn._xlws.FILTER(P$2:P$1073,($C$2:$C$1073=$C11)*($E$2:$E$1073=$E11)*(ROW(P$2:P$1073)<>ROW(P11))*(P$2:P$1073<>""))),"")} -> 28.279917 | Y11: {=IFERROR(AVERAGE(_xlfn._xlws.FILTER(Q$2:Q$1073,($C$2:$C$1073=$C11)*($E$2:$E$1073=$E11)*(ROW(Q$2:Q$1073)<>ROW(Q11))*(Q$2:Q$1073<>""))),"")} -> 0.50976916 | Z11: {=IFERROR(AVERAGE(_xlfn._xlws.FILTER(R$2:R$1073,($C$2:$C$1073=$C11)*($E$2:$E$1073=$E11)*(ROW(R$2:R$1073)<>ROW(R11))*(R$2:R$1073<>""))),"")} -> 0.012025011 | AA11: {=IFERROR(AVERAGE(_xlfn._xlws.FILTER(S$2:S$1073,($C$2:$C$1073=$C11)*($E$2:$E$1073=$E11)*(ROW(S$2:S$1073)<>ROW(S11))*(S$2:S$1073<>""))),"")} -> 0.68181067 | AB11: {=IFERROR(AVERAGE(_xlfn._xlws.FILTER(T$2:T$1073,($C$2:$C$1073=$C11)*($E$2:$E$1073=$E11)*(ROW(T$2:T$1073)<>ROW(T11))*(T$2:T$1073<>""))),"")} -> 0.10464156 | AC11: {=IFERROR(AVERAGE(_xlfn._xlws.FILTER(U$2:U$1073,($C$2:$C$1073=$C11)*($E$2:$E$1073=$E11)*(ROW(U$2:U$1073)<>ROW(U11))*(U$2:U$1073<>""))),"")} -> 1.0228333 | AD11: {=IFERROR(AVERAGE(_xlfn._xlws.FILTER(V$2:V$1073,($C$2:$C$1073=$C11)*($E$2:$E$1073=$E11)*(ROW(V$2:V$1073)<>ROW(V11))*(V$2:V$1073<>""))),"")} -> 0.42036601 | AE11: =IF('Дивиденды по годам'!M11<0,1,0) -> 0
A12: GAZP | B12: =A12&" "& "IV" &" кв. "&C12 -> GAZP IV кв. 2015 | C12: 2015 | D12: =SUMIFS(Дивиденды!$C:$C,Дивиденды!$A:$A,A12,Дивиденды!$I:$I,C12) -> 7.89 | E12: 1 | F12: =D12 -> 7.89 | G12: =AVERAGEIFS($D:$D,$E:$E,E12,$C:$C,C12,$A:$A,"<>"&A12) -> 35.635 | H12: =IF(D12>0,1,0) -> 1 | I12: =IFERROR((COUNTIFS($E:$E,E12,$C:$C,C12,$H:$H,1)-H12)/(COUNTIFS($E:$E,E12,$C:$C,C12)-1),0) -> 0.83333333 | J12: =IF(A13<>A12,"",IF(D12=D13,0,IF(AND(D13=0,D12<>0), 1,(D12-D13)/D13))) -> 0.095833333 | K12: =IFERROR(AVERAGEIFS($J:$J,$E:$E,E12,$C:$C,C12,$A:$A,"<>"&A12),"") -> 0.14170092 | L12: =IF(J12<>"",IF(J12>0,1,0),"") -> 1 | M12: =IFERROR(AVERAGEIFS($L:$L,$E:$E,E12,$C:$C,C12,$A:$A,"<>"&A12),"") -> 0.66666667 | N12: =IF(J12<>"",IF(J12<0,1,0),"") -> 0 | O12: =IFERROR(AVERAGEIFS($N:$N,$E:$E,E12,$C:$C,C12,$A:$A,"<>"&A12),"") -> 0.16666667 | P12: =IFERROR(LN('Дивиденды по годам'!I12),"") -> 30.467291 | Q12: =IFERROR('Дивиденды по годам'!G12/'Дивиденды по годам'!I12, "") -> 0.6453117 | R12: =IFERROR(IF(AND('Дивиденды по годам'!N12<>"",'Дивиденды по годам'!U12<>"",'Дивиденды по годам'!U12<>0),'Дивиденды по годам'!N12/'Дивиденды по годам'!U12-1,""),"") -> 0.086497916 | S12: =IFERROR(IF(AND('Дивиденды по годам'!L12<>"",'Дивиденды по годам'!I12<>"",'Дивиденды по годам'!J12<>"",'Дивиденды по годам'!K12<>"",('Дивиденды по годам'!I12-'Дивиденды по годам'!J12-'Дивиденды по годам'!K12)<>0),'Дивиденды по годам'!L12/('Дивиденды по годам'!I12-'Дивиденды по годам'!J12-'Дивиденды по годам'!K12),""),"") -> 0.94994687 | T12: =IFERROR(IF(AND('Дивиденды по годам'!Q12<>"",'Дивиденды по годам'!I12<>"",'Дивиденды по годам'!V12<>"",('Дивиденды по годам'!I12+'Дивиденды по годам'!V12)<>0),'Дивиденды по годам'!Q12/(('Дивиденды по годам'!I12+'Дивиденды по годам'!V12)/2),""),"") -> 0.049966568 | U12: =IFERROR(IF(AND('Дивиденды по годам'!J12<>"",'Дивиденды по годам'!K12<>"",'Дивиденды по годам'!M12<>"",'Дивиденды по годам'!M12<>0),('Дивиденды по годам'!J12+'Дивиденды по годам'!K12)/'Дивиденды по годам'!M12,""),"") -> 0.56231155 | V12: =IFERROR(IF(AND('Дивиденды по годам'!J12<>"",'Дивиденды по годам'!K12<>"",'Дивиденды по годам'!M12<>"",'Дивиденды по годам'!I12<>0),('Дивиденды по годам'!J12+'Дивиденды по годам'!K12)/'Дивиденды по годам'!I12,""),"") -> 0.3599228 | W12: =IFERROR('Дивиденды по годам'!I12,"") -> 17052040000000 | X12: {=IFERROR(AVERAGE(_xlfn._xlws.FILTER(P$2:P$1073,($C$2:$C$1073=$C12)*($E$2:$E$1073=$E12)*(ROW(P$2:P$1073)<>ROW(P12))*(P$2:P$1073<>""))),"")} -> 28.027872 | Y12: {=IFERROR(AVERAGE(_xlfn._xlws.FILTER(Q$2:Q$1073,($C$2:$C$1073=$C12)*($E$2:$E$1073=$E12)*(ROW(Q$2:Q$1073)<>ROW(Q12))*(Q$2:Q$1073<>""))),"")} -> 0.5715191 | Z12: {=IFERROR(AVERAGE(_xlfn._xlws.FILTER(R$2:R$1073,($C$2:$C$1073=$C12)*($E$2:$E$1073=$E12)*(ROW(R$2:R$1073)<>ROW(R12))*(R$2:R$1073<>""))),"")} -> 0.11349517 | AA12: {=IFERROR(AVERAGE(_xlfn._xlws.FILTER(S$2:S$1073,($C$2:$C$1073=$C12)*($E$2:$E$1073=$E12)*(ROW(S$2:S$1073)<>ROW(S12))*(S$2:S$1073<>""))),"")} -> 0.93141876 | AB12: {=IFERROR(AVERAGE(_xlfn._xlws.FILTER(T$2:T$1073,($C$2:$C$1073=$C12)*($E$2:$E$1073=$E12)*(ROW(T$2:T$1073)<>ROW(T12))*(T$2:T$1073<>""))),"")} -> 0.083332631 | AC12: {=IFERROR(AVERAGE(_xlfn._xlws.FILTER(U$2:U$1073,($C$2:$C$1073=$C12)*($E$2:$E$1073=$E12)*(ROW(U$2:U$1073)<>ROW(U12))*(U$2:U$1073<>""))),"")} -> -1.2671068 | AD12: {=IFERROR(AVERAGE(_xlfn._xlws.FILTER(V$2:V$1073,($C$2:$C$1073=$C12)*($E$2:$E$1073=$E12)*(ROW(V$2:V$1073)<>ROW(V12))*(V$2:V$1073<>""))),"")} -> 0.56966747 | AE12: =IF('Дивиденды по годам'!M12<0,1,0) -> 0
A13: GAZP | B13: =A13&" "& "IV" &" кв. "&C13 -> GAZP IV кв. 2014 | C13: 2014 | D13: =SUMIFS(Дивиденды!$C:$C,Дивиденды!$A:$A,A13,Дивиденды!$I:$I,C13) -> 7.2 | E13: 1 | F13: =D13 -> 7.2 | G13: =AVERAGEIFS($D:$D,$E:$E,E13,$C:$C,C13,$A:$A,"<>"&A13) -> 30.623333 | H13: =IF(D13>0,1,0) -> 1 | I13: =IFERROR((COUNTIFS($E:$E,E13,$C:$C,C13,$H:$H,1)-H13)/(COUNTIFS($E:$E,E13,$C:$C,C13)-1),0) -> 0.83333333 | J13: =IF(A14<>A13,"",IF(D13=D14,0,IF(AND(D14=0,D13<>0), 1,(D13-D14)/D14))) -> 0 | K13: =IFERROR(AVERAGEIFS($J:$J,$E:$E,E13,$C:$C,C13,$A:$A,"<>"&A13),"") -> 0.11887241 | L13: =IF(J13<>"",IF(J13>0,1,0),"") -> 0 | M13: =IFERROR(AVERAGEIFS($L:$L,$E:$E,E13,$C:$C,C13,$A:$A,"<>"&A13),"") -> 0.66666667 | N13: =IF(J13<>"",IF(J13<0,1,0),"") -> 0 | O13: =IFERROR(AVERAGEIFS($N:$N,$E:$E,E13,$C:$C,C13,$A:$A,"<>"&A13),"") -> 0.16666667 | P13: =IFERROR(LN('Дивиденды по годам'!I13),"") -> 30.350833 | Q13: =IFERROR('Дивиденды по годам'!G13/'Дивиденды по годам'!I13, "") -> 0.65559075 | R13: =IFERROR(IF(AND('Дивиденды по годам'!N13<>"",'Дивиденды по годам'!U13<>"",'Дивиденды по годам'!U13<>0),'Дивиденды по годам'!N13/'Дивиденды по годам'!U13-1,""),"") -> 0.064733003 | S13: =IFERROR(IF(AND('Дивиденды по годам'!L13<>"",'Дивиденды по годам'!I13<>"",'Дивиденды по годам'!J13<>"",'Дивиденды по годам'!K13<>"",('Дивиденды по годам'!I13-'Дивиденды по годам'!J13-'Дивиденды по годам'!K13)<>0),'Дивиденды по годам'!L13/('Дивиденды по годам'!I13-'Дивиденды по годам'!J13-'Дивиденды по годам'!K13),""),"") -> 0.94814853 | T13: =IFERROR(IF(AND('Дивиденды по годам'!Q13<>"",'Дивиденды по годам'!I13<>"",'Дивиденды по годам'!V13<>"",('Дивиденды по годам'!I13+'Дивиденды по годам'!V13)<>0),'Дивиденды по годам'!Q13/(('Дивиденды по годам'!I13+'Дивиденды по годам'!V13)/2),""),"") -> 0.010987182 | U13: =IFERROR(IF(AND('Дивиденды по годам'!J13<>"",'Дивиденды по годам'!K13<>"",'Дивиденды по годам'!M13<>"",'Дивиденды по годам'!M13<>0),('Дивиденды по годам'!J13+'Дивиденды по годам'!K13)/'Дивиденды по годам'!M13,""),"") -> 0.49974689 | V13: =IFERROR(IF(AND('Дивиденды по годам'!J13<>"",'Дивиденды по годам'!K13<>"",'Дивиденды по годам'!M13<>"",'Дивиденды по годам'!I13<>0),('Дивиденды по годам'!J13+'Дивиденды по годам'!K13)/'Дивиденды по годам'!I13,""),"") -> 0.33322082 | W13: =IFERROR('Дивиденды по годам'!I13,"") -> 15177470000000 | X13: {=IFERROR(AVERAGE(_xlfn._xlws.FILTER(P$2:P$1073,($C$2:$C$1073=$C13)*($E$2:$E$1073=$E13)*(ROW(P$2:P$1073)<>ROW(P13))*(P$2:P$1073<>""))),"")} -> 28.372329 | Y13: {=IFERROR(AVERAGE(_xlfn._xlws.FILTER(Q$2:Q$1073,($C$2:$C$1073=$C13)*($E$2:$E$1073=$E13)*(ROW(Q$2:Q$1073)<>ROW(Q13))*(Q$2:Q$1073<>""))),"")} -> 0.62176756 | Z13: {=IFERROR(AVERAGE(_xlfn._xlws.FILTER(R$2:R$1073,($C$2:$C$1073=$C13)*($E$2:$E$1073=$E13)*(ROW(R$2:R$1073)<>ROW(R13))*(R$2:R$1073<>""))),"")} -> 0.16466401 | AA13: {=IFERROR(AVERAGE(_xlfn._xlws.FILTER(S$2:S$1073,($C$2:$C$1073=$C13)*($E$2:$E$1073=$E13)*(ROW(S$2:S$1073)<>ROW(S13))*(S$2:S$1073<>""))),"")} -> 0.93308346 | AB13: {=IFERROR(AVERAGE(_xlfn._xlws.FILTER(T$2:T$1073,($C$2:$C$1073=$C13)*($E$2:$E$1073=$E13)*(ROW(T$2:T$1073)<>ROW(T13))*(T$2:T$1073<>""))),"")} -> 0.071375294 | AC13: {=IFERROR(AVERAGE(_xlfn._xlws.FILTER(U$2:U$1073,($C$2:$C$1073=$C13)*($E$2:$E$1073=$E13)*(ROW(U$2:U$1073)<>ROW(U13))*(U$2:U$1073<>""))),"")} -> 0.86783657 | AD13: {=IFERROR(AVERAGE(_xlfn._xlws.FILTER(V$2:V$1073,($C$2:$C$1073=$C13)*($E$2:$E$1073=$E13)*(ROW(V$2:V$1073)<>ROW(V13))*(V$2:V$1073<>""))),"")} -> 0.39861041 | AE13: =IF('Дивиденды по годам'!M13<0,1,0) -> 0
... A1072: SMLT | B1072: =A1072&" "& "IV" &" кв. "&C1072 -> SMLT IV кв. 2011 | C1072: 2011 | D1072: =SUMIFS(Дивиденды!$C:$C,Дивиденды!$A:$A,A1072,Дивиденды!$I:$I,C1072) -> 0 | E1072: 8 | F1072: =D1072 -> 0 | G1072: =AVERAGEIFS($D:$D,$E:$E,E1072,$C:$C,C1072,$A:$A,"<>"&A1072) -> 6.6666667 | H1072: =IF(D1072>0,1,0) -> 0 | I1072: =IFERROR((COUNTIFS($E:$E,E1072,$C:$C,C1072,$H:$H,1)-H1072)/(COUNTIFS($E:$E,E1072,$C:$C,C1072)-1),0) -> 0.33333333 | J1072: =IF(A1073<>A1072,"",IF(D1072=D1073,0,IF(AND(D1073=0,D1072<>0), 1,(D1072-D1073)/D1073))) -> 0 | K1072: =IFERROR(AVERAGEIFS($J:$J,$E:$E,E1072,$C:$C,C1072,$A:$A,"<>"&A1072),"") -> 0.11111111 | L1072: =IF(J1072<>"",IF(J1072>0,1,0),"") -> 0 | M1072: =IFERROR(AVERAGEIFS($L:$L,$E:$E,E1072,$C:$C,C1072,$A:$A,"<>"&A1072),"") -> 0.33333333 | N1072: =IF(J1072<>"",IF(J1072<0,1,0),"") -> 0 | O1072: =IFERROR(AVERAGEIFS($N:$N,$E:$E,E1072,$C:$C,C1072,$A:$A,"<>"&A1072),"") -> 0 | P1072: =IFERROR(LN('Дивиденды по годам'!I1072),"") | Q1072: =IFERROR('Дивиденды по годам'!G1072/'Дивиденды по годам'!I1072, "") | R1072: =IFERROR(IF(AND('Дивиденды по годам'!N1072<>"",'Дивиденды по годам'!U1072<>"",'Дивиденды по годам'!U1072<>0),'Дивиденды по годам'!N1072/'Дивиденды по годам'!U1072-1,""),"") | S1072: =IFERROR(IF(AND('Дивиденды по годам'!L1072<>"",'Дивиденды по годам'!I1072<>"",'Дивиденды по годам'!J1072<>"",'Дивиденды по годам'!K1072<>"",('Дивиденды по годам'!I1072-'Дивиденды по годам'!J1072-'Дивиденды по годам'!K1072)<>0),'Дивиденды по годам'!L1072/('Дивиденды по годам'!I1072-'Дивиденды по годам'!J1072-'Дивиденды по годам'!K1072),""),"") | T1072: =IFERROR(IF(AND('Дивиденды по годам'!Q1072<>"",'Дивиденды по годам'!I1072<>"",'Дивиденды по годам'!V1072<>"",('Дивиденды по годам'!I1072+'Дивиденды по годам'!V1072)<>0),'Дивиденды по годам'!Q1072/(('Дивиденды по годам'!I1072+'Дивиденды по годам'!V1072)/2),""),"") | U1072: =IFERROR(IF(AND('Дивиденды по годам'!J1072<>"",'Дивиденды по годам'!K1072<>"",'Дивиденды по годам'!M1072<>"",'Дивиденды по годам'!M1072<>0),('Дивиденды по годам'!J1072+'Дивиденды по годам'!K1072)/'Дивиденды по годам'!M1072,""),"") | V1072: =IFERROR(IF(AND('Дивиденды по годам'!J1072<>"",'Дивиденды по годам'!K1072<>"",'Дивиденды по годам'!M1072<>"",'Дивиденды по годам'!I1072<>0),('Дивиденды по годам'!J1072+'Дивиденды по годам'!K1072)/'Дивиденды по годам'!I1072,""),"") | W1072: =IFERROR('Дивиденды по годам'!I1072,"") | X1072: {=IFERROR(AVERAGE(_xlfn._xlws.FILTER(P$2:P$1073,($C$2:$C$1073=$C1072)*($E$2:$E$1073=$E1072)*(ROW(P$2:P$1073)<>ROW(P1072))*(P$2:P$1073<>""))),"")} -> 25.573846 | Y1072: {=IFERROR(AVERAGE(_xlfn._xlws.FILTER(Q$2:Q$1073,($C$2:$C$1073=$C1072)*($E$2:$E$1073=$E1072)*(ROW(Q$2:Q$1073)<>ROW(Q1072))*(Q$2:Q$1073<>""))),"")} -> 0.18216029 | Z1072: {=IFERROR(AVERAGE(_xlfn._xlws.FILTER(R$2:R$1073,($C$2:$C$1073=$C1072)*($E$2:$E$1073=$E1072)*(ROW(R$2:R$1073)<>ROW(R1072))*(R$2:R$1073<>""))),"")} | AA1072: {=IFERROR(AVERAGE(_xlfn._xlws.FILTER(S$2:S$1073,($C$2:$C$1073=$C1072)*($E$2:$E$1073=$E1072)*(ROW(S$2:S$1073)<>ROW(S1072))*(S$2:S$1073<>""))),"")} | AB1072: {=IFERROR(AVERAGE(_xlfn._xlws.FILTER(T$2:T$1073,($C$2:$C$1073=$C1072)*($E$2:$E$1073=$E1072)*(ROW(T$2:T$1073)<>ROW(T1072))*(T$2:T$1073<>""))),"")} | AC1072: {=IFERROR(AVERAGE(_xlfn._xlws.FILTER(U$2:U$1073,($C$2:$C$1073=$C1072)*($E$2:$E$1073=$E1072)*(ROW(U$2:U$1073)<>ROW(U1072))*(U$2:U$1073<>""))),"")} -> 295.529 | AD1072: {=IFERROR(AVERAGE(_xlfn._xlws.FILTER(V$2:V$1073,($C$2:$C$1073=$C1072)*($E$2:$E$1073=$E1072)*(ROW(V$2:V$1073)<>ROW(V1072))*(V$2:V$1073<>""))),"")} -> 0.78653108 | AE1072: =IF('Дивиденды по годам'!M1072<0,1,0) -> 0
A1073: SMLT | B1073: =A1073&" "& "IV" &" кв. "&C1073 -> SMLT IV кв. 2010 | C1073: 2010 | D1073: =SUMIFS(Дивиденды!$C:$C,Дивиденды!$A:$A,A1073,Дивиденды!$I:$I,C1073) -> 0 | E1073: 8 | F1073: =D1073 -> 0 | G1073: =AVERAGEIFS($D:$D,$E:$E,E1073,$C:$C,C1073,$A:$A,"<>"&A1073) -> 5 | H1073: =IF(D1073>0,1,0) -> 0 | I1073: =IFERROR((COUNTIFS($E:$E,E1073,$C:$C,C1073,$H:$H,1)-H1073)/(COUNTIFS($E:$E,E1073,$C:$C,C1073)-1),0) -> 0.33333333 | J1073: =IF(A1074<>A1073,"",IF(D1073=D1074,0,IF(AND(D1074=0,D1073<>0), 1,(D1073-D1074)/D1074))) | K1073: =IFERROR(AVERAGEIFS($J:$J,$E:$E,E1073,$C:$C,C1073,$A:$A,"<>"&A1073),"") | L1073: =IF(J1073<>"",IF(J1073>0,1,0),"") | M1073: =IFERROR(AVERAGEIFS($L:$L,$E:$E,E1073,$C:$C,C1073,$A:$A,"<>"&A1073),"") | N1073: =IF(J1073<>"",IF(J1073<0,1,0),"") | O1073: =IFERROR(AVERAGEIFS($N:$N,$E:$E,E1073,$C:$C,C1073,$A:$A,"<>"&A1073),"") | P1073: =IFERROR(LN('Дивиденды по годам'!I1073),"") | Q1073: =IFERROR('Дивиденды по годам'!G1073/'Дивиденды по годам'!I1073, "") | R1073: =IFERROR(IF(AND('Дивиденды по годам'!N1073<>"",'Дивиденды по годам'!U1073<>"",'Дивиденды по годам'!U1073<>0),'Дивиденды по годам'!N1073/'Дивиденды по годам'!U1073-1,""),"") | S1073: =IFERROR(IF(AND('Дивиденды по годам'!L1073<>"",'Дивиденды по годам'!I1073<>"",'Дивиденды по годам'!J1073<>"",'Дивиденды по годам'!K1073<>"",('Дивиденды по годам'!I1073-'Дивиденды по годам'!J1073-'Дивиденды по годам'!K1073)<>0),'Дивиденды по годам'!L1073/('Дивиденды по годам'!I1073-'Дивиденды по годам'!J1073-'Дивиденды по годам'!K1073),""),"") | T1073: =IFERROR(IF(AND('Дивиденды по годам'!Q1073<>"",'Дивиденды по годам'!I1073<>"",'Дивиденды по годам'!V1073<>"",('Дивиденды по годам'!I1073+'Дивиденды по годам'!V1073)<>0),'Дивиденды по годам'!Q1073/(('Дивиденды по годам'!I1073+'Дивиденды по годам'!V1073)/2),""),"") | U1073: =IFERROR(IF(AND('Дивиденды по годам'!J1073<>"",'Дивиденды по годам'!K1073<>"",'Дивиденды по годам'!M1073<>"",'Дивиденды по годам'!M1073<>0),('Дивиденды по годам'!J1073+'Дивиденды по годам'!K1073)/'Дивиденды по годам'!M1073,""),"") | X1073: {=IFERROR(AVERAGE(_xlfn._xlws.FILTER(P$2:P$1073,($C$2:$C$1073=$C1073)*($E$2:$E$1073=$E1073)*(ROW(P$2:P$1073)<>ROW(P1073))*(P$2:P$1073<>""))),"")} | Y1073: {=IFERROR(AVERAGE(_xlfn._xlws.FILTER(Q$2:Q$1073,($C$2:$C$1073=$C1073)*($E$2:$E$1073=$E1073)*(ROW(Q$2:Q$1073)<>ROW(Q1073))*(Q$2:Q$1073<>""))),"")} | Z1073: {=IFERROR(AVERAGE(_xlfn._xlws.FILTER(R$2:R$1073,($C$2:$C$1073=$C1073)*($E$2:$E$1073=$E1073)*(ROW(R$2:R$1073)<>ROW(R1073))*(R$2:R$1073<>""))),"")} | AA1073: {=IFERROR(AVERAGE(_xlfn._xlws.FILTER(S$2:S$1073,($C$2:$C$1073=$C1073)*($E$2:$E$1073=$E1073)*(ROW(S$2:S$1073)<>ROW(S1073))*(S$2:S$1073<>""))),"")} | AB1073: {=IFERROR(AVERAGE(_xlfn._xlws.FILTER(T$2:T$1073,($C$2:$C$1073=$C1073)*($E$2:$E$1073=$E1073)*(ROW(T$2:T$1073)<>ROW(T1073))*(T$2:T$1073<>""))),"")} | AC1073: {=IFERROR(AVERAGE(_xlfn._xlws.FILTER(U$2:U$1073,($C$2:$C$1073=$C1073)*($E$2:$E$1073=$E1073)*(ROW(U$2:U$1073)<>ROW(U1073))*(U$2:U$1073<>""))),"")}

Sheet Дивиденды по годам
A1: Тикер | B1: Наименование | C1: Год | D1: Дивиденд | E1: Денежные средства и их эквиваленты | F1: Итого оборотные активы | G1: Основные средства | H1: Нематериальные активы | I1: Активы | J1: Итого краткосрочные обязательства | K1: Итого долгосрочные обязательства | L1: Нераспределенная прибыль | M1: Капитал | N1: Выручка | O1: Операционная прибыль | P1: Прибыль до налогообложения | Q1: Чистая прибыль (убыток) | R1: Износ, истощение и амортизация | S1: EBITDA | T1: Капитальные затраты | U1: Выручка предыдущ периода | V1: Активы предыдущ периода
A2: GAZP | B2: =A2&" "& "IV" &" кв. "&C2 -> GAZP IV кв. 2025 | C2: 2025 | D2: =SUMIFS(Дивиденды!$C:$C,Дивиденды!$A:$A,A2,Дивиденды!$I:$I,C2) -> 0 | E2: =IFERROR(IF(VLOOKUP($B2,Показатели!$E:$W,2,FALSE)=0,"",VLOOKUP($B2,Показатели!$E:$W,2,FALSE)),"") | F2: =IFERROR(IF(VLOOKUP($B2,Показатели!$E:$W,3,FALSE)=0,"",VLOOKUP($B2,Показатели!$E:$W,3,FALSE)),"") | G2: =IFERROR(IF(VLOOKUP($B2,Показатели!$E:$W,4,FALSE)=0,"",VLOOKUP($B2,Показатели!$E:$W,4,FALSE)),"") | H2: =IFERROR(IF(VLOOKUP($B2,Показатели!$E:$W,5,FALSE)=0,"",VLOOKUP($B2,Показатели!$E:$W,5,FALSE)),"") | I2: =IFERROR(IF(VLOOKUP($B2,Показатели!$E:$W,6,FALSE)=0,"",VLOOKUP($B2,Показатели!$E:$W,6,FALSE)),"") | J2: =IFERROR(IF(VLOOKUP($B2,Показатели!$E:$W,7,FALSE)=0,"",VLOOKUP($B2,Показатели!$E:$W,7,FALSE)),"") | K2: =IFERROR(IF(VLOOKUP($B2,Показатели!$E:$W,8,FALSE)=0,"",VLOOKUP($B2,Показатели!$E:$W,8,FALSE)),"") | L2: =IFERROR(IF(VLOOKUP($B2,Показатели!$E:$W,9,FALSE)=0,"",VLOOKUP($B2,Показатели!$E:$W,9,FALSE)),"") | M2: =IFERROR(IF(VLOOKUP($B2,Показатели!$E:$W,10,FALSE)=0,"",VLOOKUP($B2,Показатели!$E:$W,10,FALSE)),"") | N2: =IFERROR(IF(VLOOKUP($B2,Показатели!$E:$W,11,FALSE)=0,"",VLOOKUP($B2,Показатели!$E:$W,11,FALSE)),"") | O2: =IFERROR(IF(VLOOKUP($B2,Показатели!$E:$W,12,FALSE)=0,"",VLOOKUP($B2,Показатели!$E:$W,12,FALSE)),"") | P2: =IFERROR(IF(VLOOKUP($B2,Показатели!$E:$W,13,FALSE)=0,"",VLOOKUP($B2,Показатели!$E:$W,13,FALSE)),"") | Q2: =IFERROR(IF(VLOOKUP($B2,Показатели!$E:$W,14,FALSE)=0,"",VLOOKUP($B2,Показатели!$E:$W,14,FALSE)),"") | R2: =IFERROR(IF(VLOOKUP($B2,Показатели!$E:$W,15,FALSE)=0,"",VLOOKUP($B2,Показатели!$E:$W,15,FALSE)),"") | S2: =IFERROR(IF(VLOOKUP($B2,Показатели!$E:$W,16,FALSE)=0,"",VLOOKUP($B2,Показатели!$E:$W,16,FALSE)),"") | T2: =IFERROR(IF(VLOOKUP($B2,Показатели!$E:$W,17,FALSE)=0,"",VLOOKUP($B2,Показатели!$E:$W,17,FALSE)),"") | U2: =IFERROR(IF(VLOOKUP($B2,Показатели!$E:$W,18,FALSE)=0,"",VLOOKUP($B2,Показатели!$E:$W,18,FALSE)),"") | V2: =IFERROR(IF(VLOOKUP($B2,Показатели!$E:$W,19,FALSE)=0,"",VLOOKUP($B2,Показатели!$E:$W,19,FALSE)),"")
A3: GAZP | B3: =A3&" "& "IV" &" кв. "&C3 -> GAZP IV кв. 2024 | C3: 2024 | D3: =SUMIFS(Дивиденды!$C:$C,Дивиденды!$A:$A,A3,Дивиденды!$I:$I,C3) -> 0 | E3: =IFERROR(IF(VLOOKUP($B3,Показатели!$E:$W,2,FALSE)=0,"",VLOOKUP($B3,Показатели!$E:$W,2,FALSE)),"") -> 991889000000 | F3: =IFERROR(IF(VLOOKUP($B3,Показатели!$E:$W,3,FALSE)=0,"",VLOOKUP($B3,Показатели!$E:$W,3,FALSE)),"") -> 4368456000000 | G3: =IFERROR(IF(VLOOKUP($B3,Показатели!$E:$W,4,FALSE)=0,"",VLOOKUP($B3,Показатели!$E:$W,4,FALSE)),"") -> 20779950000000 | H3: =IFERROR(IF(VLOOKUP($B3,Показатели!$E:$W,5,FALSE)=0,"",VLOOKUP($B3,Показатели!$E:$W,5,FALSE)),"") -> 138420000000 | I3: =IFERROR(IF(VLOOKUP($B3,Показатели!$E:$W,6,FALSE)=0,"",VLOOKUP($B3,Показатели!$E:$W,6,FALSE)),"") -> 30698255000000 | J3: =IFERROR(IF(VLOOKUP($B3,Показатели!$E:$W,7,FALSE)=0,"",VLOOKUP($B3,Показатели!$E:$W,7,FALSE)),"") -> 4971895000000 | K3: =IFERROR(IF(VLOOKUP($B3,Показатели!$E:$W,8,FALSE)=0,"",VLOOKUP($B3,Показатели!$E:$W,8,FALSE)),"") -> 8065398000000 | L3: =IFERROR(IF(VLOOKUP($B3,Показатели!$E:$W,9,FALSE)=0,"",VLOOKUP($B3,Показатели!$E:$W,9,FALSE)),"") -> 15628372000000 | M3: =IFERROR(IF(VLOOKUP($B3,Показатели!$E:$W,10,FALSE)=0,"",VLOOKUP($B3,Показатели!$E:$W,10,FALSE)),"") -> 17660962000000 | N3: =IFERROR(IF(VLOOKUP($B3,Показатели!$E:$W,11,FALSE)=0,"",VLOOKUP($B3,Показатели!$E:$W,11,FALSE)),"") -> 10714686000000 | O3: =IFERROR(IF(VLOOKUP($B3,Показатели!$E:$W,12,FALSE)=0,"",VLOOKUP($B3,Показатели!$E:$W,12,FALSE)),"") -> 1456390000000 | P3: =IFERROR(IF(VLOOKUP($B3,Показатели!$E:$W,13,FALSE)=0,"",VLOOKUP($B3,Показатели!$E:$W,13,FALSE)),"") -> 1662936000000 | Q3: =IFERROR(IF(VLOOKUP($B3,Показатели!$E:$W,14,FALSE)=0,"",VLOOKUP($B3,Показатели!$E:$W,14,FALSE)),"") -> 1318710000000 | R3: =IFERROR(IF(VLOOKUP($B3,Показатели!$E:$W,15,FALSE)=0,"",VLOOKUP($B3,Показатели!$E:$W,15,FALSE)),"") -> 1377774000000 | S3: =IFERROR(IF(VLOOKUP($B3,Показатели!$E:$W,16,FALSE)=0,"",VLOOKUP($B3,Показатели!$E:$W,16,FALSE)),"") -> 3107875000000 | T3: =IFERROR(IF(VLOOKUP($B3,Показатели!$E:$W,17,FALSE)=0,"",VLOOKUP($B3,Показатели!$E:$W,17,FALSE)),"") -> -2353789000000 | U3: =IFERROR(IF(VLOOKUP($B3,Показатели!$E:$W,18,FALSE)=0,"",VLOOKUP($B3,Показатели!$E:$W,18,FALSE)),"") -> 8541818000000 | V3: =IFERROR(IF(VLOOKUP($B3,Показатели!$E:$W,19,FALSE)=0,"",VLOOKUP($B3,Показатели!$E:$W,19,FALSE)),"") -> 28713748000000
A4: GAZP | B4: =A4&" "& "IV" &" кв. "&C4 -> GAZP IV кв. 2023 | C4: 2023 | D4: =SUMIFS(Дивиденды!$C:$C,Дивиденды!$A:$A,A4,Дивиденды!$I:$I,C4) -> 0 | E4: =IFERROR(IF(VLOOKUP($B4,Показатели!$E:$W,2,FALSE)=0,"",VLOOKUP($B4,Показатели!$E:$W,2,FALSE)),"") -> 1426780000000 | F4: =IFERROR(IF(VLOOKUP($B4,Показатели!$E:$W,3,FALSE)=0,"",VLOOKUP($B4,Показатели!$E:$W,3,FALSE)),"") -> 4780869000000 | G4: =IFERROR(IF(VLOOKUP($B4,Показатели!$E:$W,4,FALSE)=0,"",VLOOKUP($B4,Показатели!$E:$W,4,FALSE)),"") -> 18436207000000 | H4: =IFERROR(IF(VLOOKUP($B4,Показатели!$E:$W,5,FALSE)=0,"",VLOOKUP($B4,Показатели!$E:$W,5,FALSE)),"") -> 147273000000 | I4: =IFERROR(IF(VLOOKUP($B4,Показатели!$E:$W,6,FALSE)=0,"",VLOOKUP($B4,Показатели!$E:$W,6,FALSE)),"") -> 28713748000000 | J4: =IFERROR(IF(VLOOKUP($B4,Показатели!$E:$W,7,FALSE)=0,"",VLOOKUP($B4,Показатели!$E:$W,7,FALSE)),"") -> 4531986000000 | K4: =IFERROR(IF(VLOOKUP($B4,Показатели!$E:$W,8,FALSE)=0,"",VLOOKUP($B4,Показатели!$E:$W,8,FALSE)),"") -> 7729048000000 | L4: =IFERROR(IF(VLOOKUP($B4,Показатели!$E:$W,9,FALSE)=0,"",VLOOKUP($B4,Показатели!$E:$W,9,FALSE)),"") -> 14591946000000 | M4: =IFERROR(IF(VLOOKUP($B4,Показатели!$E:$W,10,FALSE)=0,"",VLOOKUP($B4,Показатели!$E:$W,10,FALSE)),"") -> 16452714000000 | N4: =IFERROR(IF(VLOOKUP($B4,Показатели!$E:$W,11,FALSE)=0,"",VLOOKUP($B4,Показатели!$E:$W,11,FALSE)),"") -> 8541818000000 | O4: =IFERROR(IF(VLOOKUP($B4,Показатели!$E:$W,12,FALSE)=0,"",VLOOKUP($B4,Показатели!$E:$W,12,FALSE)),"") -> -363689000000 | P4: =IFERROR(IF(VLOOKUP($B4,Показатели!$E:$W,13,FALSE)=0,"",VLOOKUP($B4,Показатели!$E:$W,13,FALSE)),"") -> -659070000000 | Q4: =IFERROR(IF(VLOOKUP($B4,Показатели!$E:$W,14,FALSE)=0,"",VLOOKUP($B4,Показатели!$E:$W,14,FALSE)),"") -> -583076000000 | R4: =IFERROR(IF(VLOOKUP($B4,Показатели!$E:$W,15,FALSE)=0,"",VLOOKUP($B4,Показатели!$E:$W,15,FALSE)),"") -> 982058000000 | S4: =IFERROR(IF(VLOOKUP($B4,Показатели!$E:$W,16,FALSE)=0,"",VLOOKUP($B4,Показатели!$E:$W,16,FALSE)),"") -> 1764554000000 | T4: =IFERROR(IF(VLOOKUP($B4,Показатели!$E:$W,17,FALSE)=0,"",VLOOKUP($B4,Показатели!$E:$W,17,FALSE)),"") -> -2422017000000 | U4: =IFERROR(IF(VLOOKUP($B4,Показатели!$E:$W,18,FALSE)=0,"",VLOOKUP($B4,Показатели!$E:$W,18,FALSE)),"") -> 11673950000000 | V4: =IFERROR(IF(VLOOKUP($B4,Показатели!$E:$W,19,FALSE)=0,"",VLOOKUP($B4,Показатели!$E:$W,19,FALSE)),"") -> 26128929000000
A5: GAZP | B5: =A5&" "& "IV" &" кв. "&C5 -> GAZP IV кв. 2022 | C5: 2022 | D5: =SUMIFS(Дивиденды!$C:$C,Дивиденды!$A:$A,A5,Дивиденды!$I:$I,C5) -> 51.03 | E5: =IFERROR(IF(VLOOKUP($B5,Показатели!$E:$W,2,FALSE)=0,"",VLOOKUP($B5,Показатели!$E:$W,2,FALSE)),"") -> 1157587000000 | F5: =IFERROR(IF(VLOOKUP($B5,Показатели!$E:$W,3,FALSE)=0,"",VLOOKUP($B5,Показатели!$E:$W,3,FALSE)),"") -> 4620117000000 | G5: =IFERROR(IF(VLOOKUP($B5,Показатели!$E:$W,4,FALSE)=0,"",VLOOKUP($B5,Показатели!$E:$W,4,FALSE)),"") -> 17419060000000 | H5: =IFERROR(IF(VLOOKUP($B5,Показатели!$E:$W,5,FALSE)=0,"",VLOOKUP($B5,Показатели!$E:$W,5,FALSE)),"") -> 130585000000 | I5: =IFERROR(IF(VLOOKUP($B5,Показатели!$E:$W,6,FALSE)=0,"",VLOOKUP($B5,Показатели!$E:$W,6,FALSE)),"") -> 26128929000000 | J5: =IFERROR(IF(VLOOKUP($B5,Показатели!$E:$W,7,FALSE)=0,"",VLOOKUP($B5,Показатели!$E:$W,7,FALSE)),"") -> 2900860000000 | K5: =IFERROR(IF(VLOOKUP($B5,Показатели!$E:$W,8,FALSE)=0,"",VLOOKUP($B5,Показатели!$E:$W,8,FALSE)),"") -> 6782224000000 | L5: =IFERROR(IF(VLOOKUP($B5,Показатели!$E:$W,9,FALSE)=0,"",VLOOKUP($B5,Показатели!$E:$W,9,FALSE)),"") -> 15126010000000 | M5: =IFERROR(IF(VLOOKUP($B5,Показатели!$E:$W,10,FALSE)=0,"",VLOOKUP($B5,Показатели!$E:$W,10,FALSE)),"") -> 16445845000000 | N5: =IFERROR(IF(VLOOKUP($B5,Показатели!$E:$W,11,FALSE)=0,"",VLOOKUP($B5,Показатели!$E:$W,11,FALSE)),"") -> 11673950000000 | O5: =IFERROR(IF(VLOOKUP($B5,Показатели!$E:$W,12,FALSE)=0,"",VLOOKUP($B5,Показатели!$E:$W,12,FALSE)),"") -> 1935159000000 | P5: =IFERROR(IF(VLOOKUP($B5,Показатели!$E:$W,13,FALSE)=0,"",VLOOKUP($B5,Показатели!$E:$W,13,FALSE)),"") -> 2190558000000 | Q5: =IFERROR(IF(VLOOKUP($B5,Показатели!$E:$W,14,FALSE)=0,"",VLOOKUP($B5,Показатели!$E:$W,14,FALSE)),"") -> 1311645000000 | R5: =IFERROR(IF(VLOOKUP($B5,Показатели!$E:$W,15,FALSE)=0,"",VLOOKUP($B5,Показатели!$E:$W,15,FALSE)),"") -> 862380000000 | S5: =IFERROR(IF(VLOOKUP($B5,Показатели!$E:$W,16,FALSE)=0,"",VLOOKUP($B5,Показатели!$E:$W,16,FALSE)),"") -> 3637555000000 | T5: =IFERROR(IF(VLOOKUP($B5,Показатели!$E:$W,17,FALSE)=0,"",VLOOKUP($B5,Показатели!$E:$W,17,FALSE)),"") -> -2191642000000 | U5: =IFERROR(IF(VLOOKUP($B5,Показатели!$E:$W,18,FALSE)=0,"",VLOOKUP($B5,Показатели!$E:$W,18,FALSE)),"") -> 10241353000000 | V5: =IFERROR(IF(VLOOKUP($B5,Показатели!$E:$W,19,FALSE)=0,"",VLOOKUP($B5,Показатели!$E:$W,19,FALSE)),"") -> 27047230000000
A6: GAZP | B6: =A6&" "& "IV" &" кв. "&C6 -> GAZP IV кв. 2021 | C6: 2021 | D6: =SUMIFS(Дивиденды!$C:$C,Дивиденды!$A:$A,A6,Дивиденды!$I:$I,C6) -> 0 | E6: =IFERROR(IF(VLOOKUP($B6,Показатели!$E:$W,2,FALSE)=0,"",VLOOKUP($B6,Показатели!$E:$W,2,FALSE)),"") -> 2013923000000 | F6: =IFERROR(IF(VLOOKUP($B6,Показатели!$E:$W,3,FALSE)=0,"",VLOOKUP($B6,Показатели!$E:$W,3,FALSE)),"") -> 6214283000000 | G6: =IFERROR(IF(VLOOKUP($B6,Показатели!$E:$W,4,FALSE)=0,"",VLOOKUP($B6,Показатели!$E:$W,4,FALSE)),"") -> 16673568000000 | H6: =IFERROR(IF(VLOOKUP($B6,Показатели!$E:$W,5,FALSE)=0,"",VLOOKUP($B6,Показатели!$E:$W,5,FALSE)),"") -> 120768000000 | I6: =IFERROR(IF(VLOOKUP($B6,Показатели!$E:$W,6,FALSE)=0,"",VLOOKUP($B6,Показатели!$E:$W,6,FALSE)),"") -> 27047230000000 | J6: =IFERROR(IF(VLOOKUP($B6,Показатели!$E:$W,7,FALSE)=0,"",VLOOKUP($B6,Показатели!$E:$W,7,FALSE)),"") -> 4022945000000 | K6: =IFERROR(IF(VLOOKUP($B6,Показатели!$E:$W,8,FALSE)=0,"",VLOOKUP($B6,Показатели!$E:$W,8,FALSE)),"") -> 6157706000000 | L6: =IFERROR(IF(VLOOKUP($B6,Показатели!$E:$W,9,FALSE)=0,"",VLOOKUP($B6,Показатели!$E:$W,9,FALSE)),"") -> 15613466000000 | M6: =IFERROR(IF(VLOOKUP($B6,Показатели!$E:$W,10,FALSE)=0,"",VLOOKUP($B6,Показатели!$E:$W,10,FALSE)),"") -> 16866579000000 | N6: =IFERROR(IF(VLOOKUP($B6,Показатели!$E:$W,11,FALSE)=0,"",VLOOKUP($B6,Показатели!$E:$W,11,FALSE)),"") -> 10241353000000 | O6: =IFERROR(IF(VLOOKUP($B6,Показатели!$E:$W,12,FALSE)=0,"",VLOOKUP($B6,Показатели!$E:$W,12,FALSE)),"") -> 2411261000000 | P6: =IFERROR(IF(VLOOKUP($B6,Показатели!$E:$W,13,FALSE)=0,"",VLOOKUP($B6,Показатели!$E:$W,13,FALSE)),"") -> 2769514000000 | Q6: =IFERROR(IF(VLOOKUP($B6,Показатели!$E:$W,14,FALSE)=0,"",VLOOKUP($B6,Показатели!$E:$W,14,FALSE)),"") -> 2159086000000 | R6: =IFERROR(IF(VLOOKUP($B6,Показатели!$E:$W,15,FALSE)=0,"",VLOOKUP($B6,Показатели!$E:$W,15,FALSE)),"") -> 828027000000 | S6: =IFERROR(IF(VLOOKUP($B6,Показатели!$E:$W,16,FALSE)=0,"",VLOOKUP($B6,Показатели!$E:$W,16,FALSE)),"") -> 3686890000000 | T6: =IFERROR(IF(VLOOKUP($B6,Показатели!$E:$W,17,FALSE)=0,"",VLOOKUP($B6,Показатели!$E:$W,17,FALSE)),"") -> -1933766000000 | U6: =IFERROR(IF(VLOOKUP($B6,Показатели!$E:$W,18,FALSE)=0,"",VLOOKUP($B6,Показатели!$E:$W,18,FALSE)),"") -> 6321559000000 | V6: =IFERROR(IF(VLOOKUP($B6,Показатели!$E:$W,19,FALSE)=0,"",VLOOKUP($B6,Показатели!$E:$W,19,FALSE)),"") -> 23352185000000
A7: GAZP | B7: =A7&" "& "IV" &" кв. "&C7 -> GAZP IV кв. 2020 | C7: 2020 | D7: =SUMIFS(Дивиденды!$C:$C,Дивиденды!$A:$A,A7,Дивиденды!$I:$I,C7) -> 12.55 | E7: =IFERROR(IF(VLOOKUP($B7,Показатели!$E:$W,2,FALSE)=0,"",VLOOKUP($B7,Показатели!$E:$W,2,FALSE)),"") -> 1034919000000 | F7: =IFERROR(IF(VLOOKUP($B7,Показатели!$E:$W,3,FALSE)=0,"",VLOOKUP($B7,Показатели!$E:$W,3,FALSE)),"") -> 3774289000000 | G7: =IFERROR(IF(VLOOKUP($B7,Показатели!$E:$W,4,FALSE)=0,"",VLOOKUP($B7,Показатели!$E:$W,4,FALSE)),"") -> 16103095000000 | H7: =IFERROR(IF(VLOOKUP($B7,Показатели!$E:$W,5,FALSE)=0,"",VLOOKUP($B7,Показатели!$E:$W,5,FALSE)),"") -> 119854000000 | I7: =IFERROR(IF(VLOOKUP($B7,Показатели!$E:$W,6,FALSE)=0,"",VLOOKUP($B7,Показатели!$E:$W,6,FALSE)),"") -> 23352185000000 | J7: =IFERROR(IF(VLOOKUP($B7,Показатели!$E:$W,7,FALSE)=0,"",VLOOKUP($B7,Показатели!$E:$W,7,FALSE)),"") -> 2626964000000 | K7: =IFERROR(IF(VLOOKUP($B7,Показатели!$E:$W,8,FALSE)=0,"",VLOOKUP($B7,Показатели!$E:$W,8,FALSE)),"") -> 5920489000000 | L7: =IFERROR(IF(VLOOKUP($B7,Показатели!$E:$W,9,FALSE)=0,"",VLOOKUP($B7,Показатели!$E:$W,9,FALSE)),"") -> 13717464000000 | M7: =IFERROR(IF(VLOOKUP($B7,Показатели!$E:$W,10,FALSE)=0,"",VLOOKUP($B7,Показатели!$E:$W,10,FALSE)),"") -> 14804732000000 | N7: =IFERROR(IF(VLOOKUP($B7,Показатели!$E:$W,11,FALSE)=0,"",VLOOKUP($B7,Показатели!$E:$W,11,FALSE)),"") -> 6321559000000 | O7: =IFERROR(IF(VLOOKUP($B7,Показатели!$E:$W,12,FALSE)=0,"",VLOOKUP($B7,Показатели!$E:$W,12,FALSE)),"") -> 614851000000 | P7: =IFERROR(IF(VLOOKUP($B7,Показатели!$E:$W,13,FALSE)=0,"",VLOOKUP($B7,Показатели!$E:$W,13,FALSE)),"") -> 133469000000 | Q7: =IFERROR(IF(VLOOKUP($B7,Показатели!$E:$W,14,FALSE)=0,"",VLOOKUP($B7,Показатели!$E:$W,14,FALSE)),"") -> 162407000000 | R7: =IFERROR(IF(VLOOKUP($B7,Показатели!$E:$W,15,FALSE)=0,"",VLOOKUP($B7,Показатели!$E:$W,15,FALSE)),"") -> 798436000000 | S7: =IFERROR(IF(VLOOKUP($B7,Показатели!$E:$W,16,FALSE)=0,"",VLOOKUP($B7,Показатели!$E:$W,16,FALSE)),"") -> 1466541000000 | T7: =IFERROR(IF(VLOOKUP($B7,Показатели!$E:$W,17,FALSE)=0,"",VLOOKUP($B7,Показатели!$E:$W,17,FALSE)),"") -> -1522565000000 | U7: =IFERROR(IF(VLOOKUP($B7,Показатели!$E:$W,18,FALSE)=0,"",VLOOKUP($B7,Показатели!$E:$W,18,FALSE)),"") -> 7659623000000 | V7: =IFERROR(IF(VLOOKUP($B7,Показатели!$E:$W,19,FALSE)=0,"",VLOOKUP($B7,Показатели!$E:$W,19,FALSE)),"") -> 21882348000000
A8: GAZP | B8: =A8&" "& "IV" &" кв. "&C8 -> GAZP IV кв. 2019 | C8: 2019 | D8: =SUMIFS(Дивиденды!$C:$C,Дивиденды!$A:$A,A8,Дивиденды!$I:$I,C8) -> 15.24 | E8: =IFERROR(IF(VLOOKUP($B8,Показатели!$E:$W,2,FALSE)=0,"",VLOOKUP($B8,Показатели!$E:$W,2,FALSE)),"") -> 696057000000 | F8: =IFERROR(IF(VLOOKUP($B8,Показатели!$E:$W,3,FALSE)=0,"",VLOOKUP($B8,Показатели!$E:$W,3,FALSE)),"") -> 3828153000000 | G8: =IFERROR(IF(VLOOKUP($B8,Показатели!$E:$W,4,FALSE)=0,"",VLOOKUP($B8,Показатели!$E:$W,4,FALSE)),"") -> 14856448000000 | H8: =IFERROR(IF(VLOOKUP($B8,Показатели!$E:$W,5,FALSE)=0,"",VLOOKUP($B8,Показатели!$E:$W,5,FALSE)),"") -> 130028000000 | I8: =IFERROR(IF(VLOOKUP($B8,Показатели!$E:$W,6,FALSE)=0,"",VLOOKUP($B8,Показатели!$E:$W,6,FALSE)),"") -> 21882348000000 | J8: =IFERROR(IF(VLOOKUP($B8,Показатели!$E:$W,7,FALSE)=0,"",VLOOKUP($B8,Показатели!$E:$W,7,FALSE)),"") -> 2527476000000 | K8: =IFERROR(IF(VLOOKUP($B8,Показатели!$E:$W,8,FALSE)=0,"",VLOOKUP($B8,Показатели!$E:$W,8,FALSE)),"") -> 4739185000000 | L8: =IFERROR(IF(VLOOKUP($B8,Показатели!$E:$W,9,FALSE)=0,"",VLOOKUP($B8,Показатели!$E:$W,9,FALSE)),"") -> 13779970000000 | M8: =IFERROR(IF(VLOOKUP($B8,Показатели!$E:$W,10,FALSE)=0,"",VLOOKUP($B8,Показатели!$E:$W,10,FALSE)),"") -> 14615687000000 | N8: =IFERROR(IF(VLOOKUP($B8,Показатели!$E:$W,11,FALSE)=0,"",VLOOKUP($B8,Показатели!$E:$W,11,FALSE)),"") -> 7659623000000 | O8: =IFERROR(IF(VLOOKUP($B8,Показатели!$E:$W,12,FALSE)=0,"",VLOOKUP($B8,Показатели!$E:$W,12,FALSE)),"") -> 1119857000000 | P8: =IFERROR(IF(VLOOKUP($B8,Показатели!$E:$W,13,FALSE)=0,"",VLOOKUP($B8,Показатели!$E:$W,13,FALSE)),"") -> 1627065000000 | Q8: =IFERROR(IF(VLOOKUP($B8,Показатели!$E:$W,14,FALSE)=0,"",VLOOKUP($B8,Показатели!$E:$W,14,FALSE)),"") -> 1269517000000 | R8: =IFERROR(IF(VLOOKUP($B8,Показатели!$E:$W,15,FALSE)=0,"",VLOOKUP($B8,Показатели!$E:$W,15,FALSE)),"") -> 715229000000 | S8: =IFERROR(IF(VLOOKUP($B8,Показатели!$E:$W,16,FALSE)=0,"",VLOOKUP($B8,Показатели!$E:$W,16,FALSE)),"") -> 1859679000000 | T8: =IFERROR(IF(VLOOKUP($B8,Показатели!$E:$W,17,FALSE)=0,"",VLOOKUP($B8,Показатели!$E:$W,17,FALSE)),"") -> -1775923000000 | U8: =IFERROR(IF(VLOOKUP($B8,Показатели!$E:$W,18,FALSE)=0,"",VLOOKUP($B8,Показатели!$E:$W,18,FALSE)),"") -> 8224177000000 | V8: =IFERROR(IF(VLOOKUP($B8,Показатели!$E:$W,19,FALSE)=0,"",VLOOKUP($B8,Показатели!$E:$W,19,FALSE)),"") -> 20810440000000
A9: GAZP | B9: =A9&" "& "IV" &" кв. "&C9 -> GAZP IV кв. 2018 | C9: 2018 | D9: =SUMIFS(Дивиденды!$C:$C,Дивиденды!$A:$A,A9,Дивиденды!$I:$I,C9) -> 16.61 | E9: =IFERROR(IF(VLOOKUP($B9,Показатели!$E:$W,2,FALSE)=0,"",VLOOKUP($B9,Показатели!$E:$W,2,FALSE)),"") -> 849419000000 | F9: =IFERROR(IF(VLOOKUP($B9,Показатели!$E:$W,3,FALSE)=0,"",VLOOKUP($B9,Показатели!$E:$W,3,FALSE)),"") -> 4212230000000 | G9: =IFERROR(IF(VLOOKUP($B9,Показатели!$E:$W,4,FALSE)=0,"",VLOOKUP($B9,Показатели!$E:$W,4,FALSE)),"") -> 13809434000000 | H9: =IFERROR(IF(VLOOKUP($B9,Показатели!$E:$W,5,FALSE)=0,"",VLOOKUP($B9,Показатели!$E:$W,5,FALSE)),"") -> 108097000000 | I9: =IFERROR(IF(VLOOKUP($B9,Показатели!$E:$W,6,FALSE)=0,"",VLOOKUP($B9,Показатели!$E:$W,6,FALSE)),"") -> 20810440000000 | J9: =IFERROR(IF(VLOOKUP($B9,Показатели!$E:$W,7,FALSE)=0,"",VLOOKUP($B9,Показатели!$E:$W,7,FALSE)),"") -> 2473695000000 | K9: =IFERROR(IF(VLOOKUP($B9,Показатели!$E:$W,8,FALSE)=0,"",VLOOKUP($B9,Показатели!$E:$W,8,FALSE)),"") -> 4560592000000 | L9: =IFERROR(IF(VLOOKUP($B9,Показатели!$E:$W,9,FALSE)=0,"",VLOOKUP($B9,Показатели!$E:$W,9,FALSE)),"") -> 13210734000000 | M9: =IFERROR(IF(VLOOKUP($B9,Показатели!$E:$W,10,FALSE)=0,"",VLOOKUP($B9,Показатели!$E:$W,10,FALSE)),"") -> 13776153000000 | N9: =IFERROR(IF(VLOOKUP($B9,Показатели!$E:$W,11,FALSE)=0,"",VLOOKUP($B9,Показатели!$E:$W,11,FALSE)),"") -> 8224177000000 | O9: =IFERROR(IF(VLOOKUP($B9,Показатели!$E:$W,12,FALSE)=0,"",VLOOKUP($B9,Показатели!$E:$W,12,FALSE)),"") -> 1930030000000 | P9: =IFERROR(IF(VLOOKUP($B9,Показатели!$E:$W,13,FALSE)=0,"",VLOOKUP($B9,Показатели!$E:$W,13,FALSE)),"") -> 1852562000000 | Q9: =IFERROR(IF(VLOOKUP($B9,Показатели!$E:$W,14,FALSE)=0,"",VLOOKUP($B9,Показатели!$E:$W,14,FALSE)),"") -> 1528996000000 | R9: =IFERROR(IF(VLOOKUP($B9,Показатели!$E:$W,15,FALSE)=0,"",VLOOKUP($B9,Показатели!$E:$W,15,FALSE)),"") -> 647993000000 | S9: =IFERROR(IF(VLOOKUP($B9,Показатели!$E:$W,16,FALSE)=0,"",VLOOKUP($B9,Показатели!$E:$W,16,FALSE)),"") -> 2599284000000 | T9: =IFERROR(IF(VLOOKUP($B9,Показатели!$E:$W,17,FALSE)=0,"",VLOOKUP($B9,Показатели!$E:$W,17,FALSE)),"") -> -1639474000000 | U9: =IFERROR(IF(VLOOKUP($B9,Показатели!$E:$W,18,FALSE)=0,"",VLOOKUP($B9,Показатели!$E:$W,18,FALSE)),"") -> 6546143000000 | V9: =IFERROR(IF(VLOOKUP($B9,Показатели!$E:$W,19,FALSE)=0,"",VLOOKUP($B9,Показатели!$E:$W,19,FALSE)),"") -> 18238770000000
A10: GAZP | B10: =A10&" "& "IV" &" кв. "&C10 -> GAZP IV кв. 2017 | C10: 2017 | D10: =SUMIFS(Дивиденды!$C:$C,Дивиденды!$A:$A,A10,Дивиденды!$I:$I,C10) -> 8.04 | E10: =IFERROR(IF(VLOOKUP($B10,Показатели!$E:$W,2,FALSE)=0,"",VLOOKUP($B10,Показатели!$E:$W,2,FALSE)),"") -> 869007000000 | F10: =IFERROR(IF(VLOOKUP($B10,Показатели!$E:$W,3,FALSE)=0,"",VLOOKUP($B10,Показатели!$E:$W,3,FALSE)),"") -> 3469266000000 | G10: =IFERROR(IF(VLOOKUP($B10,Показатели!$E:$W,4,FALSE)=0,"",VLOOKUP($B10,Показатели!$E:$W,4,FALSE)),"") -> 12545079000000 | H10: =IFERROR(IF(VLOOKUP($B10,Показатели!$E:$W,5,FALSE)=0,"",VLOOKUP($B10,Показатели!$E:$W,5,FALSE)),"") -> 105469000000 | I10: =IFERROR(IF(VLOOKUP($B10,Показатели!$E:$W,6,FALSE)=0,"",VLOOKUP($B10,Показатели!$E:$W,6,FALSE)),"") -> 18238770000000 | J10: =IFERROR(IF(VLOOKUP($B10,Показатели!$E:$W,7,FALSE)=0,"",VLOOKUP($B10,Показатели!$E:$W,7,FALSE)),"") -> 2589516000000 | K10: =IFERROR(IF(VLOOKUP($B10,Показатели!$E:$W,8,FALSE)=0,"",VLOOKUP($B10,Показатели!$E:$W,8,FALSE)),"") -> 3633773000000 | L10: =IFERROR(IF(VLOOKUP($B10,Показатели!$E:$W,9,FALSE)=0,"",VLOOKUP($B10,Показатели!$E:$W,9,FALSE)),"") -> 11539811000000 | M10: =IFERROR(IF(VLOOKUP($B10,Показатели!$E:$W,10,FALSE)=0,"",VLOOKUP($B10,Показатели!$E:$W,10,FALSE)),"") -> 12015481000000 | N10: =IFERROR(IF(VLOOKUP($B10,Показатели!$E:$W,11,FALSE)=0,"",VLOOKUP($B10,Показатели!$E:$W,11,FALSE)),"") -> 6546143000000 | O10: =IFERROR(IF(VLOOKUP($B10,Показатели!$E:$W,12,FALSE)=0,"",VLOOKUP($B10,Показатели!$E:$W,12,FALSE)),"") -> 870523000000 | P10: =IFERROR(IF(VLOOKUP($B10,Показатели!$E:$W,13,FALSE)=0,"",VLOOKUP($B10,Показатели!$E:$W,13,FALSE)),"") -> 1018006000000 | Q10: =IFERROR(IF(VLOOKUP($B10,Показатели!$E:$W,14,FALSE)=0,"",VLOOKUP($B10,Показатели!$E:$W,14,FALSE)),"") -> 766879000000 | R10: =IFERROR(IF(VLOOKUP($B10,Показатели!$E:$W,15,FALSE)=0,"",VLOOKUP($B10,Показатели!$E:$W,15,FALSE)),"") -> 613160000000 | S10: =IFERROR(IF(VLOOKUP($B10,Показатели!$E:$W,16,FALSE)=0,"",VLOOKUP($B10,Показатели!$E:$W,16,FALSE)),"") -> 1466910000000 | T10: =IFERROR(IF(VLOOKUP($B10,Показатели!$E:$W,17,FALSE)=0,"",VLOOKUP($B10,Показатели!$E:$W,17,FALSE)),"") -> -1405780000000 | U10: =IFERROR(IF(VLOOKUP($B10,Показатели!$E:$W,18,FALSE)=0,"",VLOOKUP($B10,Показатели!$E:$W,18,FALSE)),"") -> 6111051000000 | V10: =IFERROR(IF(VLOOKUP($B10,Показатели!$E:$W,19,FALSE)=0,"",VLOOKUP($B10,Показатели!$E:$W,19,FALSE)),"") -> 16918938000000
A11: GAZP | B11: =A11&" "& "IV" &" кв. "&C11 -> GAZP IV кв. 2016 | C11: 2016 | D11: =SUMIFS(Дивиденды!$C:$C,Дивиденды!$A:$A,A11,Дивиденды!$I:$I,C11) -> 8.04 | E11: =IFERROR(IF(VLOOKUP($B11,Показатели!$E:$W,2,FALSE)=0,"",VLOOKUP($B11,Показатели!$E:$W,2,FALSE)),"") -> 896728000000 | F11: =IFERROR(IF(VLOOKUP($B11,Показатели!$E:$W,3,FALSE)=0,"",VLOOKUP($B11,Показатели!$E:$W,3,FALSE)),"") -> 3234346000000 | G11: =IFERROR(IF(VLOOKUP($B11,Показатели!$E:$W,4,FALSE)=0,"",VLOOKUP($B11,Показатели!$E:$W,4,FALSE)),"") -> 11502747000000 | H11: =IFERROR(IF(VLOOKUP($B11,Показатели!$E:$W,5,FALSE)=0,"",VLOOKUP($B11,Показатели!$E:$W,5,FALSE)),"") | I11: =IFERROR(IF(VLOOKUP($B11,Показатели!$E:$W,6,FALSE)=0,"",VLOOKUP($B11,Показатели!$E:$W,6,FALSE)),"") -> 16918938000000 | J11: =IFERROR(IF(VLOOKUP($B11,Показатели!$E:$W,7,FALSE)=0,"",VLOOKUP($B11,Показатели!$E:$W,7,FALSE)),"") -> 1921808000000 | K11: =IFERROR(IF(VLOOKUP($B11,Показатели!$E:$W,8,FALSE)=0,"",VLOOKUP($B11,Показатели!$E:$W,8,FALSE)),"") -> 3555291000000 | L11: =IFERROR(IF(VLOOKUP($B11,Показатели!$E:$W,9,FALSE)=0,"",VLOOKUP($B11,Показатели!$E:$W,9,FALSE)),"") -> 11005256000000 | M11: =IFERROR(IF(VLOOKUP($B11,Показатели!$E:$W,10,FALSE)=0,"",VLOOKUP($B11,Показатели!$E:$W,10,FALSE)),"") -> 11441839000000 | N11: =IFERROR(IF(VLOOKUP($B11,Показатели!$E:$W,11,FALSE)=0,"",VLOOKUP($B11,Показатели!$E:$W,11,FALSE)),"") -> 6111051000000 | O11: =IFERROR(IF(VLOOKUP($B11,Показатели!$E:$W,12,FALSE)=0,"",VLOOKUP($B11,Показатели!$E:$W,12,FALSE)),"") -> 725580000000 | P11: =IFERROR(IF(VLOOKUP($B11,Показатели!$E:$W,13,FALSE)=0,"",VLOOKUP($B11,Показатели!$E:$W,13,FALSE)),"") -> 1285138000000 | Q11: =IFERROR(IF(VLOOKUP($B11,Показатели!$E:$W,14,FALSE)=0,"",VLOOKUP($B11,Показатели!$E:$W,14,FALSE)),"") -> 997104000000 | R11: =IFERROR(IF(VLOOKUP($B11,Показатели!$E:$W,15,FALSE)=0,"",VLOOKUP($B11,Показатели!$E:$W,15,FALSE)),"") | S11: =IFERROR(IF(VLOOKUP($B11,Показатели!$E:$W,16,FALSE)=0,"",VLOOKUP($B11,Показатели!$E:$W,16,FALSE)),"") -> 1322000000000 | T11: =IFERROR(IF(VLOOKUP($B11,Показатели!$E:$W,17,FALSE)=0,"",VLOOKUP($B11,Показатели!$E:$W,17,FALSE)),"") -> 1369000000000 | U11: =IFERROR(IF(VLOOKUP($B11,Показатели!$E:$W,18,FALSE)=0,"",VLOOKUP($B11,Показатели!$E:$W,18,FALSE)),"") -> 6073318000000 | V11: =IFERROR(IF(VLOOKUP($B11,Показатели!$E:$W,19,FALSE)=0,"",VLOOKUP($B11,Показатели!$E:$W,19,FALSE)),"") -> 17052040000000
A12: GAZP | B12: =A12&" "& "IV" &" кв. "&C12 -> GAZP IV кв. 2015 | C12: 2015 | D12: =SUMIFS(Дивиденды!$C:$C,Дивиденды!$A:$A,A12,Дивиденды!$I:$I,C12) -> 7.89 | E12: =IFERROR(IF(VLOOKUP($B12,Показатели!$E:$W,2,FALSE)=0,"",VLOOKUP($B12,Показатели!$E:$W,2,FALSE)),"") -> 1359095000000 | F12: =IFERROR(IF(VLOOKUP($B12,Показатели!$E:$W,3,FALSE)=0,"",VLOOKUP($B12,Показатели!$E:$W,3,FALSE)),"") -> 3993722000000 | G12: =IFERROR(IF(VLOOKUP($B12,Показатели!$E:$W,4,FALSE)=0,"",VLOOKUP($B12,Показатели!$E:$W,4,FALSE)),"") -> 11003881000000 | H12: =IFERROR(IF(VLOOKUP($B12,Показатели!$E:$W,5,FALSE)=0,"",VLOOKUP($B12,Показатели!$E:$W,5,FALSE)),"") | I12: =IFERROR(IF(VLOOKUP($B12,Показатели!$E:$W,6,FALSE)=0,"",VLOOKUP($B12,Показатели!$E:$W,6,FALSE)),"") -> 17052040000000 | J12: =IFERROR(IF(VLOOKUP($B12,Показатели!$E:$W,7,FALSE)=0,"",VLOOKUP($B12,Показатели!$E:$W,7,FALSE)),"") -> 2124701000000 | K12: =IFERROR(IF(VLOOKUP($B12,Показатели!$E:$W,8,FALSE)=0,"",VLOOKUP($B12,Показатели!$E:$W,8,FALSE)),"") -> 4012717000000 | L12: =IFERROR(IF(VLOOKUP($B12,Показатели!$E:$W,9,FALSE)=0,"",VLOOKUP($B12,Показатели!$E:$W,9,FALSE)),"") -> 10368311000000 | M12: =IFERROR(IF(VLOOKUP($B12,Показатели!$E:$W,10,FALSE)=0,"",VLOOKUP($B12,Показатели!$E:$W,10,FALSE)),"") -> 10914622000000 | N12: =IFERROR(IF(VLOOKUP($B12,Показатели!$E:$W,11,FALSE)=0,"",VLOOKUP($B12,Показатели!$E:$W,11,FALSE)),"") -> 6073318000000 | O12: =IFERROR(IF(VLOOKUP($B12,Показатели!$E:$W,12,FALSE)=0,"",VLOOKUP($B12,Показатели!$E:$W,12,FALSE)),"") -> 1228301000000 | P12: =IFERROR(IF(VLOOKUP($B12,Показатели!$E:$W,13,FALSE)=0,"",VLOOKUP($B12,Показатели!$E:$W,13,FALSE)),"") -> 925241000000 | Q12: =IFERROR(IF(VLOOKUP($B12,Показатели!$E:$W,14,FALSE)=0,"",VLOOKUP($B12,Показатели!$E:$W,14,FALSE)),"") -> 805199000000 | R12: =IFERROR(IF(VLOOKUP($B12,Показатели!$E:$W,15,FALSE)=0,"",VLOOKUP($B12,Показатели!$E:$W,15,FALSE)),"") | S12: =IFERROR(IF(VLOOKUP($B12,Показатели!$E:$W,16,FALSE)=0,"",VLOOKUP($B12,Показатели!$E:$W,16,FALSE)),"") -> 1875000000000 | T12: =IFERROR(IF(VLOOKUP($B12,Показатели!$E:$W,17,FALSE)=0,"",VLOOKUP($B12,Показатели!$E:$W,17,FALSE)),"") -> 1641024000000 | U12: =IFERROR(IF(VLOOKUP($B12,Показатели!$E:$W,18,FALSE)=0,"",VLOOKUP($B12,Показатели!$E:$W,18,FALSE)),"") -> 5589811000000 | V12: =IFERROR(IF(VLOOKUP($B12,Показатели!$E:$W,19,FALSE)=0,"",VLOOKUP($B12,Показатели!$E:$W,19,FALSE)),"") -> 15177470000000
A13: GAZP | B13: =A13&" "& "IV" &" кв. "&C13 -> GAZP IV кв. 2014 | C13: 2014 | D13: =SUMIFS(Дивиденды!$C:$C,Дивиденды!$A:$A,A13,Дивиденды!$I:$I,C13) -> 7.2 | E13: =IFERROR(IF(VLOOKUP($B13,Показатели!$E:$W,2,FALSE)=0,"",VLOOKUP($B13,Показатели!$E:$W,2,FALSE)),"") -> 1038191000000 | F13: =IFERROR(IF(VLOOKUP($B13,Показатели!$E:$W,3,FALSE)=0,"",VLOOKUP($B13,Показатели!$E:$W,3,FALSE)),"") -> 3461155000000 | G13: =IFERROR(IF(VLOOKUP($B13,Показатели!$E:$W,4,FALSE)=0,"",VLOOKUP($B13,Показатели!$E:$W,4,FALSE)),"") -> 9950209000000 | H13: =IFERROR(IF(VLOOKUP($B13,Показатели!$E:$W,5,FALSE)=0,"",VLOOKUP($B13,Показатели!$E:$W,5,FALSE)),"") | I13: =IFERROR(IF(VLOOKUP($B13,Показатели!$E:$W,6,FALSE)=0,"",VLOOKUP($B13,Показатели!$E:$W,6,FALSE)),"") -> 15177470000000 | J13: =IFERROR(IF(VLOOKUP($B13,Показатели!$E:$W,7,FALSE)=0,"",VLOOKUP($B13,Показатели!$E:$W,7,FALSE)),"") -> 1855947000000 | K13: =IFERROR(IF(VLOOKUP($B13,Показатели!$E:$W,8,FALSE)=0,"",VLOOKUP($B13,Показатели!$E:$W,8,FALSE)),"") -> 3201502000000 | L13: =IFERROR(IF(VLOOKUP($B13,Показатели!$E:$W,9,FALSE)=0,"",VLOOKUP($B13,Показатели!$E:$W,9,FALSE)),"") -> 9595283000000 | M13: =IFERROR(IF(VLOOKUP($B13,Показатели!$E:$W,10,FALSE)=0,"",VLOOKUP($B13,Показатели!$E:$W,10,FALSE)),"") -> 10120021000000 | N13: =IFERROR(IF(VLOOKUP($B13,Показатели!$E:$W,11,FALSE)=0,"",VLOOKUP($B13,Показатели!$E:$W,11,FALSE)),"") -> 5589811000000 | O13: =IFERROR(IF(VLOOKUP($B13,Показатели!$E:$W,12,FALSE)=0,"",VLOOKUP($B13,Показатели!$E:$W,12,FALSE)),"") -> 1310424000000 | P13: =IFERROR(IF(VLOOKUP($B13,Показатели!$E:$W,13,FALSE)=0,"",VLOOKUP($B13,Показатели!$E:$W,13,FALSE)),"") -> 306823000000 | Q13: =IFERROR(IF(VLOOKUP($B13,Показатели!$E:$W,14,FALSE)=0,"",VLOOKUP($B13,Показатели!$E:$W,14,FALSE)),"") -> 157192000000 | R13: =IFERROR(IF(VLOOKUP($B13,Показатели!$E:$W,15,FALSE)=0,"",VLOOKUP($B13,Показатели!$E:$W,15,FALSE)),"") | S13: =IFERROR(IF(VLOOKUP($B13,Показатели!$E:$W,16,FALSE)=0,"",VLOOKUP($B13,Показатели!$E:$W,16,FALSE)),"") -> 1962558000000 | T13: =IFERROR(IF(VLOOKUP($B13,Показатели!$E:$W,17,FALSE)=0,"",VLOOKUP($B13,Показатели!$E:$W,17,FALSE)),"") -> 1262140000000 | U13: =IFERROR(IF(VLOOKUP($B13,Показатели!$E:$W,18,FALSE)=0,"",VLOOKUP($B13,Показатели!$E:$W,18,FALSE)),"") -> 5249965000000 | V13: =IFERROR(IF(VLOOKUP($B13,Показатели!$E:$W,19,FALSE)=0,"",VLOOKUP($B13,Показатели!$E:$W,19,FALSE)),"") -> 13436236000000
... A1073: SMLT | B1073: =A1073&" "& "IV" &" кв. "&C1073 -> SMLT IV кв. 2010 | C1073: 2010 | D1073: =SUMIFS(Дивиденды!$C:$C,Дивиденды!$A:$A,A1073,Дивиденды!$I:$I,C1073) -> 0 | E1073: =IFERROR(IF(VLOOKUP($B1073,Показатели!$E:$W,2,FALSE)=0,"",VLOOKUP($B1073,Показатели!$E:$W,2,FALSE)),"") | F1073: =IFERROR(IF(VLOOKUP($B1073,Показатели!$E:$W,3,FALSE)=0,"",VLOOKUP($B1073,Показатели!$E:$W,3,FALSE)),"") | G1073: =IFERROR(IF(VLOOKUP($B1073,Показатели!$E:$W,4,FALSE)=0,"",VLOOKUP($B1073,Показатели!$E:$W,4,FALSE)),"") | H1073: =IFERROR(IF(VLOOKUP($B1073,Показатели!$E:$W,5,FALSE)=0,"",VLOOKUP($B1073,Показатели!$E:$W,5,FALSE)),"") | I1073: =IFERROR(IF(VLOOKUP($B1073,Показатели!$E:$W,6,FALSE)=0,"",VLOOKUP($B1073,Показатели!$E:$W,6,FALSE)),"") | J1073: =IFERROR(IF(VLOOKUP($B1073,Показатели!$E:$W,7,FALSE)=0,"",VLOOKUP($B1073,Показатели!$E:$W,7,FALSE)),"") | K1073: =IFERROR(IF(VLOOKUP($B1073,Показатели!$E:$W,8,FALSE)=0,"",VLOOKUP($B1073,Показатели!$E:$W,8,FALSE)),"") | L1073: =IFERROR(IF(VLOOKUP($B1073,Показатели!$E:$W,9,FALSE)=0,"",VLOOKUP($B1073,Показатели!$E:$W,9,FALSE)),"") | M1073: =IFERROR(IF(VLOOKUP($B1073,Показатели!$E:$W,10,FALSE)=0,"",VLOOKUP($B1073,Показатели!$E:$W,10,FALSE)),"") | N1073: =IFERROR(IF(VLOOKUP($B1073,Показатели!$E:$W,11,FALSE)=0,"",VLOOKUP($B1073,Показатели!$E:$W,11,FALSE)),"") | O1073: =IFERROR(IF(VLOOKUP($B1073,Показатели!$E:$W,12,FALSE)=0,"",VLOOKUP($B1073,Показатели!$E:$W,12,FALSE)),"") | P1073: =IFERROR(IF(VLOOKUP($B1073,Показатели!$E:$W,13,FALSE)=0,"",VLOOKUP($B1073,Показатели!$E:$W,13,FALSE)),"") | Q1073: =IFERROR(IF(VLOOKUP($B1073,Показатели!$E:$W,14,FALSE)=0,"",VLOOKUP($B1073,Показатели!$E:$W,14,FALSE)),"") | R1073: =IFERROR(IF(VLOOKUP($B1073,Показатели!$E:$W,15,FALSE)=0,"",VLOOKUP($B1073,Показатели!$E:$W,15,FALSE)),"") | S1073: =IFERROR(IF(VLOOKUP($B1073,Показатели!$E:$W,16,FALSE)=0,"",VLOOKUP($B1073,Показатели!$E:$W,16,FALSE)),"") | T1073: =IFERROR(IF(VLOOKUP($B1073,Показатели!$E:$W,17,FALSE)=0,"",VLOOKUP($B1073,Показатели!$E:$W,17,FALSE)),"") | U1073: =IFERROR(IF(VLOOKUP($B1073,Показатели!$E:$W,18,FALSE)=0,"",VLOOKUP($B1073,Показатели!$E:$W,18,FALSE)),"") | V1073: =IFERROR(IF(VLOOKUP($B1073,Показатели!$E:$W,19,FALSE)=0,"",VLOOKUP($B1073,Показатели!$E:$W,19,FALSE)),"")

Sheet Показатели
C1: Объем | D1: Валюта | E1: Наименование | F1: Денежные средства и их эквиваленты | G1: Итого оборотные активы | H1: Основные средства | I1: Нематериальные активы | J1: Активы | K1: Итого краткосрочные обязательства | L1: Итого долгосрочные обязательства | M1: Нераспределенная прибыль | N1: Капитал | O1: Выручка | P1: Операционная прибыль | Q1: Прибыль до налогообложения | R1: Чистая прибыль (убыток) | S1: Износ, истощение и амортизация | T1: EBITDA | U1: Капитальные затраты | V1: Выручка предыдущ периода | W1: Активы предыдущ периода
A2: =IF(D2="USD",VLOOKUP(VALUE(RIGHT(E2,4)),'USD RUB'!$E:$F,2,FALSE),1) -> 1 | B2: 1 | C2: 1000000 | D2: RUB | E2: GAZP III кв. 2025 | F2: 675617000000 | G2: 3732336000000 | H2: 21827376000000 | I2: 138420000000 | J2: 31455796000000 | K2: 4660456000000 | L2: 8101409000000 | M2: 16877948000000 | N2: 18693931000000 | O2: 7165136000000 | P2: 1093572000000 | Q2: 1678701000000 | R2: 1182594000000 | S2: 1075645000000 | U2: -1725508000000 | V2: =_xlfn.XLOOKUP(LEFT(E2,LEN(E2)-4)&(VALUE(RIGHT(E2,4))-1),$E:$E,$O:$O,"") -> 7499593000000 | W2: =_xlfn.XLOOKUP(LEFT(E2,LEN(E2)-4)&(VALUE(RIGHT(E2,4))-1),$E:$E,$J:$J,"") -> 30118258000000
A3: =IF(D3="USD",VLOOKUP(VALUE(RIGHT(E3,4)),'USD RUB'!$E:$F,2,FALSE),1) -> 1 | B3: 1 | C3: 1000000 | D3: RUB | E3: GAZP II кв. 2025 | F3: 537263000000 | G3: 3420375000000 | H3: 21263738000000 | I3: 138420000000 | J3: 30580217000000 | K3: 4373772000000 | L3: 7581502000000 | M3: 16618900000000 | N3: 18624943000000 | O3: 4989693000000 | P3: 823999000000 | Q3: 1448399000000 | R3: 1034473000000 | S3: 710276000000 | T3: 1547000000000 | U3: -1194700000000 | V3: =_xlfn.XLOOKUP(LEFT(E3,LEN(E3)-4)&(VALUE(RIGHT(E3,4))-1),$E:$E,$O:$O,"") -> 5088055000000 | W3: =_xlfn.XLOOKUP(LEFT(E3,LEN(E3)-4)&(VALUE(RIGHT(E3,4))-1),$E:$E,$J:$J,"") -> 29270926000000
A4: =IF(D4="USD",VLOOKUP(VALUE(RIGHT(E4,4)),'USD RUB'!$E:$F,2,FALSE),1) -> 1 | B4: 1 | C4: 1000000 | D4: RUB | E4: GAZP I кв. 2025 | F4: 896830000000 | G4: 3905551000000 | H4: 20868892000000 | I4: 138420000000 | J4: 30497901000000 | K4: 4646179000000 | L4: 7491160000000 | M4: 16364119000000 | N4: 18360562000000 | O4: 2808692000000 | P4: 479604000000 | Q4: 988095000000 | R4: 694400000000 | S4: 352420000000 | T4: 844000000000 | U4: -690245000000 | V4: =_xlfn.XLOOKUP(LEFT(E4,LEN(E4)-4)&(VALUE(RIGHT(E4,4))-1),$E:$E,$O:$O,"") -> 2778865000000 | W4: =_xlfn.XLOOKUP(LEFT(E4,LEN(E4)-4)&(VALUE(RIGHT(E4,4))-1),$E:$E,$J:$J,"") -> 0
A5: =IF(D5="USD",VLOOKUP(VALUE(RIGHT(E5,4)),'USD RUB'!$E:$F,2,FALSE),1) -> 1 | B5: 1 | C5: 1000000 | D5: RUB | E5: GAZP IV кв. 2024 | F5: 991889000000 | G5: 4368456000000 | H5: 20779950000000 | I5: 138420000000 | J5: 30698255000000 | K5: 4971895000000 | L5: 8065398000000 | M5: 15628372000000 | N5: 17660962000000 | O5: 10714686000000 | P5: 1456390000000 | Q5: 1662936000000 | R5: 1318710000000 | S5: 1377774000000 | T5: 3107875000000 | U5: -2353789000000 | V5: =_xlfn.XLOOKUP(LEFT(E5,LEN(E5)-4)&(VALUE(RIGHT(E5,4))-1),$E:$E,$O:$O,"") -> 8541818000000 | W5: =_xlfn.XLOOKUP(LEFT(E5,LEN(E5)-4)&(VALUE(RIGHT(E5,4))-1),$E:$E,$J:$J,"") -> 28713748000000
A6: =IF(D6="USD",VLOOKUP(VALUE(RIGHT(E6,4)),'USD RUB'!$E:$F,2,FALSE),1) -> 1 | B6: 1 | C6: 1000000 | D6: RUB | E6: GAZP III кв. 2024 | F6: 933331000000 | G6: 4251488000000 | H6: 20164139000000 | I6: 138835000000 | J6: 30118258000000 | K6: 4073811000000 | L6: 8543618000000 | M6: 15504215000000 | N6: 17500829000000 | O6: 7499593000000 | P6: 1420359000000 | Q6: 1540589000000 | R6: 1057747000000 | S6: 835933000000 | T6: 2141000000000 | U6: -1644693000000 | V6: =_xlfn.XLOOKUP(LEFT(E6,LEN(E6)-4)&(VALUE(RIGHT(E6,4))-1),$E:$E,$O:$O,"") -> 6233540000000 | W6: =_xlfn.XLOOKUP(LEFT(E6,LEN(E6)-4)&(VALUE(RIGHT(E6,4))-1),$E:$E,$J:$J,"") -> 0
A7: =IF(D7="USD",VLOOKUP(VALUE(RIGHT(E7,4)),'USD RUB'!$E:$F,2,FALSE),1) -> 1 | B7: 1 | C7: 1000000 | D7: RUB | E7: GAZP II кв. 2024 | F7: 669228000000 | G7: 4354199000000 | H7: 19564253000000 | I7: 138835000000 | J7: 29270926000000 | K7: 3928456000000 | L7: 7770719000000 | M7: 15617937000000 | N7: 17571751000000 | O7: 5088055000000 | P7: 1020154000000 | Q7: 1253911000000 | R7: 1095966000000 | S7: 558647000000 | T7: 1459000000000 | U7: -1057888000000 | V7: =_xlfn.XLOOKUP(LEFT(E7,LEN(E7)-4)&(VALUE(RIGHT(E7,4))-1),$E:$E,$O:$O,"") -> 4114280000000 | W7: =_xlfn.XLOOKUP(LEFT(E7,LEN(E7)-4)&(VALUE(RIGHT(E7,4))-1),$E:$E,$J:$J,"") -> 27501540000000
A8: =IF(D8="USD",VLOOKUP(VALUE(RIGHT(E8,4)),'USD RUB'!$E:$F,2,FALSE),1) -> 1 | B8: 1 | C8: 1000000 | D8: RUB | E8: GAZP I кв. 2024 | O8: 2778865000000 | P8: 627436000000 | Q8: 722454000000 | R8: 677375000000 | S8: 273154000000 | T8: 909000000000 | U8: -518874000000 | V8: =_xlfn.XLOOKUP(LEFT(E8,LEN(E8)-4)&(VALUE(RIGHT(E8,4))-1),$E:$E,$O:$O,"") | W8: =_xlfn.XLOOKUP(LEFT(E8,LEN(E8)-4)&(VALUE(RIGHT(E8,4))-1),$E:$E,$J:$J,"")
A9: =IF(D9="USD",VLOOKUP(VALUE(RIGHT(E9,4)),'USD RUB'!$E:$F,2,FALSE),1) -> 1 | B9: 1 | C9: 1000000 | D9: RUB | E9: GAZP IV кв. 2023 | F9: 1426780000000 | G9: 4780869000000 | H9: 18436207000000 | I9: 147273000000 | J9: 28713748000000 | K9: 4531986000000 | L9: 7729048000000 | M9: 14591946000000 | N9: 16452714000000 | O9: 8541818000000 | P9: -363689000000 | Q9: -659070000000 | R9: -583076000000 | S9: 982058000000 | T9: 1764554000000 | U9: -2422017000000 | V9: =_xlfn.XLOOKUP(LEFT(E9,LEN(E9)-4)&(VALUE(RIGHT(E9,4))-1),$E:$E,$O:$O,"") -> 11673950000000 | W9: =_xlfn.XLOOKUP(LEFT(E9,LEN(E9)-4)&(VALUE(RIGHT(E9,4))-1),$E:$E,$J:$J,"") -> 26128929000000
A10: =IF(D10="USD",VLOOKUP(VALUE(RIGHT(E10,4)),'USD RUB'!$E:$F,2,FALSE),1) -> 1 | B10: 1 | C10: 1000000 | D10: RUB | E10: GAZP III кв. 2023 | O10: 6233540000000 | P10: 1001608000000 | Q10: 470179000000 | R10: 410250000000 | S10: 707063000000 | U10: -1766218000000 | V10: =_xlfn.XLOOKUP(LEFT(E10,LEN(E10)-4)&(VALUE(RIGHT(E10,4))-1),$E:$E,$O:$O,"") | W10: =_xlfn.XLOOKUP(LEFT(E10,LEN(E10)-4)&(VALUE(RIGHT(E10,4))-1),$E:$E,$J:$J,"")
A11: =IF(D11="USD",VLOOKUP(VALUE(RIGHT(E11,4)),'USD RUB'!$E:$F,2,FALSE),1) -> 1 | B11: 1 | C11: 1000000 | D11: RUB | E11: GAZP II кв. 2023 | F11: 683574000000 | G11: 4134258000000 | H11: 18346111000000 | I11: 130602000000 | J11: 27501540000000 | K11: 3148033000000 | L11: 7451932000000 | N11: 16901575000000 | O11: 4114280000000 | P11: 744777000000 | Q11: 360608000000 | R11: 330996000000 | S11: 462848000000 | T11: 1228000000000 | U11: -1188000000000 | V11: =_xlfn.XLOOKUP(LEFT(E11,LEN(E11)-4)&(VALUE(RIGHT(E11,4))-1),$E:$E,$O:$O,"") | W11: =_xlfn.XLOOKUP(LEFT(E11,LEN(E11)-4)&(VALUE(RIGHT(E11,4))-1),$E:$E,$J:$J,"")
A12: =IF(D12="USD",VLOOKUP(VALUE(RIGHT(E12,4)),'USD RUB'!$E:$F,2,FALSE),1) -> 1 | B12: 1 | C12: 1000000 | D12: RUB | E12: GAZP IV кв. 2022 | F12: 1157587000000 | G12: 4620117000000 | H12: 17419060000000 | I12: 130585000000 | J12: 26128929000000 | K12: 2900860000000 | L12: 6782224000000 | M12: 15126010000000 | N12: 16445845000000 | O12: 11673950000000 | P12: 1935159000000 | Q12: 2190558000000 | R12: 1311645000000 | S12: 862380000000 | T12: 3637555000000 | U12: -2191642000000 | V12: =_xlfn.XLOOKUP(LEFT(E12,LEN(E12)-4)&(VALUE(RIGHT(E12,4))-1),$E:$E,$O:$O,"") -> 10241353000000 | W12: =_xlfn.XLOOKUP(LEFT(E12,LEN(E12)-4)&(VALUE(RIGHT(E12,4))-1),$E:$E,$J:$J,"") -> 27047230000000
A13: =IF(D13="USD",VLOOKUP(VALUE(RIGHT(E13,4)),'USD RUB'!$E:$F,2,FALSE),1) -> 1 | B13: 1 | C13: 1000000 | D13: RUB | E13: GAZP IV кв. 2021 | F13: 2013923000000 | G13: 6214283000000 | H13: 16673568000000 | I13: 120768000000 | J13: 27047230000000 | K13: 4022945000000 | L13: 6157706000000 | M13: 15613466000000 | N13: 16866579000000 | O13: 10241353000000 | P13: 2411261000000 | Q13: 2769514000000 | R13: 2159086000000 | S13: 828027000000 | T13: 3686890000000 | U13: -1933766000000 | V13: =_xlfn.XLOOKUP(LEFT(E13,LEN(E13)-4)&(VALUE(RIGHT(E13,4))-1),$E:$E,$O:$O,"") -> 6321559000000 | W13: =_xlfn.XLOOKUP(LEFT(E13,LEN(E13)-4)&(VALUE(RIGHT(E13,4))-1),$E:$E,$J:$J,"") -> 23352185000000
A14: =IF(D14="USD",VLOOKUP(VALUE(RIGHT(E14,4)),'USD RUB'!$E:$F,2,FALSE),1) -> 1 | B14: 1 | C14: 1000000 | D14: RUB | E14: GAZP III кв. 2021 | F14: 1307630000000 | G14: 5247814000000 | H14: 16552055000000 | I14: 120668000000 | J14: 26012278000000 | K14: 3669488000000 | L14: 6002616000000 | M14: 15121009000000 | N14: 16340174000000 | O14: 6725132000000 | P14: 1589217000000 | Q14: 1946480000000 | R14: 1579938000000 | S14: 619993000000 | T14: 2213614000000 | U14: -1293894000000 | V14: =_xlfn.XLOOKUP(LEFT(E14,LEN(E14)-4)&(VALUE(RIGHT(E14,4))-1),$E:$E,$O:$O,"") -> 4301218000000 | W14: =_xlfn.XLOOKUP(LEFT(E14,LEN(E14)-4)&(VALUE(RIGHT(E14,4))-1),$E:$E,$J:$J,"") -> 22460133000000
A15: =IF(D15="USD",VLOOKUP(VALUE(RIGHT(E15,4)),'USD RUB'!$E:$F,2,FALSE),1) -> 1 | B15: 1 | C15: 1000000 | D15: RUB | E15: GAZP II кв. 2021 | F15: 1411790000000 | G15: 4411770000000 | H15: 16305814000000 | I15: 120949000000 | J15: 24624250000000 | K15: 2966366000000 | L15: 6025111000000 | M15: 14483314000000 | N15: 15632773000000 | O15: 4351968000000 | P15: 986598000000 | Q15: 1241226000000 | R15: 995521000000 | S15: 413843000000 | T15: 1403981000000 | U15: -831440000000 | V15: =_xlfn.XLOOKUP(LEFT(E15,LEN(E15)-4)&(VALUE(RIGHT(E15,4))-1),$E:$E,$O:$O,"") -> 2903148000000 | W15: =_xlfn.XLOOKUP(LEFT(E15,LEN(E15)-4)&(VALUE(RIGHT(E15,4))-1),$E:$E,$J:$J,"") -> 22059001000000
A16: =IF(D16="USD",VLOOKUP(VALUE(RIGHT(E16,4)),'USD RUB'!$E:$F,2,FALSE),1) -> 1 | B16: 1 | C16: 1000000 | D16: RUB | E16: GAZP I кв. 2021 | F16: 1271783000000 | G16: 4083210000000 | H16: 16148208000000 | I16: 121208000000 | J16: 24020955000000 | K16: 2513817000000 | L16: 6099450000000 | M16: 14304146000000 | N16: 15407688000000 | O16: 2285161000000 | P16: 490193000000 | Q16: 573486000000 | R16: 465614000000 | S16: 207670000000 | T16: 700596000000 | U16: -414783000000 | V16: =_xlfn.XLOOKUP(LEFT(E16,LEN(E16)-4)&(VALUE(RIGHT(E16,4))-1),$E:$E,$O:$O,"") -> 1739832000000 | W16: =_xlfn.XLOOKUP(LEFT(E16,LEN(E16)-4)&(VALUE(RIGHT(E16,4))-1),$E:$E,$J:$J,"") -> 22479468000000
A17: =IF(D17="USD",VLOOKUP(VALUE(RIGHT(E17,4)),'USD RUB'!$E:$F,2,FALSE),1) -> 1 | B17: 1 | C17: 1000000 | D17: RUB | E17: GAZP IV кв. 2020 | F17: 1034919000000 | G17: 3774289000000 | H17: 16103095000000 | I17: 119854000000 | J17: 23352185000000 | K17: 2626964000000 | L17: 5920489000000 | M17: 13717464000000 | N17: 14804732000000 | O17: 6321559000000 | P17: 614851000000 | Q17: 133469000000 | R17: 162407000000 | S17: 798436000000 | T17: 1466541000000 | U17: -1522565000000 | V17: =_xlfn.XLOOKUP(LEFT(E17,LEN(E17)-4)&(VALUE(RIGHT(E17,4))-1),$E:$E,$O:$O,"") -> 7659623000000 | W17: =_xlfn.XLOOKUP(LEFT(E17,LEN(E17)-4)&(VALUE(RIGHT(E17,4))-1),$E:$E,$J:$J,"") -> 21882348000000
A18: =IF(D18="USD",VLOOKUP(VALUE(RIGHT(E18,4)),'USD RUB'!$E:$F,2,FALSE),1) -> 1 | B18: 1 | C18: 1000000 | D18: RUB | E18: GAZP III кв. 2020 | F18: 498740000000 | G18: 3157758000000 | H18: 15771007000000 | I18: 133589000000 | J18: 22460133000000 | K18: 2251279000000 | L18: 5871308000000 | M18: 13469895000000 | N18: 14337546000000 | O18: 4301218000000 | P18: 325152000000 | Q18: -327023000000 | R18: -202207000000 | S18: 594635000000 | T18: 935000000000 | U18: -1089456000000 | V18: =_xlfn.XLOOKUP(LEFT(E18,LEN(E18)-4)&(VALUE(RIGHT(E18,4))-1),$E:$E,$O:$O,"") -> 5698339000000 | W18: =_xlfn.XLOOKUP(LEFT(E18,LEN(E18)-4)&(VALUE(RIGHT(E18,4))-1),$E:$E,$J:$J,"") -> 21384390000000
A19: =IF(D19="USD",VLOOKUP(VALUE(RIGHT(E19,4)),'USD RUB'!$E:$F,2,FALSE),1) -> 1 | B19: 1 | C19: 1000000 | D19: RUB | E19: GAZP II кв. 2020 | F19: 738836000000 | G19: 3511030000000 | H19: 15259745000000 | I19: 130995000000 | J19: 22059001000000 | K19: 2367514000000 | L19: 5381914000000 | M19: 13461589000000 | N19: 14309573000000 | O19: 2903148000000 | P19: 189985000000 | Q19: -16806000000 | R19: 45460000000 | S19: 396891000000 | T19: 601000000000 | U19: -720196000000 | V19: =_xlfn.XLOOKUP(LEFT(E19,LEN(E19)-4)&(VALUE(RIGHT(E19,4))-1),$E:$E,$O:$O,"") -> 4076751000000 | W19: =_xlfn.XLOOKUP(LEFT(E19,LEN(E19)-4)&(VALUE(RIGHT(E19,4))-1),$E:$E,$J:$J,"") -> 21282648000000
A20: =IF(D20="USD",VLOOKUP(VALUE(RIGHT(E20,4)),'USD RUB'!$E:$F,2,FALSE),1) -> 1 | B20: 1 | C20: 1000000 | D20: RUB | E20: GAZP I кв. 2020 | F20: 772924000000 | G20: 3802641000000 | H20: 15357259000000 | I20: 132609000000 | J20: 22479468000000 | K20: 2349965000000 | L20: 5441798000000 | M20: 13822007000000 | N20: 14687705000000 | O20: 1739832000000 | P20: 293459000000 | Q20: -208720000000 | R20: -108082000000 | S20: 199564000000 | T20: 507000000000 | U20: -419458000000 | V20: =_xlfn.XLOOKUP(LEFT(E20,LEN(E20)-4)&(VALUE(RIGHT(E20,4))-1),$E:$E,$O:$O,"") -> 2291821000000 | W20: =_xlfn.XLOOKUP(LEFT(E20,LEN(E20)-4)&(VALUE(RIGHT(E20,4))-1),$E:$E,$J:$J,"") -> 21234741000000
A21: =IF(D21="USD",VLOOKUP(VALUE(RIGHT(E21,4)),'USD RUB'!$E:$F,2,FALSE),1) -> 1 | B21: 1 | C21: 1000000 | D21: RUB | E21: GAZP IV кв. 2019 | F21: 696057000000 | G21: 3828153000000 | H21: 14856448000000 | I21: 130028000000 | J21: 21882348000000 | K21: 2527476000000 | L21: 4739185000000 | M21: 13779970000000 | N21: 14615687000000 | O21: 7659623000000 | P21: 1119857000000 | Q21: 1627065000000 | R21: 1269517000000 | S21: 715229000000 | T21: 1859679000000 | U21: -1775923000000 | V21: =_xlfn.XLOOKUP(LEFT(E21,LEN(E21)-4)&(VALUE(RIGHT(E21,4))-1),$E:$E,$O:$O,"") -> 8224177000000 | W21: =_xlfn.XLOOKUP(LEFT(E21,LEN(E21)-4)&(VALUE(RIGHT(E21,4))-1),$E:$E,$J:$J,"") -> 20810440000000
A22: =IF(D22="USD",VLOOKUP(VALUE(RIGHT(E22,4)),'USD RUB'!$E:$F,2,FALSE),1) -> 1 | B22: 1 | C22: 1000000 | D22: RUB | E22: GAZP III кв. 2019 | F22: 960597000000 | G22: 3697370000000 | H22: 14308754000000 | I22: 107442000000 | J22: 21384390000000 | K22: 2114021000000 | L22: 4842643000000 | M22: 13720954000000 | N22: 14427726000000 | O22: 5698339000000 | P22: 972631000000 | Q22: 1399454000000 | R22: 1106948000000 | S22: 525044000000 | T22: 371000000000 | U22: -1224735000000 | V22: =_xlfn.XLOOKUP(LEFT(E22,LEN(E22)-4)&(VALUE(RIGHT(E22,4))-1),$E:$E,$O:$O,"") -> 5901591000000 | W22: =_xlfn.XLOOKUP(LEFT(E22,LEN(E22)-4)&(VALUE(RIGHT(E22,4))-1),$E:$E,$J:$J,"") -> 19935162000000
A23: =IF(D23="USD",VLOOKUP(VALUE(RIGHT(E23,4)),'USD RUB'!$E:$F,2,FALSE),1) -> 1 | B23: 1 | C23: 1000000 | D23: RUB | E23: GAZP II кв. 2019 | F23: 1153970000000 | G23: 3961800000000 | H23: 14008873000000 | I23: 107596000000 | J23: 21282648000000 | K23: 2447455000000 | L23: 4752433000000 | M23: 13496359000000 | N23: 14082760000000 | O23: 4076751000000 | P23: 780878000000 | Q23: 1125278000000 | R23: 878644000000 | S23: 347875000000 | T23: 497000000000 | U23: -788381000000 | V23: =_xlfn.XLOOKUP(LEFT(E23,LEN(E23)-4)&(VALUE(RIGHT(E23,4))-1),$E:$E,$O:$O,"") -> 3971555000000 | W23: =_xlfn.XLOOKUP(LEFT(E23,LEN(E23)-4)&(VALUE(RIGHT(E23,4))-1),$E:$E,$J:$J,"") -> 19120236000000
... A32: =IF(D32="USD",VLOOKUP(VALUE(RIGHT(E32,4)),'USD RUB'!$E:$F,2,FALSE),1) -> 1 | B32: 1 | C32: 1000000 | D32: RUB | E32: GAZP I кв. 2017 | F32: 686746000000 | G32: 3224056000000 | H32: 11539885000000 | I32: 103419000000 | J32: 16808867000000 | K32: 1644045000000 | L32: 3520182000000 | M32: 11196415000000 | N32: 11644640000000 | O32: 1815301000000 | P32: 294003000000 | Q32: 454048000000 | R32: 350387000000 | S32: 149694000000 | T32: 450000000000 | U32: -321487000000 | V32: =_xlfn.XLOOKUP(LEFT(E32,LEN(E32)-4)&(VALUE(RIGHT(E32,4))-1),$E:$E,$O:$O,"") -> 1737364000000 | W32: =_xlfn.XLOOKUP(LEFT(E32,LEN(E32)-4)&(VALUE(RIGHT(E32,4))-1),$E:$E,$J:$J,"") -> 17148311000000
A33: =IF(D33="USD",VLOOKUP(VALUE(RIGHT(E33,4)),'USD RUB'!$E:$F,2,FALSE),1) -> 1 | B33: 1 | C33: 1000000 | D33: RUB | E33: GAZP IV кв. 2016 | F33: 896728000000 | G33: 3234346000000 | H33: 11502747000000 | J33: 16918938000000 | K33: 1921808000000 | L33: 3555291000000 | M33: 11005256000000 | N33: 11441839000000 | O33: 6111051000000 | P33: 725580000000 | Q33: 1285138000000 | R33: 997104000000 | T33: 1322000000000 | U33: 1369000000000 | V33: =_xlfn.XLOOKUP(LEFT(E33,LEN(E33)-4)&(VALUE(RIGHT(E33,4))-1),$E:$E,$O:$O,"") -> 6073318000000 | W33: =_xlfn.XLOOKUP(LEFT(E33,LEN(E33)-4)&(VALUE(RIGHT(E33,4))-1),$E:$E,$J:$J,"") -> 17052040000000
A34: =IF(D34="USD",VLOOKUP(VALUE(RIGHT(E34,4)),'USD RUB'!$E:$F,2,FALSE),1) -> 1 | B34: 1 | C34: 1000000 | D34: RUB | E34: GAZP III кв. 2016 | F34: 787627000000 | G34: 3073814000000 | H34: 11311016000000 | J34: 16668492000000 | K34: 1758763000000 | L34: 3795556000000 | M34: 10682371000000 | N34: 11114173000000 | O34: 4321364000000 | P34: 567820000000 | Q34: 941690000000 | R34: 737391000000 | U34: 1069326000000 | V34: =_xlfn.XLOOKUP(LEFT(E34,LEN(E34)-4)&(VALUE(RIGHT(E34,4))-1),$E:$E,$O:$O,"") -> 4206217000000 | W34: =_xlfn.XLOOKUP(LEFT(E34,LEN(E34)-4)&(VALUE(RIGHT(E34,4))-1),$E:$E,$J:$J,"") -> 16377825000000
A35: =IF(D35="USD",VLOOKUP(VALUE(RIGHT(E35,4)),'USD RUB'!$E:$F,2,FALSE),1) -> 1 | B35: 1 | C35: 1000000 | D35: RUB | E35: GAZP II кв. 2016 | F35: 1321632000000 | G35: 3556165000000 | H35: 11141372000000 | J35: 16903001000000 | K35: 1914084000000 | L35: 3842502000000 | M35: 10592760000000 | N35: 11146415000000 | O35: 3064372000000 | P35: 413169000000 | Q35: 780837000000 | R35: 625405000000 | T35: 693000000000 | U35: 723518000000 | V35: =_xlfn.XLOOKUP(LEFT(E35,LEN(E35)-4)&(VALUE(RIGHT(E35,4))-1),$E:$E,$O:$O,"") -> 2913452000000 | W35: =_xlfn.XLOOKUP(LEFT(E35,LEN(E35)-4)&(VALUE(RIGHT(E35,4))-1),$E:$E,$J:$J,"") -> 15357226000000
A36: =IF(D36="USD",VLOOKUP(VALUE(RIGHT(E36,4)),'USD RUB'!$E:$F,2,FALSE),1) -> 1 | B36: 1 | C36: 1000000 | D36: RUB | E36: GAZP I кв. 2016 | F36: 1564565000000 | G36: 3990806000000 | H36: 11078191000000 | J36: 17148311000000 | K36: 1983081000000 | L36: 3976316000000 | M36: 10633491000000 | N36: 11188914000000 | O36: 1737364000000 | P36: 301973000000 | Q36: 481960000000 | R36: 373341000000 | T36: 444000000000 | U36: 436932000000 | V36: =_xlfn.XLOOKUP(LEFT(E36,LEN(E36)-4)&(VALUE(RIGHT(E36,4))-1),$E:$E,$O:$O,"") -> 1648253000000 | W36: =_xlfn.XLOOKUP(LEFT(E36,LEN(E36)-4)&(VALUE(RIGHT(E36,4))-1),$E:$E,$J:$J,"") -> 15384163000000
A37: =IF(D37="USD",VLOOKUP(VALUE(RIGHT(E37,4)),'USD RUB'!$E:$F,2,FALSE),1) -> 1 | B37: 1 | C37: 1000000 | D37: RUB | E37: GAZP IV кв. 2015 | F37: 1359095000000 | G37: 3993722000000 | H37: 11003881000000 | J37: 17052040000000 | K37: 2124701000000 | L37: 4012717000000 | M37: 10368311000000 | N37: 10914622000000 | O37: 6073318000000 | P37: 1228301000000 | Q37: 925241000000 | R37: 805199000000 | T37: 1875000000000 | U37: 1641024000000 | V37: =_xlfn.XLOOKUP(LEFT(E37,LEN(E37)-4)&(VALUE(RIGHT(E37,4))-1),$E:$E,$O:$O,"") -> 5589811000000 | W37: =_xlfn.XLOOKUP(LEFT(E37,LEN(E37)-4)&(VALUE(RIGHT(E37,4))-1),$E:$E,$J:$J,"") -> 15177470000000
A38: =IF(D38="USD",VLOOKUP(VALUE(RIGHT(E38,4)),'USD RUB'!$E:$F,2,FALSE),1) -> 1 | B38: 1 | C38: 1000000 | D38: RUB | E38: GAZP III кв. 2015 | F38: 1125162000000 | G38: 3636475000000 | H38: 10543280000000 | J38: 16377825000000 | K38: 1989627000000 | L38: 3599084000000 | M38: 10245454000000 | N38: 10789114000000 | O38: 4206217000000 | Q38: 864837000000 | R38: 690271000000 | U38: 1165551000000 | V38: =_xlfn.XLOOKUP(LEFT(E38,LEN(E38)-4)&(VALUE(RIGHT(E38,4))-1),$E:$E,$O:$O,"") -> 4007522000000 | W38: =_xlfn.XLOOKUP(LEFT(E38,LEN(E38)-4)&(VALUE(RIGHT(E38,4))-1),$E:$E,$J:$J,"") -> 14052124000000
A39: =IF(D39="USD",VLOOKUP(VALUE(RIGHT(E39,4)),'USD RUB'!$E:$F,2,FALSE),1) -> 1 | B39: 1 | C39: 1000000 | D39: RUB | E39: GAZP II кв. 2015 | F39: 104568000000 | G39: 3267971000000 | H39: 10143082000000 | J39: 15357226000000 | K39: 1755220000000 | L39: 3084567000000 | M39: 9987023000000 | N39: 10517439000000 | O39: 2913452000000 | Q39: 857010000000 | R39: 691256000000 | T39: 933000000000 | U39: 784905000000 | V39: =_xlfn.XLOOKUP(LEFT(E39,LEN(E39)-4)&(VALUE(RIGHT(E39,4))-1),$E:$E,$O:$O,"") -> 2873932000000 | W39: =_xlfn.XLOOKUP(LEFT(E39,LEN(E39)-4)&(VALUE(RIGHT(E39,4))-1),$E:$E,$J:$J,"") -> 13772801000000
A40: =IF(D40="USD",VLOOKUP(VALUE(RIGHT(E40,4)),'USD RUB'!$E:$F,2,FALSE),1) -> 1 | B40: 1 | C40: 1000000 | D40: RUB | E40: GAZP I кв. 2015 | F40: 1228145000000 | G40: 3534303000000 | H40: 10016497000000 | J40: 15384163000000 | K40: 1753366000000 | L40: 3178629000000 | M40: 9923481000000 | N40: 10452168000000 | O40: 1648253000000 | Q40: 496094000000 | R40: 389618000000 | T40: 583000000000 | U40: 444280000000 | V40: =_xlfn.XLOOKUP(LEFT(E40,LEN(E40)-4)&(VALUE(RIGHT(E40,4))-1),$E:$E,$O:$O,"") -> 1558737000000 | W40: =_xlfn.XLOOKUP(LEFT(E40,LEN(E40)-4)&(VALUE(RIGHT(E40,4))-1),$E:$E,$J:$J,"") -> 13737342000000
A41: =IF(D41="USD",VLOOKUP(VALUE(RIGHT(E41,4)),'USD RUB'!$E:$F,2,FALSE),1) -> 1 | B41: 1 | C41: 1000000 | D41: RUB | E41: GAZP IV кв. 2014 | F41: 1038191000000 | G41: 3461155000000 | H41: 9950209000000 | J41: 15177470000000 | K41: 1855947000000 | L41: 3201502000000 | M41: 9595283000000 | N41: 10120021000000 | O41: 5589811000000 | P41: 1310424000000 | Q41: 306823000000 | R41: 157192000000 | T41: 1962558000000 | U41: 1262140000000 | V41: =_xlfn.XLOOKUP(LEFT(E41,LEN(E41)-4)&(VALUE(RIGHT(E41,4))-1),$E:$E,$O:$O,"") -> 5249965000000 | W41: =_xlfn.XLOOKUP(LEFT(E41,LEN(E41)-4)&(VALUE(RIGHT(E41,4))-1),$E:$E,$J:$J,"") -> 13436236000000
A42: =IF(D42="USD",VLOOKUP(VALUE(RIGHT(E42,4)),'USD RUB'!$E:$F,2,FALSE),1) -> 1 | B42: 1 | C42: 1000000 | D42: RUB | E42: GAZP III кв. 2014 | F42: 753767000000 | G42: 2956248000000 | H42: 9424849000000 | J42: 14052124000000 | K42: 1319099000000 | L42: 2678668000000 | M42: 9524171000000 | N42: 10054357000000 | O42: 4007522000000 | P42: 998601000000 | Q42: 756859000000 | R42: 572654000000 | U42: 930005000000 | V42: =_xlfn.XLOOKUP(LEFT(E42,LEN(E42)-4)&(VALUE(RIGHT(E42,4))-1),$E:$E,$O:$O,"") -> 3772668000000 | W42: =_xlfn.XLOOKUP(LEFT(E42,LEN(E42)-4)&(VALUE(RIGHT(E42,4))-1),$E:$E,$J:$J,"") -> 12865916000000
A43: =IF(D43="USD",VLOOKUP(VALUE(RIGHT(E43,4)),'USD RUB'!$E:$F,2,FALSE),1) -> 1 | B43: 1 | C43: 1000000 | D43: RUB | E43: GAZP II кв. 2014 | F43: 943882000000 | G43: 2908530000000 | H43: 9177778000000 | J43: 13772801000000 | K43: 1325123000000 | L43: 2541904000000 | M43: 9368324000000 | N43: 9905774000000 | O43: 2873932000000 | P43: 639650000000 | Q43: 634564000000 | R43: 465226000000 | T43: 872000000000 | U43: 620690000000 | V43: =_xlfn.XLOOKUP(LEFT(E43,LEN(E43)-4)&(VALUE(RIGHT(E43,4))-1),$E:$E,$O:$O,"") -> 2568122000000 | W43: =_xlfn.XLOOKUP(LEFT(E43,LEN(E43)-4)&(VALUE(RIGHT(E43,4))-1),$E:$E,$J:$J,"") -> 12555820000000
A44: =IF(D44="USD",VLOOKUP(VALUE(RIGHT(E44,4)),'USD RUB'!$E:$F,2,FALSE),1) -> 1 | B44: 1 | C44: 1000000 | D44: RUB | E44: GAZP I кв. 2014 | F44: 956738000000 | G44: 3032620000000 | H44: 9078237000000 | J44: 13737342000000 | K44: 1200464000000 | L44: 2640065000000 | M44: 9352103000000 | N44: 9896813000000 | O44: 1558737000000 | P44: 472790000000 | Q44: 317950000000 | R44: 231664000000 | T44: 591000000000 | U44: 398557000000 | V44: =_xlfn.XLOOKUP(LEFT(E44,LEN(E44)-4)&(VALUE(RIGHT(E44,4))-1),$E:$E,$O:$O,"") -> 1461441000000 | W44: =_xlfn.XLOOKUP(LEFT(E44,LEN(E44)-4)&(VALUE(RIGHT(E44,4))-1),$E:$E,$J:$J,"") -> 12214858000000
A45: =IF(D45="USD",VLOOKUP(VALUE(RIGHT(E45,4)),'USD RUB'!$E:$F,2,FALSE),1) -> 1 | B45: 1 | C45: 1000000 | D45: RUB | E45: GAZP IV кв. 2013 | F45: 689130000000 | G45: 2862670000000 | H45: 8940088000000 | J45: 13436236000000 | K45: 1391465000000 | L45: 2410417000000 | M45: =9098315*C45 -> 9098315000000 | N45: 9634354000000 | O45: 5249965000000 | Q45: 1486083000000 | R45: 1165705000000 | T45: 2009000000000 | V45: =_xlfn.XLOOKUP(LEFT(E45,LEN(E45)-4)&(VALUE(RIGHT(E45,4))-1),$E:$E,$O:$O,"") -> 4764411000000 | W45: =_xlfn.XLOOKUP(LEFT(E45,LEN(E45)-4)&(VALUE(RIGHT(E45,4))-1),$E:$E,$J:$J,"") -> 12068139000000
A46: =IF(D46="USD",VLOOKUP(VALUE(RIGHT(E46,4)),'USD RUB'!$E:$F,2,FALSE),1) -> 1 | B46: 1 | C46: 1000000 | D46: RUB | E46: GAZP III кв. 2013 | F46: 570774000000 | G46: 2622571000000 | H46: 8559165000000 | J46: 12865916000000 | K46: 1244984000000 | L46: 2286299000000 | N46: 9334633000000 | O46: 3772668000000 | P46: 1182900000000 | Q46: 1096976000000 | R46: 876331000000 | V46: =_xlfn.XLOOKUP(LEFT(E46,LEN(E46)-4)&(VALUE(RIGHT(E46,4))-1),$E:$E,$O:$O,"") -> 3351303000000 | W46: =_xlfn.XLOOKUP(LEFT(E46,LEN(E46)-4)&(VALUE(RIGHT(E46,4))-1),$E:$E,$J:$J,"") -> 11619410000000
A47: =IF(D47="USD",VLOOKUP(VALUE(RIGHT(E47,4)),'USD RUB'!$E:$F,2,FALSE),1) -> 1 | B47: 1 | C47: 1000000 | D47: RUB | E47: GAZP II кв. 2013 | F47: 713201000000 | G47: 2682676000000 | H47: 8221881000000 | J47: 12555820000000 | K47: 1275282000000 | L47: 2227426000000 | N47: 9053112000000 | O47: 2568122000000 | P47: 853002000000 | Q47: 741844000000 | R47: 593405000000 | T47: 1065000000000 | V47: =_xlfn.XLOOKUP(LEFT(E47,LEN(E47)-4)&(VALUE(RIGHT(E47,4))-1),$E:$E,$O:$O,"") -> 2230366000000 | W47: =_xlfn.XLOOKUP(LEFT(E47,LEN(E47)-4)&(VALUE(RIGHT(E47,4))-1),$E:$E,$J:$J,"") -> 11412977000000
A48: =IF(D48="USD",VLOOKUP(VALUE(RIGHT(E48,4)),'USD RUB'!$E:$F,2,FALSE),1) -> 1 | B48: 1 | C48: 1000000 | D48: RUB | E48: GAZP I кв. 2013 | F48: 572890000000 | G48: 2590874000000 | H48: 8018433000000 | J48: 12214858000000 | K48: 1190630000000 | L48: 2157839000000 | N48: 8866389000000 | O48: 1461441000000 | P48: 515981000000 | Q48: 489919000000 | R48: 388152000000 | T48: 626000000000 | V48: =_xlfn.XLOOKUP(LEFT(E48,LEN(E48)-4)&(VALUE(RIGHT(E48,4))-1),$E:$E,$O:$O,"") -> 1224878000000 | W48: =_xlfn.XLOOKUP(LEFT(E48,LEN(E48)-4)&(VALUE(RIGHT(E48,4))-1),$E:$E,$J:$J,"") -> 11105990000000
A49: =IF(D49="USD",VLOOKUP(VALUE(RIGHT(E49,4)),'USD RUB'!$E:$F,2,FALSE),1) -> 1 | B49: 1 | C49: 1000000 | D49: RUB | E49: GAZP IV кв. 2012 | F49: 423194000000 | G49: 2408746000000 | H49: 7818392000000 | J49: 12068139000000 | K49: 1489817000000 | L49: 1877228000000 | M49: 8170631000000 | N49: 8701094000000 | O49: 4764411000000 | P49: 1289176000000 | Q49: 1511955000000 | R49: 1210566000000 | U49: -1339878000000 | V49: =_xlfn.XLOOKUP(LEFT(E49,LEN(E49)-4)&(VALUE(RIGHT(E49,4))-1),$E:$E,$O:$O,"") -> 4637090000000 | W49: =_xlfn.XLOOKUP(LEFT(E49,LEN(E49)-4)&(VALUE(RIGHT(E49,4))-1),$E:$E,$J:$J,"") -> 10900696000000
A50: =IF(D50="USD",VLOOKUP(VALUE(RIGHT(E50,4)),'USD RUB'!$E:$F,2,FALSE),1) -> 1 | B50: 1 | C50: 1000000 | D50: RUB | E50: GAZP III кв. 2012 | F50: 475152000000 | G50: 2336291000000 | H50: 7323898000000 | J50: 11619410000000 | K50: 1394153000000 | L50: 1894660000000 | M50: 7798312000000 | N50: 8330597000000 | O50: 3351303000000 | P50: 865368000000 | Q50: 1040217000000 | R50: 833125000000 | U50: -956529000000 | V50: =_xlfn.XLOOKUP(LEFT(E50,LEN(E50)-4)&(VALUE(RIGHT(E50,4))-1),$E:$E,$O:$O,"") -> 3296656000000 | W50: =_xlfn.XLOOKUP(LEFT(E50,LEN(E50)-4)&(VALUE(RIGHT(E50,4))-1),$E:$E,$J:$J,"") -> 10069310000000
A51: =IF(D51="USD",VLOOKUP(VALUE(RIGHT(E51,4)),'USD RUB'!$E:$F,2,FALSE),1) -> 1 | B51: 1 | C51: 1000000 | D51: RUB | E51: GAZP II кв. 2012 | F51: 512809000000 | G51: 2395939000000 | H51: 7088061000000 | J51: 11412977000000 | K51: 1553704000000 | L51: 1807783000000 | N51: 8051490000000 | O51: 2230366000000 | P51: 612133000000 | Q51: 655074000000 | R51: 525526000000 | V51: =_xlfn.XLOOKUP(LEFT(E51,LEN(E51)-4)&(VALUE(RIGHT(E51,4))-1),$E:$E,$O:$O,"") -> 2347071000000 | W51: =_xlfn.XLOOKUP(LEFT(E51,LEN(E51)-4)&(VALUE(RIGHT(E51,4))-1),$E:$E,$J:$J,"") -> 9732710000000
A52: =IF(D52="USD",VLOOKUP(VALUE(RIGHT(E52,4)),'USD RUB'!$E:$F,2,FALSE),1) -> 1 | B52: 1 | C52: 1000000 | D52: RUB | E52: GAZP I кв. 2012 | F52: 685768000000 | G52: 2335649000000 | H52: 6816962000000 | J52: 11105990000000 | K52: 1363235000000 | L52: 1654639000000 | N52: 8088116000000 | O52: 1224878000000 | P52: 298967000000 | Q52: 456297000000 | R52: 367615000000 | T52: 378000000000 | V52: =_xlfn.XLOOKUP(LEFT(E52,LEN(E52)-4)&(VALUE(RIGHT(E52,4))-1),$E:$E,$O:$O,"") -> 1316747000000 | W52: =_xlfn.XLOOKUP(LEFT(E52,LEN(E52)-4)&(VALUE(RIGHT(E52,4))-1),$E:$E,$J:$J,"") -> 9508009000000
A53: =IF(D53="USD",VLOOKUP(VALUE(RIGHT(E53,4)),'USD RUB'!$E:$F,2,FALSE),1) -> 1 | B53: 1 | C53: 1000000 | D53: RUB | E53: GAZP IV кв. 2011 | F53: 501344000000 | G53: 2240293000000 | H53: 6718575000000 | J53: 10900696000000 | K53: 1309255000000 | L53: 1830450000000 | M53: =7242982*C53 -> 7242982000000 | N53: 7760991000000 | O53: 4637090000000 | P53: 1656843000000 | Q53: 1679936000000 | R53: 1342442000000 | T53: 1930533000000 | V53: =_xlfn.XLOOKUP(LEFT(E53,LEN(E53)-4)&(VALUE(RIGHT(E53,4))-1),$E:$E,$O:$O,"") -> 3597054000000 | W53: =_xlfn.XLOOKUP(LEFT(E53,LEN(E53)-4)&(VALUE(RIGHT(E53,4))-1),$E:$E,$J:$J,"") -> 9235993000000
A54: =IF(D54="USD",VLOOKUP(VALUE(RIGHT(E54,4)),'USD RUB'!$E:$F,2,FALSE),1) -> 1 | B54: 1 | C54: 1000000 | D54: RUB | E54: GAZP III кв. 2011 | F54: 381748000000 | G54: 2002313000000 | H54: 6046053000000 | J54: 10069310000000 | K54: 954577000000 | L54: 1756314000000 | N54: 7358419000000 | O54: 3296656000000 | P54: 1176530000000 | Q54: 1173839000000 | R54: 940827000000 | T54: 1377000000000 | V54: =_xlfn.XLOOKUP(LEFT(E54,LEN(E54)-4)&(VALUE(RIGHT(E54,4))-1),$E:$E,$O:$O,"") -> 2507744000000 | W54: =_xlfn.XLOOKUP(LEFT(E54,LEN(E54)-4)&(VALUE(RIGHT(E54,4))-1),$E:$E,$J:$J,"") -> 8688286000000
A55: =IF(D55="USD",VLOOKUP(VALUE(RIGHT(E55,4)),'USD RUB'!$E:$F,2,FALSE),1) -> 1 | B55: 1 | C55: 1000000 | D55: RUB | E55: GAZP II кв. 2011 | F55: 455369000000 | G55: 1931250000000 | H55: 5751955000000 | J55: 9732710000000 | K55: 908825000000 | L55: 1643668000000 | N55: 7180217000000 | O55: 2347071000000 | P55: 848495000000 | Q55: 973982000000 | R55: 785202000000 | V55: =_xlfn.XLOOKUP(LEFT(E55,LEN(E55)-4)&(VALUE(RIGHT(E55,4))-1),$E:$E,$O:$O,"") -> 1721293000000 | W55: =_xlfn.XLOOKUP(LEFT(E55,LEN(E55)-4)&(VALUE(RIGHT(E55,4))-1),$E:$E,$J:$J,"") -> 8516394000000
A56: =IF(D56="USD",VLOOKUP(VALUE(RIGHT(E56,4)),'USD RUB'!$E:$F,2,FALSE),1) -> 1 | B56: 1 | C56: 1000000 | D56: RUB | E56: GAZP I кв. 2011 | F56: 444356000000 | G56: 1915486000000 | H56: 5590829000000 | J56: 9508009000000 | K56: 851757000000 | L56: 1675888000000 | N56: 6980364000000 | O56: 1316747000000 | P56: 498508000000 | Q56: 591066000000 | R56: 478500000000 | V56: =_xlfn.XLOOKUP(LEFT(E56,LEN(E56)-4)&(VALUE(RIGHT(E56,4))-1),$E:$E,$O:$O,"") -> 956816000000 | W56: =_xlfn.XLOOKUP(LEFT(E56,LEN(E56)-4)&(VALUE(RIGHT(E56,4))-1),$E:$E,$J:$J,"") -> 8558242000000
A57: =IF(D57="USD",VLOOKUP(VALUE(RIGHT(E57,4)),'USD RUB'!$E:$F,2,FALSE),1) -> 1 | B57: 1 | C57: 1000000 | D57: RUB | E57: GAZP IV кв. 2010 | F57: 440786000000 | G57: 1865895000000 | H57: 5486429000000 | J57: 9235993000000 | K57: 1011261000000 | L57: 1688371000000 | M57: =6028543*C57 -> 6028543000000 | N57: 6536361000000 | O57: 3597054000000 | P57: 1113822000000 | Q57: 1273703000000 | R57: 997993000000 | T57: 1363778000000 | V57: =_xlfn.XLOOKUP(LEFT(E57,LEN(E57)-4)&(VALUE(RIGHT(E57,4))-1),$E:$E,$O:$O,"") | W57: =_xlfn.XLOOKUP(LEFT(E57,LEN(E57)-4)&(VALUE(RIGHT(E57,4))-1),$E:$E,$J:$J,"")
A58: =IF(D58="USD",VLOOKUP(VALUE(RIGHT(E58,4)),'USD RUB'!$E:$F,2,FALSE),1) -> 1 | B58: 1 | C58: 1000000 | D58: RUB | E58: GAZP III кв. 2010 | F58: 315832000000 | G58: 1624721000000 | H58: 5245555000000 | J58: 8688286000000 | K58: 845130000000 | L58: 1594796000000 | N58: 6248360000000 | O58: 2507744000000 | P58: 774739000000 | Q58: 849938000000 | R58: 668753000000 | V58: =_xlfn.XLOOKUP(LEFT(E58,LEN(E58)-4)&(VALUE(RIGHT(E58,4))-1),$E:$E,$O:$O,"") | W58: =_xlfn.XLOOKUP(LEFT(E58,LEN(E58)-4)&(VALUE(RIGHT(E58,4))-1),$E:$E,$J:$J,"")
A59: =IF(D59="USD",VLOOKUP(VALUE(RIGHT(E59,4)),'USD RUB'!$E:$F,2,FALSE),1) -> 1 | B59: 1 | C59: 1000000 | D59: RUB | E59: GAZP II кв. 2010 | F59: 371178000000 | G59: 1641051000000 | H59: 5114504000000 | J59: 8516394000000 | K59: 885507000000 | L59: 1568532000000 | N59: 6062355000000 | O59: 1721293000000 | P59: 577720000000 | Q59: 640198000000 | R59: 508234000000 | V59: =_xlfn.XLOOKUP(LEFT(E59,LEN(E59)-4)&(VALUE(RIGHT(E59,4))-1),$E:$E,$O:$O,"") | W59: =_xlfn.XLOOKUP(LEFT(E59,LEN(E59)-4)&(VALUE(RIGHT(E59,4))-1),$E:$E,$J:$J,"")
A60: =IF(D60="USD",VLOOKUP(VALUE(RIGHT(E60,4)),'USD RUB'!$E:$F,2,FALSE),1) -> 1 | B60: 1 | C60: 1000000 | D60: RUB | E60: GAZP I кв. 2010 | F60: 398797000000 | G60: 1830417000000 | H60: 4983770000000 | J60: 8558242000000 | K60: 991944000000 | L60: 1589988000000 | N60: 5976310000000 | O60: 956816000000 | P60: 339301000000 | Q60: 421696000000 | R60: 336849000000 | V60: =_xlfn.XLOOKUP(LEFT(E60,LEN(E60)-4)&(VALUE(RIGHT(E60,4))-1),$E:$E,$O:$O,"") | W60: =_xlfn.XLOOKUP(LEFT(E60,LEN(E60)-4)&(VALUE(RIGHT(E60,4))-1),$E:$E,$J:$J,"")
A61: =IF(D61="USD",VLOOKUP(VALUE(RIGHT(E61,4)),'USD RUB'!$E:$F,2,FALSE),1) -> 1 | B61: 1 | C61: 1000000 | D61: RUB | E61: LKOH IV кв. 2025 | F61: 543815000000 | G61: 1128446000000 | H61: 3754828000000 | I61: 93327000000 | J61: 5474421000000 | K61: 1222340000000 | L61: 625628000000 | M61: 4072539000000 | N61: 3626453000000 | O61: 3767768000000 | P61: 526646000000 | Q61: 219317000000 | R61: -1059859000000 | S61: 522714000000 | T61: 892086000000 | U61: -774550000000 | V61: =_xlfn.XLOOKUP(LEFT(E61,LEN(E61)-4)&(VALUE(RIGHT(E61,4))-1),$E:$E,$O:$O,"") -> 8621561000000 | W61: =_xlfn.XLOOKUP(LEFT(E61,LEN(E61)-4)&(VALUE(RIGHT(E61,4))-1),$E:$E,$J:$J,"") -> 9282619000000
A62: =IF(D62="USD",VLOOKUP(VALUE(RIGHT(E62,4)),'USD RUB'!$E:$F,2,FALSE),1) -> 1 | B62: 1 | C62: 1000000 | D62: RUB | E62: LKOH II кв. 2025 | F62: 488247000000 | G62: 2014136000000 | H62: 4930688000000 | I62: 93135000000 | J62: 7750749000000 | K62: 1306038000000 | L62: 829965000000 | M62: 5661221000000 | N62: 5614746000000 | O62: 3601697000000 | P62: 344681000000 | Q62: 414835000000 | R62: 288566000000 | S62: 261559000000 | T62: 606240000000 | U62: -386630000000 | V62: =_xlfn.XLOOKUP(LEFT(E62,LEN(E62)-4)&(VALUE(RIGHT(E62,4))-1),$E:$E,$O:$O,"") -> 4333568000000 | W62: =_xlfn.XLOOKUP(LEFT(E62,LEN(E62)-4)&(VALUE(RIGHT(E62,4))-1),$E:$E,$J:$J,"") -> 8619431000000
A63: =IF(D63="USD",VLOOKUP(VALUE(RIGHT(E63,4)),'USD RUB'!$E:$F,2,FALSE),1) -> 1 | B63: 1 | C63: 1000000 | D63: RUB | E63: LKOH IV кв. 2024 | F63: 1426264000000 | G63: 3309453000000 | H63: 5016584000000 | I63: 94622000000 | J63: 9282619000000 | K63: 1486739000000 | L63: 903872000000 | M63: 5713233000000 | N63: 6892008000000 | O63: 8621561000000 | P63: 1191817000000 | Q63: 1202833000000 | R63: 851546000000 | S63: 593446000000 | T63: 1785263000000 | U63: -779724000000 | V63: =_xlfn.XLOOKUP(LEFT(E63,LEN(E63)-4)&(VALUE(RIGHT(E63,4))-1),$E:$E,$O:$O,"") -> 7928303000000 | W63: =_xlfn.XLOOKUP(LEFT(E63,LEN(E63)-4)&(VALUE(RIGHT(E63,4))-1),$E:$E,$J:$J,"") -> 8600173000000
A64: =IF(D64="USD",VLOOKUP(VALUE(RIGHT(E64,4)),'USD RUB'!$E:$F,2,FALSE),1) -> 1 | B64: 1 | C64: 1000000 | D64: RUB | E64: LKOH II кв. 2024 | F64: 1127498000000 | G64: 3009017000000 | H64: 4722538000000 | I64: 78976000000 | J64: 8619431000000 | K64: 1372259000000 | L64: 747269000000 | M64: 5804291000000 | N64: 6499903000000 | O64: 4333568000000 | P64: 694187000000 | Q64: 714107000000 | R64: 591542000000 | S64: 290607000000 | T64: 984794000000 | U64: -327061000000 | V64: =_xlfn.XLOOKUP(LEFT(E64,LEN(E64)-4)&(VALUE(RIGHT(E64,4))-1),$E:$E,$O:$O,"") -> 3606535000000 | W64: =_xlfn.XLOOKUP(LEFT(E64,LEN(E64)-4)&(VALUE(RIGHT(E64,4))-1),$E:$E,$J:$J,"") -> 7907304000000
A65: =IF(D65="USD",VLOOKUP(VALUE(RIGHT(E65,4)),'USD RUB'!$E:$F,2,FALSE),1) -> 1 | B65: 1 | C65: 1000000 | D65: RUB | E65: LKOH IV кв. 2023 | F65: 1179673000000 | G65: 2994282000000 | H65: 4723002000000 | I65: 77413000000 | J65: 8600173000000 | K65: 1441830000000 | L65: 757110000000 | M65: 5558875000000 | N65: 6401233000000 | O65: 7928303000000 | P65: 1427697000000 | Q65: 1408350000000 | R65: 1160271000000 | S65: 577367000000 | T65: 2005064000000 | V65: =_xlfn.XLOOKUP(LEFT(E65,LEN(E65)-4)&(VALUE(RIGHT(E65,4))-1),$E:$E,$O:$O,"") | W65: =_xlfn.XLOOKUP(LEFT(E65,LEN(E65)-4)&(VALUE(RIGHT(E65,4))-1),$E:$E,$J:$J,"")
A66: =IF(D66="USD",VLOOKUP(VALUE(RIGHT(E66,4)),'USD RUB'!$E:$F,2,FALSE),1) -> 1 | B66: 1 | C66: 1000000 | D66: RUB | E66: LKOH II кв. 2023 | F66: 1020064000000 | G66: 2570430000000 | H66: 4653247000000 | I66: 63196000000 | J66: 7907304000000 | K66: 1122233000000 | L66: 746485000000 | M66: 5280402000000 | N66: 6038586000000 | O66: 3606535000000 | P66: 611801000000 | Q66: 703735000000 | R66: 565441000000 | S66: 258736000000 | T66: 870537000000 | V66: =_xlfn.XLOOKUP(LEFT(E66,LEN(E66)-4)&(VALUE(RIGHT(E66,4))-1),$E:$E,$O:$O,"") | W66: =_xlfn.XLOOKUP(LEFT(E66,LEN(E66)-4)&(VALUE(RIGHT(E66,4))-1),$E:$E,$J:$J,"")
A67: =IF(D67="USD",VLOOKUP(VALUE(RIGHT(E67,4)),'USD RUB'!$E:$F,2,FALSE),1) -> 1 | B67: 1 | C67: 1000000 | D67: RUB | E67: LKOH IV кв. 2021 | F67: 677482000000 | G67: 2149157000000 | H67: 4263130000000 | I67: 44342000000 | J67: 6864749000000 | K67: 1244680000000 | L67: 1096885000000 | M67: 4280226000000 | N67: 4523184000000 | O67: 9435143000000 | P67: 978945000000 | Q67: 966964000000 | R67: 775513000000 | S67: 425466000000 | T67: 1404411000000 | U67: -433042000000 | V67: =_xlfn.XLOOKUP(LEFT(E67,LEN(E67)-4)&(VALUE(RIGHT(E67,4))-1),$E:$E,$O:$O,"") -> 5639401000000 | W67: =_xlfn.XLOOKUP(LEFT(E67,LEN(E67)-4)&(VALUE(RIGHT(E67,4))-1),$E:$E,$J:$J,"") -> 5991579000000
A68: =IF(D68="USD",VLOOKUP(VALUE(RIGHT(E68,4)),'USD RUB'!$E:$F,2,FALSE),1) -> 1 | B68: 1 | C68: 1000000 | D68: RUB | E68: LKOH III кв. 2021 | F68: 627117000000 | G68: 1984556000000 | H68: 4195199000000 | I68: 49794000000 | J68: 6634357000000 | K68: 1188553000000 | L68: 938618000000 | M68: 4273654000000 | N68: 4507186000000 | O68: 6667112000000 | P68: 681767000000 | Q68: 671137000000 | R68: 541482000000 | S68: 327631000000 | T68: 1009398000000 | U68: -305761000000 | V68: =_xlfn.XLOOKUP(LEFT(E68,LEN(E68)-4)&(VALUE(RIGHT(E68,4))-1),$E:$E,$O:$O,"") -> 4109062000000 | W68: =_xlfn.XLOOKUP(LEFT(E68,LEN(E68)-4)&(VALUE(RIGHT(E68,4))-1),$E:$E,$J:$J,"") -> 6195855000000
A69: =IF(D69="USD",VLOOKUP(VALUE(RIGHT(E69,4)),'USD RUB'!$E:$F,2,FALSE),1) -> 1 | B69: 1 | C69: 1000000 | D69: RUB | E69: LKOH II кв. 2021 | F69: 555269000000 | G69: 1838580000000 | H69: 4217399000000 | I69: 50050000000 | J69: 6508931000000 | K69: 1278284000000 | L69: 924909000000 | M69: 4073338000000 | N69: 4305738000000 | O69: 4078367000000 | P69: 433994000000 | Q69: 428969000000 | R69: 348363000000 | S69: 220228000000 | T69: 654222000000 | U69: -211433000000 | V69: =_xlfn.XLOOKUP(LEFT(E69,LEN(E69)-4)&(VALUE(RIGHT(E69,4))-1),$E:$E,$O:$O,"") -> 2652412000000 | W69: =_xlfn.XLOOKUP(LEFT(E69,LEN(E69)-4)&(VALUE(RIGHT(E69,4))-1),$E:$E,$J:$J,"") -> 6002486000000
A70: =IF(D70="USD",VLOOKUP(VALUE(RIGHT(E70,4)),'USD RUB'!$E:$F,2,FALSE),1) -> 1 | B70: 1 | C70: 1000000 | D70: RUB | E70: LKOH I кв. 2021 | F70: 489180000000 | G70: 1651400000000 | H70: 4255270000000 | I70: 50201000000 | J70: 6378319000000 | K70: 1070851000000 | L70: 988019000000 | M70: 4023326000000 | N70: 4319449000000 | O70: 1876483000000 | P70: 200666000000 | Q70: 198979000000 | R70: 157967000000 | S70: 113714000000 | T70: 314380000000 | U70: -107220000000 | V70: =_xlfn.XLOOKUP(LEFT(E70,LEN(E70)-4)&(VALUE(RIGHT(E70,4))-1),$E:$E,$O:$O,"") -> 1665985000000 | W70: =_xlfn.XLOOKUP(LEFT(E70,LEN(E70)-4)&(VALUE(RIGHT(E70,4))-1),$E:$E,$J:$J,"") -> 6127796000000
A71: =IF(D71="USD",VLOOKUP(VALUE(RIGHT(E71,4)),'USD RUB'!$E:$F,2,FALSE),1) -> 1 | B71: 1 | C71: 1000000 | D71: RUB | E71: LKOH IV кв. 2020 | F71: 343832000000 | G71: 1276460000000 | H71: 4264474000000 | I71: 50159000000 | J71: 5991579000000 | K71: 885659000000 | L71: 975154000000 | M71: 3858057000000 | N71: 4130766000000 | O71: 5639401000000 | P71: 281654000000 | Q71: 98787000000 | R71: 16633000000 | S71: 405440000000 | T71: 687094000000 | U71: -495443000000 | V71: =_xlfn.XLOOKUP(LEFT(E71,LEN(E71)-4)&(VALUE(RIGHT(E71,4))-1),$E:$E,$O:$O,"") -> 7841246000000 | W71: =_xlfn.XLOOKUP(LEFT(E71,LEN(E71)-4)&(VALUE(RIGHT(E71,4))-1),$E:$E,$J:$J,"") -> 5947050000000
A72: =IF(D72="USD",VLOOKUP(VALUE(RIGHT(E72,4)),'USD RUB'!$E:$F,2,FALSE),1) -> 1 | B72: 1 | C72: 1000000 | D72: RUB | E72: LKOH III кв. 2020 | F72: 443975000000 | G72: 1442886000000 | H72: 4313143000000 | I72: 48795000000 | J72: 6195855000000 | K72: 951463000000 | L72: 1017769000000 | M72: 3852652000000 | N72: 4226623000000 | O72: 4109062000000 | P72: 182600000000 | Q72: 37969000000 | R72: -13329000000 | S72: 314882000000 | T72: 497482000000 | U72: -360282000000 | V72: =_xlfn.XLOOKUP(LEFT(E72,LEN(E72)-4)&(VALUE(RIGHT(E72,4))-1),$E:$E,$O:$O,"") -> 5928807000000 | W72: =_xlfn.XLOOKUP(LEFT(E72,LEN(E72)-4)&(VALUE(RIGHT(E72,4))-1),$E:$E,$J:$J,"") -> 5848001000000
A73: =IF(D73="USD",VLOOKUP(VALUE(RIGHT(E73,4)),'USD RUB'!$E:$F,2,FALSE),1) -> 1 | B73: 1 | C73: 1000000 | D73: RUB | E73: LKOH II кв. 2020 | F73: 616207000000 | G73: 1475130000000 | H73: 4145254000000 | I73: 45017000000 | J73: 6002486000000 | K73: 1105217000000 | L73: 934821000000 | M73: 3794391000000 | N73: 3962448000000 | O73: 2652412000000 | P73: 83816000000 | Q73: -28199000000 | R73: -64241000000 | S73: 211443000000 | T73: 295259000000 | U73: -247456000000 | V73: =_xlfn.XLOOKUP(LEFT(E73,LEN(E73)-4)&(VALUE(RIGHT(E73,4))-1),$E:$E,$O:$O,"") -> 3976485000000 | W73: =_xlfn.XLOOKUP(LEFT(E73,LEN(E73)-4)&(VALUE(RIGHT(E73,4))-1),$E:$E,$J:$J,"") -> 5898378000000
A74: =IF(D74="USD",VLOOKUP(VALUE(RIGHT(E74,4)),'USD RUB'!$E:$F,2,FALSE),1) -> 1 | B74: 1 | C74: 1000000 | D74: RUB | E74: LKOH I кв. 2020 | F74: 500653000000 | G74: 1452164000000 | H74: 4258283000000 | I74: 46550000000 | J74: 6127796000000 | K74: 883170000000 | L74: 877029000000 | M74: 4047772000000 | N74: 4367597000000 | O74: 1665985000000 | P74: 40125000000 | Q74: -22406000000 | R74: -45784000000 | S74: 110718000000 | T74: 150843000000 | U74: -130211000000 | V74: =_xlfn.XLOOKUP(LEFT(E74,LEN(E74)-4)&(VALUE(RIGHT(E74,4))-1),$E:$E,$O:$O,"") -> 1850933000000 | W74: =_xlfn.XLOOKUP(LEFT(E74,LEN(E74)-4)&(VALUE(RIGHT(E74,4))-1),$E:$E,$J:$J,"") -> 5823274000000
A75: =IF(D75="USD",VLOOKUP(VALUE(RIGHT(E75,4)),'USD RUB'!$E:$F,2,FALSE),1) -> 1 | B75: 1 | C75: 1000000 | D75: RUB | E75: LKOH IV кв. 2019 | F75: 516032000000 | G75: 1554187000000 | H75: 4026007000000 | I75: 43108000000 | J75: 5947050000000 | K75: 1207677000000 | L75: 765924000000 | M75: 4203138000000 | N75: 3973449000000 | O75: 7841246000000 | P75: 821098000000 | Q75: 793354000000 | R75: 642221000000 | S75: 415094000000 | T75: 1236200000000 | U75: -449975000000 | V75: =_xlfn.XLOOKUP(LEFT(E75,LEN(E75)-4)&(VALUE(RIGHT(E75,4))-1),$E:$E,$O:$O,"") -> 8035889000000 | W75: =_xlfn.XLOOKUP(LEFT(E75,LEN(E75)-4)&(VALUE(RIGHT(E75,4))-1),$E:$E,$J:$J,"") -> 5732382000000
A76: =IF(D76="USD",VLOOKUP(VALUE(RIGHT(E76,4)),'USD RUB'!$E:$F,2,FALSE),1) -> 1 | B76: 1 | C76: 1000000 | D76: RUB | E76: LKOH III кв. 2019 | F76: 447168000000 | G76: 1484617000000 | H76: 3977151000000 | I76: 39682000000 | J76: 5848001000000 | K76: 874674000000 | L76: 823218000000 | M76: 4209090000000 | N76: 4150109000000 | O76: 5928807000000 | P76: 643968000000 | Q76: 643082000000 | R76: 522478000000 | S76: 314064000000 | T76: 958032000000 | U76: -314038000000 | V76: =_xlfn.XLOOKUP(LEFT(E76,LEN(E76)-4)&(VALUE(RIGHT(E76,4))-1),$E:$E,$O:$O,"") -> 5992672000000 | W76: =_xlfn.XLOOKUP(LEFT(E76,LEN(E76)-4)&(VALUE(RIGHT(E76,4))-1),$E:$E,$J:$J,"") -> 5713550000000
A77: =IF(D77="USD",VLOOKUP(VALUE(RIGHT(E77,4)),'USD RUB'!$E:$F,2,FALSE),1) -> 1 | B77: 1 | C77: 1000000 | D77: RUB | E77: LKOH II кв. 2019 | F77: 506116000000 | G77: 1586417000000 | H77: 398119000000 | I77: 39704000000 | J77: 5898378000000 | K77: 1197008000000 | L77: 826418000000 | M77: 4199220000000 | N77: 3874952000000 | O77: 3976485000000 | P77: 420667000000 | Q77: 416314000000 | R77: 331591000000 | S77: 209560000000 | T77: 630227000000 | U77: -204976000000 | V77: =_xlfn.XLOOKUP(LEFT(E77,LEN(E77)-4)&(VALUE(RIGHT(E77,4))-1),$E:$E,$O:$O,"") -> 2056058000000 | W77: =_xlfn.XLOOKUP(LEFT(E77,LEN(E77)-4)&(VALUE(RIGHT(E77,4))-1),$E:$E,$J:$J,"") -> 5492067000000
A78: =IF(D78="USD",VLOOKUP(VALUE(RIGHT(E78,4)),'USD RUB'!$E:$F,2,FALSE),1) -> 1 | B78: 1 | C78: 1000000 | D78: RUB | E78: LKOH I кв. 2019 | F78: 444494000000 | G78: 1498146000000 | H78: 3921362000000 | I78: 40311000000 | J78: 5823274000000 | K78: 924205000000 | L78: 842285000000 | M78: 4120706000000 | N78: 4056784000000 | O78: 1850933000000 | P78: 194227000000 | Q78: 192586000000 | R78: 149790000000 | S78: 103830000000 | T78: 298057000000 | U78: -97421000000 | V78: =_xlfn.XLOOKUP(LEFT(E78,LEN(E78)-4)&(VALUE(RIGHT(E78,4))-1),$E:$E,$O:$O,"") -> 1630728000000 | W78: =_xlfn.XLOOKUP(LEFT(E78,LEN(E78)-4)&(VALUE(RIGHT(E78,4))-1),$E:$E,$J:$J,"") -> 5205186000000
... A86: =IF(D86="USD",VLOOKUP(VALUE(RIGHT(E86,4)),'USD RUB'!$E:$F,2,FALSE),1) -> 1 | B86: 1 | C86: 1000000 | D86: RUB | E86: LKOH I кв. 2017 | F86: 19641000000 | G86: 1088461000000 | H86: 3377943000000 | I86: 41110000000 | J86: 4813959000000 | K86: 647115000000 | L86: 895338000000 | M86: 3365132000000 | N86: 3271506000000 | O86: 1431599000000 | P86: 126871000000 | Q86: 78449000000 | R86: 62684000000 | S86: 80774000000 | T86: 207600000000 | U86: 130200000000 | V86: =_xlfn.XLOOKUP(LEFT(E86,LEN(E86)-4)&(VALUE(RIGHT(E86,4))-1),$E:$E,$O:$O,"") -> 1177674000000 | W86: =_xlfn.XLOOKUP(LEFT(E86,LEN(E86)-4)&(VALUE(RIGHT(E86,4))-1),$E:$E,$J:$J,"") -> 4982254000000
A87: =IF(D87="USD",VLOOKUP(VALUE(RIGHT(E87,4)),'USD RUB'!$E:$F,2,FALSE),1) -> 1 | B87: 1 | C87: 1000000 | D87: RUB | E87: LKOH IV кв. 2016 | F87: 261367000000 | G87: 1255641000000 | H87: 3391366000000 | J87: 5014673000000 | K87: 830686000000 | L87: 956323000000 | M87: 3302855000000 | N87: 3227664000000 | O87: 5227045000000 | P87: 419143000000 | Q87: 272515000000 | R87: 207642000000 | T87: 731000000000 | U87: 497130000000 | V87: =_xlfn.XLOOKUP(LEFT(E87,LEN(E87)-4)&(VALUE(RIGHT(E87,4))-1),$E:$E,$O:$O,"") -> 5749050000000 | W87: =_xlfn.XLOOKUP(LEFT(E87,LEN(E87)-4)&(VALUE(RIGHT(E87,4))-1),$E:$E,$J:$J,"") -> 5020607000000
A88: =IF(D88="USD",VLOOKUP(VALUE(RIGHT(E88,4)),'USD RUB'!$E:$F,2,FALSE),1) -> 1 | B88: 1 | C88: 1000000 | D88: RUB | E88: LKOH III кв. 2016 | F88: 345175000000 | G88: 1173823000000 | H88: 3413480000000 | J88: 4972564000000 | K88: 685216000000 | L88: 1016705000000 | M88: 3309726000000 | N88: 3270643000000 | O88: 3826121000000 | P88: 316707000000 | Q88: 211179000000 | R88: 160767000000 | T88: 547453000000 | U88: 357392000000 | V88: =_xlfn.XLOOKUP(LEFT(E88,LEN(E88)-4)&(VALUE(RIGHT(E88,4))-1),$E:$E,$O:$O,"") -> 4.5761224e+12 | W88: =_xlfn.XLOOKUP(LEFT(E88,LEN(E88)-4)&(VALUE(RIGHT(E88,4))-1),$E:$E,$J:$J,"") -> 6.6503593e+12
A89: =IF(D89="USD",VLOOKUP(VALUE(RIGHT(E89,4)),'USD RUB'!$E:$F,2,FALSE),1) -> 1 | B89: 1 | C89: 1000000 | D89: RUB | E89: LKOH II кв. 2016 | F89: 346703000000 | G89: 1284902000000 | H89: 3380811000000 | J89: 5046471000000 | K89: 798656000000 | L89: 1030571000000 | M89: 3254923000000 | N89: 3217244000000 | O89: 2516633000000 | P89: 225607000000 | Q89: 135387000000 | R89: 105392000000 | T89: 381563000000 | U89: 248664000000 | V89: =_xlfn.XLOOKUP(LEFT(E89,LEN(E89)-4)&(VALUE(RIGHT(E89,4))-1),$E:$E,$O:$O,"") -> 3.141766e+12 | W89: =_xlfn.XLOOKUP(LEFT(E89,LEN(E89)-4)&(VALUE(RIGHT(E89,4))-1),$E:$E,$J:$J,"") -> 6.8201448e+12
